Workbook

Sheet Base Data
A1: Expiry | D1: 18NovFut | G1: 18DecFut | H1: 19JanFut
A2: Initial Portfolio Size (Rs.) | D2: 100000
A3: Initial Max. Risk per Trade % | D3: 0.105
A4: Current P&L (Rs.) | F4: Link this cell to the current P&L
A5: Current Portfolio Size (Rs.) | D5: =D2+D4 -> 100000
A6: Current Max. Risk per Trade % | D6: =IF((D5>=100%*D2),D3,IF(AND((D5>=90%*D2),(D5<100%*D2)),C23,IF(AND((D5>=80%*D2),(D5<90%*D2)),D23,IF(AND((D5>=70%*D2),(D5<80%*D2)),E23,IF(AND((D5>=60%*D2),(D5<70%*D2)),F23,IF(AND((D5>=50%*D2),(D5<60%*D2)),G23,IF(AND((D5>=40%*D2),(D5<50%*D2)),H23,IF(AND((D5>=30%*D2),(D5<40%*D2)),I23,IF(AND((D5>=20%*D2),(D5<30%*D2)),J23,IF(AND((D5>=10%*D2),(D5<20%*D2)),K23,IF((D5<=10%*D2),L23,"Check"))))))))))) -> 0.105
A7: Max. Risk per Trade (Rs.) [Unit] | D7: =D5*D6 -> 10500
A8: Avg. No. of Trades | D8: =D5/D7 -> 9.5238095
A9: % Reduction in Risk | D9: 0.1
A10: ATR Multiple for SL & TP (Positional) | D10: 2
A11: Max. Positions per Scrip for Pyramiding (Positional) | D11: 5
A12: ATR Multiple for Pyramiding (Positional) | D12: 0.4
A13: ATR Multiple for SL & TP (Intraday) | D13: 0.75
A14: ORB - Points Above / Below Entry Criteria | D14: 0.05
A15: Trend Finder - MFI Up / Down Value | D15: 50 | E15: 50
A16: MFI Max. / Min. Alert Breach Level | D16: 2 | E16: 2
A17: Gann Angle - Trade Type (IntraDay = 0 / Positional = 1) | D17: 0
A18: Gann Angle - Trade Holding Period (Positional Trades) | D18: 10
A19: Gann Angle - Market Stabilisation Period | D19: =DATE(YEAR(NOW()),MONTH(NOW()),DAY(NOW()))+TIME(9,15,0) -> 45769.385 | E19: 0.39583333
A20: Gann Angle - Current Time | D20: =NOW() -> 45769.773
A22: DrawDown % | C22: 90-100% | D22: 80-90% | E22: 70-80% | F22: 60-70% | G22: 50-60% | H22: 40-50% | I22: 30-40% | J22: 20-30% | K22: 10-20% | L22: 0-10%
A23: Max. Risk per Trade % | C23: =D3 -> 0.105 | D23: =C23*(100%-$D$9) -> 0.0945 | E23: =D23*(100%-$D$9) -> 0.08505 | F23: =E23*(100%-$D$9) -> 0.076545 | G23: =F23*(100%-$D$9) -> 0.0688905 | H23: =G23*(100%-$D$9) -> 0.06200145 | I23: =H23*(100%-$D$9) -> 0.055801305 | J23: =I23*(100%-$D$9) -> 0.050221175 | K23: =J23*(100%-$D$9) -> 0.045199057 | L23: =K23*(100%-$D$9) -> 0.040679151
A25: Charges | C25: Brokerage | D25: Turnover | E25: Service Tax | F25: Edu. Cess | G25: H. Edu. Cess | H25: SEBI | I25: Stamp | J25: STT | K25: Slippage
A26: % of Turnover | C26: 0.0002 | D26: 2.1e-05 | E26: 0.14 | F26: 0.005 | G26: 0.005 | H26: - | I26: 2e-05 | J26: 0.0001 | K26: 0.0004
A27: Rate per Transaction (Rs.) | C27: 20 | D27: - | E27: - | F27: - | G27: - | H27: =20/10000000 -> 2e-06 | I27: - | J27: -
A79: Trade Type
A80: 0 | B80: IntraDay
A81: 1 | B81: Positional

Sheet All Columns
B1: =[1]NOW!$C$6 -> 9345 | C1: =[1]NOW!$E$6 -> 28.3 | D1: =NOW() -> 45769.773 | F1: Positional | G1: Positional | H1: IntraDay | BN1: Gap Up/Dn | CJ1: MFI Crossover [Price should be above 55 VW SMA Open for Long & vice versa] | CQ1: Price SMA Crossover [Price should be above 55 VW SMA Open for Long & vice versa] | DG1: Positional (MFI Crossover & SMA Crossover Strategies) | DR1: IntraDay (ORB, Gap Up/Dn & O=H/O=L Strategies) | EM1: ORB | EO1: ORB
A2: Sr. No. | B2: Scrip | C2: Current Market Price | D2: LTP - Curr. Open | E2: LTP - Prev. Close | F2: RSI Cross Decision to Trade | G2: SMA Cross Decision to Trade | H2: IntraDay Recommendation | I2: Basic Reco. | J2: Gap Up / Dn | K2: Gap Zone | L2: Gap Zone Reco. (Fade / GA) | M2: O=H & O=L | N2: Prev. Day's High/Low Break-Out | O2: IntraDay Trend (Impulse System) | P2: IntraDay Trend (Tom Demark Method) | Q2: IntraDay Trend (Modified Pivot) | R2: IAV Status | S2: No. of Lots (I) | T2: IntraDay Strength / Weakness of Market | U2: IntraDay Strength / Weakness of Market | V2: IntraDay Rank (Strong) | W2: IntraDay Rank (Weak) | X2: IntraDay Trend (Choppy Market Index) | Y2: IntraDay Trend (Buy/Sell Easier Day) | Z2: VW Avg. True Range % (21) | AA2: VW Avg. True Range % (8) | AB2: Positional Strength / Weakness of Market | AC2: Positional Rank (Strong) | AD2: Positional Rank (Weak) | AE2: Positional Trend (LTP & 13 VW EMA Open with 5 VW EMA HLC Avg. %Diff.) | AF2: Positional Trend [VW MACD Hist., MFI(14) & SMA MFI(14)] | AG2: Volume Status | AH2: No. of Lots (P) | AI2: Enter Buy / Sell Price | AJ2: Enter Strategy Type | AK2: Points | AL2: Net Profit / Loss (Post Charges) | AM2: %Returns (Post Charges) | AN2: Rank | AO2: Approx. Margin Utilised | AP2: Transaction Value | AQ2: Brokerage | AR2: Turnover Charges | AS2: Service Tax (incl. Cess) | AT2: SEBI Charges | AU2: Stamp Duty Charges | AV2: STT | AW2: Slippage | AX2: Total Charges | AY2: Gross Profit / Loss (Pre Charges) | AZ2: In Market | BA2: Scrip with Expiry | BB2: Best Buy Rate | BC2: Last Traded Price | BD2: Best Sell Rate | BE2: Qty | BF2: Approx. Margin Required Per Lot | BG2: Open | BH2: High | BI2: Low | BJ2: Prev. Open | BK2: Prev. High | BL2: Prev. Low | BM2: Prev. Close | BN2: Gap Size | BO2: Gap Size (%) | BP2: Beta with Nifty (21 D) | BQ2: Volume | BR2: Volume (21 Day SMA) | BS2: IAV | BT2: IAV (21 Day SMA) | BU2: VM SMA (Open) [55 Day] (Curr.) | BV2: VM EMA (Open) [13 Day] (Curr.) | BW2: VM EMA (Open) [13 Day] (Prev.) | BX2: VM EMA (HLC Average) [5 Day] (Curr.) | BY2: VM EMA (HLC Average) [5 Day] (Prev.) | BZ2: % Diff. [LTP & 5 VM EMA HLC Average] (Curr.) | CA2: % Diff. [P. Close & 5 VM EMA HLC Average] (Prev.) | CB2: VW MACD Hist. [HLC Avg.] (Curr.) | CC2: VW MACD Hist. [HLC Avg.] (Prev.) | CD2: VW MACD Hist. [HLC Avg.] (Prev.-1) | CE2: MFI (14) [HLC Avg.] (Curr.) | CF2: MFI (14) [HLC Avg.] (Prev.) | CG2: MFI (14) [HLC Avg.] (Prev.-1) | CH2: MFI (14) Max. Breach Level | CI2: MFI (14) Min. Breach Level | CJ2: SMA [34 Day - MFI(14)] [HLC Avg.] (Curr.) | CK2: SMA [34 Day - MFI(14)] [HLC Avg.] (Prev.) | CL2: SMA [34 Day - MFI(14)] [HLC Avg.] (Prev.-1) | CM2: SMA [21 Day - MFI(14)] [HLC Avg.] (Curr.) | CN2: SMA [21 Day - MFI(14)] [HLC Avg.] (Prev.) | CO2: Entry [MFI(14) & SMA MFI(14) Crossover] | CP2: Exit [MFI(14) & SMA MFI(14) Crossover] | CQ2: VW SMA [34 Day Open] (Curr.) | CR2: VW SMA [34 Day Open] (Prev.) | CS2: VW SMA [13 Day Low] (Curr.) | CT2: VW SMA [13 Day Low] (Prev.) | CU2: VW SMA [13 Day High] (Curr.) | CV2: VW SMA [13 Day High] (Prev.) | CW2: VW SMA [13 Day Open] (Curr.) | CX2: VW SMA [13 Day Open] (Prev.) | CY2: VW SMA [5 Day Low] (Curr.) | CZ2: VW SMA [5 Day Low] (Prev.) | DA2: VW SMA [5 Day High] (Curr.) | DB2: VW SMA [5 Day High] (Prev.) | DC2: Entry [LTP & VW SMA Open Crossover] | DD2: Exit [LTP & VW SMA Low/High Crossover] | DE2: Common Entry [LTP & VW SMA Open] with [MFI(14) & SMA MFI(14)] | DF2: Common Exit [LTP & VW SMA Low/High] with [MFI(14) & SMA MFI(14)] | DG2: VW Average True Range (21) | DH2: =CONCATENATE("Max. Lots with Risk per Trade of Rs. ",'Base Data'!$D$7," [No. of Lots]") -> Max. Lots with Risk per Trade of Rs. 10500 [No. of Lots] | DI2: =CONCATENATE("Hard Stop Loss & Target Points. from Entry [",'Base Data'!$D$10,"N]") -> Hard Stop Loss & Target Points. from Entry [2N] | DJ2: Points till Hard Stop Loss | DK2: =CONCATENATE("Hard Stop Loss [",'Base Data'!$D$10,"N]") -> Hard Stop Loss [2N] | DL2: =CONCATENATE("Enter Additional Position [",1*'Base Data'!$D$12,"N]") -> Enter Additional Position [0.4N] | DM2: =CONCATENATE("Enter Additional Position [",2*'Base Data'!$D$12,"N]") -> Enter Additional Position [0.8N] | DN2: =CONCATENATE("Enter Additional Position [",3*'Base Data'!$D$12,"N]") -> Enter Additional Position [1.2N] | DO2: =CONCATENATE("Enter Additional Position [",4*'Base Data'!$D$12,"N]") -> Enter Additional Position [1.6N] | DP2: =CONCATENATE("Target [",'Base Data'!$D$10,"N]") -> Target [2N] | DQ2: Points till Target | DR2: VW Average True Range (8) | DS2: =CONCATENATE("Max. Lots with Risk per Trade of Rs. ",'Base Data'!$D$7," [No. of Lots]") -> Max. Lots with Risk per Trade of Rs. 10500 [No. of Lots] | DT2: =CONCATENATE("Hard Stop Loss & Target Points. from Entry [",'Base Data'!$D$13,"N]") -> Hard Stop Loss & Target Points. from Entry [0.75N] | DU2: Points till Hard Stop Loss | DV2: =CONCATENATE("Hard Stop Loss [",'Base Data'!$D$13,"N]") -> Hard Stop Loss [0.75N] | DW2: =CONCATENATE("Target [",'Base Data'!$D$13,"N]") -> Target [0.75N] | DX2: Pomits till Target | DY2: Ageing | DZ2: Reco. | EA2: New Buy / Sell Reco. | EB2: Sector Buy / Sell Reco. | EC2: TP 10K | ED2: Exits | EE2: Profit | EF2: Loss | EG2: Margin Utilised for Long Trades (Positional) | EH2: Margin Utilised for Short Trades (Positional) | EI2: Margin Utilised for Long Trades (IntraDay) | EJ2: Margin Utilised for Short Trades (IntraDay) | EK2: No. of Profitable Trade | EL2: No. of Losing Trades | EM2: ORB Decision to Trade | EN2: Reco. ORB (Basic) | EO2: ORB Enter High at 9:30 AM | EP2: ORB Enter Low at 9:30 AM | EQ2: ORB Exit / Hold | ER2: % Change (LTP - Prev. Close) | ES2: % Diff. (High - Low) | ET2: HL Avg. % Change Status | EU2: HL Avg. % Change (8 Day) | EV2: HL Avg. % Change (13 Day) | EW2: HL Avg. % Change (21 Day) | EX2: HL Avg. % Change (55 Day) | EY2: ORB In Trade | EZ2: Exit & Reverse
A5: 1 | B5: BankNifty | C5: =IF(AND(I5=1,BD5<>0),BD5,IF(AND(I5=2,BB5<>0),BB5,BC5)) -> 25845.55 | D5: =(BC5-BG5) -> 115.55 | E5: =(BC5-BM5) -> 2503.8 | I5: =IF(OR(J5=0,K5=0),0,IF(AND(M5=1,N5="Up-BO"),IF(OR(AND(J5="PGDn",K5="D-CL"),AND(J5="FGDn",K5="D-L"),AND(J5="PGDn",K5="U-CO"),AND(J5="PGDn",K5="U-OL"),AND(J5="PGUp",K5="U-HC"),AND(J5="PGUp",K5="D-OC"),AND(J5="PGUp",K5="D-HO"),AND(J5="FGDn",K5="U-L")),1,IF(AND(M5=2,N5="Dn-BO"),IF(OR(AND(J5="PGDUp",K5="U-HC"),AND(J5="FGUp",K5="U-H"),AND(J5="PGUp",K5="D-OC"),AND(J5="PGUp",K5="D-HO"),AND(J5="PGDn",K5="D-CL"),AND(J5="PGDn",K5="U-CO"),AND(J5="PGDn",K5="U-OL"),AND(J5="FGUp",K5="D-H")),2,IF(AND(M5=1,N5="Dn2Up-BO"),1,IF(AND(M5=2,N5="Up2Dn-BO"),2,0))),0)),IF(AND(M5=1,N5="Up-BO"),IF(OR(AND(J5="PGDn",K5="D-CL"),AND(J5="FGDn",K5="D-L"),AND(J5="PGDn",K5="U-CO"),AND(J5="PGDn",K5="U-OL"),AND(J5="PGUp",K5="U-HC"),AND(J5="PGUp",K5="D-OC"),AND(J5="PGUp",K5="D-HO"),AND(J5="FGDn",K5="U-L")),1,IF(AND(M5=2,N5="Dn-BO"),IF(OR(AND(J5="PGDUp",K5="U-HC"),AND(J5="FGUp",K5="U-H"),AND(J5="PGUp",K5="D-OC"),AND(J5="PGUp",K5="D-HO"),AND(J5="PGDn",K5="D-CL"),AND(J5="PGDn",K5="U-CO"),AND(J5="PGDn",K5="U-OL"),AND(J5="FGUp",K5="D-H")),2,IF(AND(M5=1,N5="Dn2Up-BO"),1,IF(AND(M5=2,N5="Up2Dn-BO"),2,0))),0)),0))) -> 0 | J5: =IF(AND(BG5>BM5,BG5<=BK5),"PGUp",IF(AND(BG5>BM5,BG5>BK5),"FGUp",IF(AND(BG5<BM5,BG5>=BL5),"PGDn",IF(AND(BG5<BM5,BG5<BL5),"FGDn",0)))) -> FGUp | K5: =IF(BM5>BJ5,IF(BG5>BK5,"U-H",IF(AND(BG5<=BK5,BG5>BM5),"U-HC",IF(AND(BG5<BM5,BG5>=BJ5),"U-CO",IF(AND(BG5<BJ5,BG5>=BL5),"U-OL",IF(BG5<BL5,"U-L",0))))),IF(BM5<BJ5,IF(BG5>BK5,"D-H",IF(AND(BG5<=BK5,BG5>BJ5),"D-HO",IF(AND(BG5<=BJ5,BG5>BM5),"D-OC",IF(AND(BG5<BM5,BG5>=BL5),"D-CL",IF(BG5<BL5,"D-L",0))))),0)) -> D-H | L5: =IF(BM5>BJ5,IF(BG5>BK5,"Fade-Short",IF(AND(BG5<=BK5,BG5>BM5),"Fade-Short",IF(AND(BG5<BM5,BG5>=BJ5),"Fade-Long",IF(AND(BG5<BJ5,BG5>=BL5),"Fade-Long",IF(BG5<BL5,"GA-Short",0))))),IF(BM5<BJ5,IF(BG5>BK5,"GA-Long",IF(AND(BG5<=BK5,BG5>BJ5),"Fade-Short",IF(AND(BG5<=BJ5,BG5>BM5),"Fade-Short",IF(AND(BG5<BM5,BG5>=BL5),"Fade-Long",IF(BG5<BL5,"Fade-Long",0))))),0)) -> GA-Long | M5: =IF(BG5=BI5,1,IF(BG5=BH5,2,0)) -> 0 | N5: =IF(AND(BG5<BK5,BC5>BK5),"Up-BO",IF(AND(BG5>BL5,BC5<BL5),"Dn-BO",IF(AND(J5="FGDn",BC5>BL5),"Dn2Up-BO",IF(AND(J5="FGUp",BC5<BK5),"Up2Dn-BO",0)))) -> 0 | O5: =IF(AND((IF(BV5>BW5,1,-1)>0),(IF(CB5>CC5,1,-1)>0)),1,IF(AND((IF(BV5>BW5,1,-1)<0),(IF(CB5>CC5,1,-1)<0)),2,0)) -> 1 | P5: =IF(BC5>(BH5-(BG5*0.5%)),1,IF(BC5<(BI5+(BG5*0.5%)),2,0)) -> 1 | Q5: =IF(C5>((BG5+BK5+BL5+BM5)/4),1,IF(C5<((BG5+BK5+BL5+BM5)/4),2,0)) -> 1 | R5: =IF((BS5>BT5),1,0) -> 1 | S5: =DS5 -> 0 | T5: ='BNF-Nifty'!$FC$69 -> 2.7487488 | U5: =IF(S5<>0,T5,"-") -> - | V5: =IF(U5="-","-",_xlfn.RANK.EQ(U5,$U$5:$U$12,0)) -> - | W5: =IF(U5="-","-",_xlfn.RANK.EQ(U5,$U$5:$U$12,1)) -> - | X5: ='BNF-Nifty'!$FS$69 -> T-R | Y5: ='BNF-Nifty'!$FP$69 -> 2 | Z5: ='BNF-Nifty'!$DZ$69 -> 0.022468629 | AA5: ='BNF-Nifty'!$ER$69 -> 0.038260261 | AB5: ='BNF-Nifty'!$FB$69 -> 5.0661725 | AC5: =_xlfn.RANK.AVG(AB5,$AB$5:$AB$12,0) -> 2 | AD5: =_xlfn.RANK.AVG(AB5,$AB$5:$AB$12,1) -> 3 | AE5: =IF(AND(BC5>BU5,BC5>BV5,BZ5>=CA5,BX5>BY5),"1. Strong Up-R",IF(AND(BC5>BU5,BC5>BV5,BZ5>=CA5,BX5=BY5),"1. Strong Up-F",IF(AND(BC5>BU5,BC5>BV5,BZ5>=CA5,BX5<BY5),"1. Strong Up-D",IF(AND(BC5>BU5,BC5>BV5,BZ5<CA5,BX5>BY5),"2. Weak Up-R",IF(AND(BC5>BU5,BC5>BV5,BZ5<CA5,BX5=BY5),"2. Weak Up-F",IF(AND(BC5>BU5,BC5>BV5,BZ5<CA5,BX5<BY5),"2. Weak Up-D",IF(AND(BC5<BU5,BC5<BV5,BZ5<=CA5,BX5<BY5),"1. Strong Dn-D",IF(AND(BC5<BU5,BC5<BV5,BZ5<=CA5,BX5=BY5),"1. Strong Dn-F",IF(AND(BC5<BU5,BC5<BV5,BZ5<=CA5,BX5>BY5),"1. Strong Dn-R",IF(AND(BC5<BU5,BC5<BV5,BZ5>CA5,BX5<BY5),"2. Weak Dn-D",IF(AND(BC5<BU5,BC5<BV5,BZ5>CA5,BX5=BY5),"2. Weak Dn-F",IF(AND(BC5<BU5,BC5<BV5,BZ5>CA5,BX5>BY5),"2. Weak Dn-R","-")))))))))))) -> 1. Strong Up-R | AF5: =IF(CE5>CH5,"MFI Nr. Max. Level",IF(CE5<CI5,"MFI Nr. Min. Level",IF(AND(BC5>BU5,CB5>CC5,CC5>CD5,CB5>=0,CE5>CJ5,CE5>CF5,CE5>=50,CF5>=50),"1. Ultimate Up - R",IF(AND(BC5>BU5,CB5>CC5,CC5>CD5,CB5>=0,CE5>CJ5,CE5=CF5,CE5>=50,CF5>=50),"1. Ultimate Up - F",IF(AND(BC5>BU5,CB5>CC5,CC5>CD5,CB5>=0,CE5>CJ5,CE5<CF5,CE5>=50,CF5>=50),"1. Ultimate Up - D",IF(AND(BC5>BU5,CB5>CC5,CC5>CD5,CB5<0,CE5>CJ5,CE5>CF5,CE5>=50,CF5>=50),"2. Extreme Up - R",IF(AND(BC5>BU5,CB5>CC5,CC5>CD5,CB5<0,CE5>CJ5,CE5=CF5,CE5>=50,CF5>=50),"2. Extreme Up - F",IF(AND(BC5>BU5,CB5>CC5,CC5>CD5,CB5<0,CE5>CJ5,CE5<CF5,CE5>=50,CF5>=50),"2. Extreme Up - D",IF(AND(BC5>BU5,CB5>CC5,CC5>CD5,CB5>=0,CE5>CJ5,CE5>CF5,CE5>=50,CF5<50),"3. Uber Up",IF(AND(BC5>BU5,CB5>CC5,CC5>CD5,CB5<0,CE5>CJ5,CE5>CF5,CE5>=50,CF5<50),"4. Ultra Up",IF(AND(BC5>BU5,CB5>CC5,CC5>CD5,CB5>=0,CE5>CJ5,CE5>CF5,CE5<50),"5. Hyper Up - R",IF(AND(BC5>BU5,CB5>CC5,CC5>CD5,CB5>=0,CE5>CJ5,CE5=CF5,CE5<50),"5. Hyper Up - F",IF(AND(BC5>BU5,CB5>CC5,CC5>CD5,CB5>=0,CE5>CJ5,CE5<CF5,CE5<50),"5. Hyper Up - D",IF(AND(BC5>BU5,CB5>CC5,CC5>CD5,CB5<0,CE5>CJ5,CE5>CF5,CE5<50),"6. Super Up - R",IF(AND(BC5>BU5,CB5>CC5,CC5>CD5,CB5<0,CE5>CJ5,CE5=CF5,CE5<50),"6. Super Up - F",IF(AND(BC5>BU5,CB5>CC5,CC5>CD5,CB5<0,CE5>CJ5,CE5<CF5,CE5<50),"6. Super Up - D",IF(AND(BC5>BU5,CB5>CC5,CC5<CD5,CB5>=0,CE5>CF5,CE5>=50,CF5>=50),"7. Extra Strong Up - R",IF(AND(BC5>BU5,CB5>CC5,CC5<CD5,CB5>=0,CE5=CF5,CE5>=50,CF5>=50),"7. Extra Strong Up - F",IF(AND(BC5>BU5,CB5>CC5,CC5<CD5,CB5>=0,CE5<CF5,CE5>=50,CF5>=50),"7. Extra Strong Up - D",IF(AND(BC5>BU5,CB5>CC5,CC5<CD5,CB5>=0,CE5>CF5,CE5>=50,CF5<50),"8. Strong Up",IF(AND(BC5>BU5,CB5>CC5,CC5<CD5,CB5<0,CE5>CJ5,CE5>CF5,CE5>=50,CF5>=50),"9. Up - R",IF(AND(BC5>BU5,CB5>CC5,CC5<CD5,CB5<0,CE5>CJ5,CE5=CF5,CE5>=50,CF5>=50),"9. Up - F",IF(AND(BC5>BU5,CB5>CC5,CC5<CD5,CB5<0,CE5>CJ5,CE5<CF5,CE5>=50,CF5>=50),"9. Up - D",IF(AND(BC5>BU5,CB5>CC5,CC5<CD5,CB5<0,CE5>CF5,CE5>=50,CF5>=50),"10. Weak Up - R",IF(AND(BC5>BU5,CB5>CC5,CC5<CD5,CB5<0,CE5=CF5,CE5>=50,CF5>=50),"10. Weak Up - F",IF(AND(BC5>BU5,CB5>CC5,CC5<CD5,CB5<0,CE5<CF5,CE5>=50,CF5>=50),"10. Weak Up - D",IF(AND(BC5>BU5,CB5>CC5,CC5<CD5,CB5<0,CE5>CF5,CE5>=50,CF5<50),"11. Extra Weak Up",IF(AND(BC5>BU5,CB5>CC5,CC5>CD5,CE5>CF5,CE5<50,CF5<50),"12. Very Weak Up - R",IF(AND(BC5>BU5,CB5>CC5,CC5>CD5,CE5=CF5,CE5<50,CF5<50),"12. Very Weak Up - F",IF(AND(BC5>BU5,CB5>CC5,CC5>CD5,CE5<CF5,CE5<50,CF5<50),"12. Very Weak Up - D",IF(AND(BC5<BU5,CB5<CC5,CC5<CD5,CB5<=0,CE5<CJ5,CE5<CF5,CE5<50,CF5<50),"1. Ultimate Dn - D",IF(AND(BC5<BU5,CB5<CC5,CC5<CD5,CB5<=0,CE5<CJ5,CE5=CF5,CE5<50,CF5<50),"1. Ultimate Dn - F",IF(AND(BC5<BU5,CB5<CC5,CC5<CD5,CB5<=0,CE5<CJ5,CE5>CF5,CE5<50,CF5<50),"1. Ultimate Up - R",IF(AND(BC5<BU5,CB5<CC5,CC5<CD5,CB5>0,CE5<CJ5,CE5<CF5,CE5<50,CF5<50),"2. Extreme Dn - D",IF(AND(BC5<BU5,CB5<CC5,CC5<CD5,CB5>0,CE5<CJ5,CE5=CF5,CE5<50,CF5<50),"2. Extreme Dn - F",IF(AND(BC5<BU5,CB5<CC5,CC5<CD5,CB5>0,CE5<CJ5,CE5>CF5,CE5<50,CF5<50),"2. Extreme Dn - R",IF(AND(BC5<BU5,CB5<CC5,CC5<CD5,CB5<=0,CE5<CJ5,CE5<CF5,CE5<50,CF5>=50),"3. Uber Dn",IF(AND(BC5<BU5,CB5<CC5,CC5<CD5,CB5>0,CE5<CJ5,CE5<CF5,CE5<50,CF5>=50),"4. Ultra Dn",IF(AND(BC5<BU5,CB5<CC5,CC5<CD5,CB5<=0,CE5<CJ5,CE5<CF5,CE5>=50),"5. Hyper Dn - D",IF(AND(BC5<BU5,CB5<CC5,CC5<CD5,CB5<=0,CE5<CJ5,CE5=CF5,CE5>=50),"5. Hyper Dn - F",IF(AND(BC5<BU5,CB5<CC5,CC5<CD5,CB5<=0,CE5<CJ5,CE5>CF5,CE5>=50),"5. Hyper Dn - R",IF(AND(BC5<BU5,CB5<CC5,CC5<CD5,CB5>0,CE5<CJ5,CE5<CF5,CE5>=50),"6. Super Dn - D",IF(AND(BC5<BU5,CB5<CC5,CC5<CD5,CB5>0,CE5<CJ5,CE5=CF5,CE5>=50),"6. Super Dn - F",IF(AND(BC5<BU5,CB5<CC5,CC5<CD5,CB5>0,CE5<CJ5,CE5>CF5,CE5>=50),"6. Super Dn - R",IF(AND(BC5<BU5,CB5<CC5,CC5>CD5,CB5<=0,CE5<CF5,CE5<50,CF5<50),"7. Extra Strong Dn - D",IF(AND(BC5<BU5,CB5<CC5,CC5>CD5,CB5<=0,CE5=CF5,CE5<50,CF5<50),"7. Extra Strong Dn - F",IF(AND(BC5<BU5,CB5<CC5,CC5>CD5,CB5<=0,CE5>CF5,CE5<50,CF5<50),"7. Extra Strong Dn - R",IF(AND(BC5<BU5,CB5<CC5,CC5>CD5,CB5<=0,CE5<CF5,CE5<50,CF5>=50),"8. Strong Dn",IF(AND(BC5<BU5,CB5<CC5,CC5>CD5,CB5>0,CE5<CJ5,CE5<CF5,CE5<50,CF5<50),"9. Dn - D",IF(AND(BC5<BU5,CB5<CC5,CC5>CD5,CB5>0,CE5<CJ5,CE5=CF5,CE5<50,CF5<50),"9. Dn - F",IF(AND(BC5<BU5,CB5<CC5,CC5>CD5,CB5>0,CE5<CJ5,CE5>CF5,CE5<50,CF5<50),"9. Dn - R",IF(AND(BC5<BU5,CB5<CC5,CC5>CD5,CB5>0,CE5<CF5,CE5<50,CF5<50),"10. Weak Dn - D",IF(AND(BC5<BU5,CB5<CC5,CC5>CD5,CB5>0,CE5=CF5,CE5<50,CF5<50),"10. Weak Dn - F",IF(AND(BC5<BU5,CB5<CC5,CC5>CD5,CB5>0,CE5>CF5,CE5<50,CF5<50),"10. Weak Dn - R",IF(AND(BC5<BU5,CB5<CC5,CC5>CD5,CB5>0,CE5<CF5,CE5<50,CF5>=50),"11. Extra Weak Dn",IF(AND(BC5<BU5,CB5<CC5,CC5<CD5,CE5<CF5,CE5>=50,CF5>=50),"12. Very Weak Dn - D",IF(AND(BC5<BU5,CB5<CC5,CC5<CD5,CE5=CF5,CE5>=50,CF5>=50),"12. Very Weak Dn - F",IF(AND(BC5<BU5,CB5<CC5,CC5<CD5,CE5>CF5,CE5>=50,CF5>=50),"12. Very Weak Dn - R","No Trend")))))))))))))))))))))))))))))))))))))))))))))))))))))))))) -> 1. Ultimate Up - R | AG5: =IF(BQ5>BR5,1,0) -> 1 | AH5: =DH5 -> 0 | AK5: =IF(AI5="","",IF(AI5>0,(C5-AI5),IF(AI5<0,(-AI5-C5),"Check"))) | AL5: =IF(AI5="","",(AY5-AX5)) | AM5: =IF(AI5<>"",AL5/AO5,"") | AO5: =IF(AI5<>"",(BF5*AH5),"") | AP5: =(C5*AH5*BE5) -> 0 | AQ5: =IF(AI5="","",(AP5*'Base Data'!$C$26*2)) | AR5: =IF(AI5="","",(AP5*'Base Data'!$D$26*2)) | AS5: =IF(AI5="","",((AQ5+AR5)*'Base Data'!$E$26)+(((AQ5+AR5)*'Base Data'!$E$26)*'Base Data'!$F$26)+(((AQ5+AR5)*'Base Data'!$E$26)*'Base Data'!$G$26)) | AT5: =IF(AI5="","",(AP5*'Base Data'!$H$27*2)) | AU5: =IF(AI5="","",(AP5*'Base Data'!$I$26*2)) | AV5: =IF(AI5="","",(AP5*'Base Data'!$J$26)) | AW5: =IF(AI5="","",(AP5*'Base Data'!$K$26*2)) | AX5: =IF(AI5="","",SUM(AQ5:AW5)) | AY5: =IF(AI5="","",IF(AI5>0,((C5-AI5)*AH5*BE5),IF(AI5<0,((-AI5-C5)*AH5*BE5),"Check"))) | AZ5: =IF(AI5="","",IF(AI5>0,1,IF(AI5<0,2,0))) | BA5: =CONCATENATE(B5,'Base Data'!$D$1) -> BankNifty18NovFut | BB5: =VLOOKUP(BA5,[2]Sheet1!$A:$D,2,FALSE) -> 25845 | BC5: =VLOOKUP(BA5,[2]Sheet1!$A:$D,3,FALSE) -> 25845.55 | BD5: =VLOOKUP(BA5,[2]Sheet1!$A:$D,4,FALSE) -> 25848 | BE5: =VLOOKUP(B5,'[3]Margin - NSE Fut (5Paisa)'!$A:$K,2,FALSE) -> 20 | BF5: =VLOOKUP(B5,'[3]Margin - NSE Fut (5Paisa)'!$A:$K,11,FALSE) -> 49806.74 | BG5: =VLOOKUP(BA5,[2]Sheet1!$A:$L,9,FALSE) -> 25730 | BH5: =VLOOKUP(BA5,[2]Sheet1!$A:$L,10,FALSE) -> 25880 | BI5: =VLOOKUP(BA5,[2]Sheet1!$A:$L,11,FALSE) -> 25630.1 | BJ5: ='BNF-Nifty'!$N$67 -> 23389.5 | BK5: ='BNF-Nifty'!$O$67 -> 23399 | BL5: ='BNF-Nifty'!$P$67 -> 23280 | BM5: ='BNF-Nifty'!$Q$67 -> 23341.75 | BN5: =(BG5-BM5) -> 2388.25 | BO5: =(BG5-BM5)/BM5 -> 0.10231666 | BP5: ='BNF-Nifty'!$AB$69 -> 1.0780018 | BQ5: ='BNF-Nifty'!$R$69 -> 107918 | BR5: ='BNF-Nifty'!$R$73 -> 68980.952 | BS5: ='BNF-Nifty'!$AS$69 -> 0.2098598 | BT5: ='BNF-Nifty'!$AS$73 -> 0.19464595 | BU5: ='BNF-Nifty'!$AY$69 -> 22205.745 | BV5: ='BNF-Nifty'!$BD$69 -> 23545.59 | BW5: ='BNF-Nifty'!$BD$67 -> 22960.067 | BX5: ='BNF-Nifty'!$BI$69 -> 24422.162 | BY5: ='BNF-Nifty'!$BI$67 -> 23213.905 | BZ5: =IF(BX5="","",(BC5-BX5)/BX5) -> 0.05828263 | CA5: =IF(BY5="","",(BM5-BY5)/BY5) -> 0.0055072442 | CB5: ='BNF-Nifty'!$CP$69 -> 227.94465 | CC5: ='BNF-Nifty'!$CP$67 -> 4.7441657 | CD5: ='BNF-Nifty'!$CP$66 -> 1.4390278 | CE5: ='BNF-Nifty'!$DF$69 -> 72.348014 | CF5: ='BNF-Nifty'!$DF$67 -> 64.697314 | CG5: ='BNF-Nifty'!$DF$66 -> 60.944039 | CH5: ='BNF-Nifty'!$DD$73 -> 84 | CI5: ='BNF-Nifty'!$DG$73 -> 48 | CJ5: ='BNF-Nifty'!$DG$69 -> 69.790174 | CK5: ='BNF-Nifty'!$DG$67 -> 69.839329 | CL5: ='BNF-Nifty'!$DG$66 -> 70.011303 | CM5: ='BNF-Nifty'!$DH$69 -> 72.568943 | CN5: ='BNF-Nifty'!$DH$67 -> 72.696507 | CO5: =IF(AND(BC5>BU5,CG5<CL5,CF5>CK5,CE5>CJ5,CE5>CF5,CJ5>CK5),"M34-1",IF(AND(BC5<BU5,CG5>CL5,CF5<CK5,CE5<CJ5,CE5<CF5,CJ5<CK5),"M34-2",0)) -> 0 | CP5: =IF(AI5="",0,IF(AND(AJ5="M34-1",CF5>CN5,CE5<CM5),"Exit-Long",IF(AND(AJ5="M34-2",CF5<CN5,CE5>CM5),"Exit-Short","Hold"))) -> 0 | CQ5: ='BNF-Nifty'!$BW$69 -> 22654.619 | CR5: ='BNF-Nifty'!$BW$67 -> 22490.244 | CS5: ='BNF-Nifty'!$BX$69 -> 23134.929 | CT5: ='BNF-Nifty'!$BX$67 -> 22813.486 | CU5: ='BNF-Nifty'!$BY$69 -> 23424.381 | CV5: ='BNF-Nifty'!$BY$67 -> 23101.251 | CW5: ='BNF-Nifty'!$BT$69 -> 23236.289 | CX5: ='BNF-Nifty'!$BT$67 -> 22912.98 | CY5: ='BNF-Nifty'!$BU$69 -> 23966.107 | CZ5: ='BNF-Nifty'!$BU$67 -> 23155.23 | DA5: ='BNF-Nifty'!$BV$69 -> 24158.939 | DB5: ='BNF-Nifty'!$BV$67 -> 23348.441 | DC5: =IF(AND(BC5>BU5,BM5<CR5,BC5>CQ5,BC5>BM5),"P34-1",IF(AND(BC5<BU5,BM5>CR5,BC5<CQ5,BC5<BM5),"P34-2",IF(AND(BC5>BU5,BM5<CX5,BC5>CW5,BC5>BM5),"P13-1",IF(AND(BC5<BU5,BM5>CX5,BC5<CW5,BC5<BM5),"P13-2",0)))) -> 0 | DD5: =IF(AI5="",0,IF(OR(AND(AJ5="P34-1",BM5>CT5,BC5<CS5),AND(AJ5="P13-1",BM5>CZ5,BC5<CY5)),"Exit-Long",IF(OR(AND(AJ5="P34-2",BM5<CV5,BC5>CU5),AND(AJ5="P13-2",BM5<DB5,BC5>DA5)),"Exit-Short","Hold"))) -> 0 | DE5: =IF(AND(BC5>BU5,CG5<CL5,CF5>CK5,CE5>CJ5,CE5>CF5,CJ5>CK5),"M34-1",IF(AND(BC5<BU5,CG5>CL5,CF5<CK5,CE5<CJ5,CE5<CF5,CJ5<CK5),"M34-2",IF(AND(BC5>BU5,BM5<CR5,BC5>CQ5,BC5>BM5),"P34-1",IF(AND(BC5<BU5,BM5>CR5,BC5<CQ5,BC5<BM5),"P34-2",IF(AND(BC5>BU5,BM5<CX5,BC5>CW5,BC5>BM5),"P13-1",IF(AND(BC5<BU5,BM5>CX5,BC5<CW5,BC5<BM5),"P13-2",0)))))) -> 0 | DF5: =IF(AI5="",0,IF(OR(AND(AJ5="M34-1",CF5>CK5,CE5<CJ5),AND(AJ5="P34-1",BM5>CT5,BC5<CS5),AND(AJ5="P13-1",BM5>CZ5,BC5<CY5)),"Exit-Long",IF(OR(AND(AJ5="M34-2",CF5<CK5,CE5>CJ5),AND(AJ5="P34-2",BM5<CV5,BC5>CU5),AND(AJ5="P13-2",BM5<DB5,BC5>DA5)),"Exit-Short","Hold"))) -> 0 | DG5: ='BNF-Nifty'!$DV$69 -> 580.71406 | DH5: ='BNF-Nifty'!$DY$69 -> 0 | DI5: =IF(AI5="","-",'Base Data'!$D$10*DG5) -> - | DJ5: =IF(DK5="-","-",IF(AI5>0,(DK5-AI5),IF(AI5<0,(DK5+AI5),"Check"))) -> - | DK5: =IF(AI5="","-",IF(AI5>0,(AI5-DI5),IF(AI5<0,(-AI5+DI5),"Check"))) -> - | DL5: =IF(AI5="","-",IF(AI5>0,(AI5+(1*'Base Data'!$D$12*DG5)),IF(AI5<0,(-AI5-(1*'Base Data'!$D$12*DG5)),"Check"))) -> - | DM5: =IF(AI5="","-",IF(AI5>0,(AI5+(2*'Base Data'!$D$12*DG5)),IF(AI5<0,(-AI5-(2*'Base Data'!$D$12*DG5)),"Check"))) -> - | DN5: =IF(AI5="","-",IF(AI5>0,(AI5+(3*'Base Data'!$D$12*DG5)),IF(AI5<0,(-AI5-(3*'Base Data'!$D$12*DG5)),"Check"))) -> - | DO5: =IF(AI5="","-",IF(AI5>0,(AI5+(4*'Base Data'!$D$12*DG5)),IF(AI5<0,(-AI5-(4*'Base Data'!$D$12*DG5)),"Check"))) -> - | DP5: =IF(AI5="","-",IF(AI5>0,(AI5+DI5),IF(AI5<0,(-AI5-DI5),"Check"))) -> - | DQ5: =IF(DP5="-","-",IF(AI5>0,(DP5-AI5),IF(AI5<0,(DP5+AI5),"Check"))) -> - | DR5: ='BNF-Nifty'!$EN$69 -> 988.85749 | DS5: ='BNF-Nifty'!$EQ$69 -> 0 | DT5: =IF(AI5="","-",'Base Data'!$D$13*DR5) -> - | DU5: =IF(DV5="-","-",IF(AI5>0,(DV5-AI5),IF(AI5<0,(DV5+AI5),"Check"))) -> - | DV5: =IF(AI5="","-",IF(AI5>0,(AI5-DT5),IF(AI5<0,(-AI5+DT5),"Check"))) -> - | DW5: =IF(AI5="","-",IF(AI5>0,(AI5+DT5),IF(AI5<0,(-AI5-DT5),"Check"))) -> - | DX5: =IF(DW5="-","-",IF(AI5>0,(DW5-AI5),IF(AI5<0,(DW5+AI5),"Check"))) -> - | EE5: =IF(AI5="","",IF(AL5>0,AL5,0)) | EF5: =IF(AI5="","",IF(AL5<=0,AL5,0)) | EG5: =IF(AI5="","",IF(AI5>0,(BF5*AH5),0)) | EH5: =IF(AI5="","",IF(AI5<=0,(BF5*AH5),0)) | EI5: =IF(AI5="","",IF(AI5>0,(BF5*S5),0)) | EJ5: =IF(AI5="","",IF(AI5<=0,(BF5*S5),0)) | EK5: =IF(AI5="","",IF(AL5>0,1,0)) | EL5: =IF(AI5="","",IF(AL5<=0,1,0)) | EM5: =IF(AND(EN5=1,OR(AND(ER5>=0.5%,ER5<=1.5%),AND(ER5<=-0.5%,ER5>=-1.5%)),ES5>=0.5%),CONCATENATE("Long ",B5),IF(AND(EN5=2,OR(AND(ER5>=0.5%,ER5<=1.5%),AND(ER5<=-0.5%,ER5>=-1.5%)),ES5>=0.5%),CONCATENATE("Short ",B5),"Do Not Trade")) -> Do Not Trade | EN5: =IF(OR(EO5="",EP5=""),"",IF(BC5>=(EO5+'Base Data'!$D$14),1,IF(BC5<=(EP5-'Base Data'!$D$14),2,0))) -> 0 | EO5: =BH5 -> 25880 | EP5: =BI5 -> 25630.1 | EQ5: =IF(AI5="","",IF(AI5>0,IF(BC5<EP5,"Exit Long & Go Short",IF(BC5>(AI5+(EO5-EP5)),"Exit - TP","Hold")),IF(AI5<0,IF(BC5>EO5,"Exit Short & Go Long",IF(BC5<(-AI5-(EO5-EP5)),"Exit - TP","Hold"))))) | ER5: =(BC5-BM5)/BM5 -> 0.10726702 | ES5: =IF(OR(EO5<>"",EP5<>""),(EO5-EP5)/BG5,(BH5-BI5)/BG5) -> 0.009712398 | ET5: =IF(AND(EU5="",EV5="",EW5="",EX5=""),"",IF(AND(EU5<(80%*EX5),EV5<(80%*EX5),EW5<(80%*EX5)),0,IF(AND(EU5>=(80%*EX5),EV5<(80%*EX5),EW5<(80%*EX5)),5,IF(AND(EU5<(80%*EX5),EV5>=(80%*EX5),EW5<(80%*EX5)),10,IF(AND(EU5<(80%*EX5),EV5<(80%*EX5),EW5>=(80%*EX5)),15,IF(AND(EU5>=(80%*EX5),EV5>=(80%*EX5),EW5<(80%*EX5)),20,IF(AND(EU5>=(80%*EX5),EV5<(80%*EX5),EW5>=(80%*EX5)),25,IF(AND(EU5<(80%*EX5),EV5>=(80%*EX5),EW5>=(80%*EX5)),30,IF(AND(EU5>=(80%*EX5),EV5>=(80%*EX5),EW5>=(80%*EX5)),35,"Check"))))))))) -> 35 | EU5: ='BNF-Nifty'!$FH$69 -> 0.011999153 | EV5: ='BNF-Nifty'!$FI$69 -> 0.010656266 | EW5: ='BNF-Nifty'!$FJ$69 -> 0.0097105908 | EX5: ='BNF-Nifty'!$FG$73 -> 0.0095637767 | EY5: =IF(OR(AND(EN5=1,OR(AND(ER5>=0.5%,ER5<=1.5%),AND(ER5<=-0.5%,ER5>=-1.5%)),ES5>=0.5%),AND(EN5=2,OR(AND(ER5>=0.5%,ER5<=1.5%),AND(ER5<=-0.5%,ER5>=-1.5%)),ES5>=0.5%)),1,0) -> 0 | EZ5: =IF(OR(EQ5="Exit Long & Go Short",EQ5="Exit Short & Go Long"),1,0) -> 0
A7: =A5+1 -> 2 | B7: Nifty | C7: =IF(AND(I7=1,BD7<>0),BD7,IF(AND(I7=2,BB7<>0),BB7,BC7)) -> 10619.8 | D7: =(BC7-BG7) -> 18.8 | E7: =(BC7-BM7) -> 967.2 | J7: =IF(AND(BG7>BM7,BG7<=BK7),"PGUp",IF(AND(BG7>BM7,BG7>BK7),"FGUp",IF(AND(BG7<BM7,BG7>=BL7),"PGDn",IF(AND(BG7<BM7,BG7<BL7),"FGDn",0)))) -> FGUp | K7: =IF(BM7>BJ7,IF(BG7>BK7,"U-H",IF(AND(BG7<=BK7,BG7>BM7),"U-HC",IF(AND(BG7<BM7,BG7>=BJ7),"U-CO",IF(AND(BG7<BJ7,BG7>=BL7),"U-OL",IF(BG7<BL7,"U-L",0))))),IF(BM7<BJ7,IF(BG7>BK7,"D-H",IF(AND(BG7<=BK7,BG7>BJ7),"D-HO",IF(AND(BG7<=BJ7,BG7>BM7),"D-OC",IF(AND(BG7<BM7,BG7>=BL7),"D-CL",IF(BG7<BL7,"D-L",0))))),0)) -> D-H | L7: =IF(BM7>BJ7,IF(BG7>BK7,"Fade-Short",IF(AND(BG7<=BK7,BG7>BM7),"Fade-Short",IF(AND(BG7<BM7,BG7>=BJ7),"Fade-Long",IF(AND(BG7<BJ7,BG7>=BL7),"Fade-Long",IF(BG7<BL7,"GA-Short",0))))),IF(BM7<BJ7,IF(BG7>BK7,"GA-Long",IF(AND(BG7<=BK7,BG7>BJ7),"Fade-Short",IF(AND(BG7<=BJ7,BG7>BM7),"Fade-Short",IF(AND(BG7<BM7,BG7>=BL7),"Fade-Long",IF(BG7<BL7,"Fade-Long",0))))),0)) -> GA-Long | M7: =IF(BG7=BI7,1,IF(BG7=BH7,2,0)) -> 0 | N7: =IF(AND(BG7<BK7,BC7>BK7),"Up-BO",IF(AND(BG7>BL7,BC7<BL7),"Dn-BO",IF(AND(J7="FGDn",BC7>BL7),"Dn2Up-BO",IF(AND(J7="FGUp",BC7<BK7),"Up2Dn-BO",0)))) -> 0 | O7: =IF(AND((IF(BV7>BW7,1,-1)>0),(IF(CB7>CC7,1,-1)>0)),1,IF(AND((IF(BV7>BW7,1,-1)<0),(IF(CB7>CC7,1,-1)<0)),2,0)) -> 1 | P7: =IF(BC7>(BH7-(BG7*0.5%)),1,IF(BC7<(BI7+(BG7*0.5%)),2,0)) -> 1 | Q7: =IF(C7>((BG7+BK7+BL7+BM7)/4),1,IF(C7<((BG7+BK7+BL7+BM7)/4),2,0)) -> 1 | R7: =IF((BS7>BT7),1,0) -> 1 | S7: =DS7 -> 0 | T7: ='BNF-Nifty'!$FE$69 -> 3.4614677 | U7: =IF(S7<>0,T7,"-") -> - | V7: =IF(U7="-","-",_xlfn.RANK.EQ(U7,$U$5:$U$12,0)) -> - | W7: =IF(U7="-","-",_xlfn.RANK.EQ(U7,$U$5:$U$12,1)) -> - | X7: ='BNF-Nifty'!$FU$69 -> T-R | Y7: ='BNF-Nifty'!$FQ$69 -> 2 | Z7: ='BNF-Nifty'!$EI$69 -> 0.015880955 | AA7: ='BNF-Nifty'!$FA$69 -> 0.028731564 | AB7: ='BNF-Nifty'!$FD$69 -> 6.794639 | AC7: =_xlfn.RANK.AVG(AB7,$AB$5:$AB$12,0) -> 1 | AD7: =_xlfn.RANK.AVG(AB7,$AB$5:$AB$12,1) -> 4 | AE7: =IF(AND(BC7>BU7,BC7>BV7,BZ7>=CA7,BX7>BY7),"1. Strong Up-R",IF(AND(BC7>BU7,BC7>BV7,BZ7>=CA7,BX7=BY7),"1. Strong Up-F",IF(AND(BC7>BU7,BC7>BV7,BZ7>=CA7,BX7<BY7),"1. Strong Up-D",IF(AND(BC7>BU7,BC7>BV7,BZ7<CA7,BX7>BY7),"2. Weak Up-R",IF(AND(BC7>BU7,BC7>BV7,BZ7<CA7,BX7=BY7),"2. Weak Up-F",IF(AND(BC7>BU7,BC7>BV7,BZ7<CA7,BX7<BY7),"2. Weak Up-D",IF(AND(BC7<BU7,BC7<BV7,BZ7<=CA7,BX7<BY7),"1. Strong Dn-D",IF(AND(BC7<BU7,BC7<BV7,BZ7<=CA7,BX7=BY7),"1. Strong Dn-F",IF(AND(BC7<BU7,BC7<BV7,BZ7<=CA7,BX7>BY7),"1. Strong Dn-R",IF(AND(BC7<BU7,BC7<BV7,BZ7>CA7,BX7<BY7),"2. Weak Dn-D",IF(AND(BC7<BU7,BC7<BV7,BZ7>CA7,BX7=BY7),"2. Weak Dn-F",IF(AND(BC7<BU7,BC7<BV7,BZ7>CA7,BX7>BY7),"2. Weak Dn-R","-")))))))))))) -> 1. Strong Up-R | AF7: =IF(CE7>CH7,"MFI Nr. Max. Level",IF(CE7<CI7,"MFI Nr. Min. Level",IF(AND(BC7>BU7,CB7>CC7,CC7>CD7,CB7>=0,CE7>CJ7,CE7>CF7,CE7>=50,CF7>=50),"1. Ultimate Up - R",IF(AND(BC7>BU7,CB7>CC7,CC7>CD7,CB7>=0,CE7>CJ7,CE7=CF7,CE7>=50,CF7>=50),"1. Ultimate Up - F",IF(AND(BC7>BU7,CB7>CC7,CC7>CD7,CB7>=0,CE7>CJ7,CE7<CF7,CE7>=50,CF7>=50),"1. Ultimate Up - D",IF(AND(BC7>BU7,CB7>CC7,CC7>CD7,CB7<0,CE7>CJ7,CE7>CF7,CE7>=50,CF7>=50),"2. Extreme Up - R",IF(AND(BC7>BU7,CB7>CC7,CC7>CD7,CB7<0,CE7>CJ7,CE7=CF7,CE7>=50,CF7>=50),"2. Extreme Up - F",IF(AND(BC7>BU7,CB7>CC7,CC7>CD7,CB7<0,CE7>CJ7,CE7<CF7,CE7>=50,CF7>=50),"2. Extreme Up - D",IF(AND(BC7>BU7,CB7>CC7,CC7>CD7,CB7>=0,CE7>CJ7,CE7>CF7,CE7>=50,CF7<50),"3. Uber Up",IF(AND(BC7>BU7,CB7>CC7,CC7>CD7,CB7<0,CE7>CJ7,CE7>CF7,CE7>=50,CF7<50),"4. Ultra Up",IF(AND(BC7>BU7,CB7>CC7,CC7>CD7,CB7>=0,CE7>CJ7,CE7>CF7,CE7<50),"5. Hyper Up - R",IF(AND(BC7>BU7,CB7>CC7,CC7>CD7,CB7>=0,CE7>CJ7,CE7=CF7,CE7<50),"5. Hyper Up - F",IF(AND(BC7>BU7,CB7>CC7,CC7>CD7,CB7>=0,CE7>CJ7,CE7<CF7,CE7<50),"5. Hyper Up - D",IF(AND(BC7>BU7,CB7>CC7,CC7>CD7,CB7<0,CE7>CJ7,CE7>CF7,CE7<50),"6. Super Up - R",IF(AND(BC7>BU7,CB7>CC7,CC7>CD7,CB7<0,CE7>CJ7,CE7=CF7,CE7<50),"6. Super Up - F",IF(AND(BC7>BU7,CB7>CC7,CC7>CD7,CB7<0,CE7>CJ7,CE7<CF7,CE7<50),"6. Super Up - D",IF(AND(BC7>BU7,CB7>CC7,CC7<CD7,CB7>=0,CE7>CF7,CE7>=50,CF7>=50),"7. Extra Strong Up - R",IF(AND(BC7>BU7,CB7>CC7,CC7<CD7,CB7>=0,CE7=CF7,CE7>=50,CF7>=50),"7. Extra Strong Up - F",IF(AND(BC7>BU7,CB7>CC7,CC7<CD7,CB7>=0,CE7<CF7,CE7>=50,CF7>=50),"7. Extra Strong Up - D",IF(AND(BC7>BU7,CB7>CC7,CC7<CD7,CB7>=0,CE7>CF7,CE7>=50,CF7<50),"8. Strong Up",IF(AND(BC7>BU7,CB7>CC7,CC7<CD7,CB7<0,CE7>CJ7,CE7>CF7,CE7>=50,CF7>=50),"9. Up - R",IF(AND(BC7>BU7,CB7>CC7,CC7<CD7,CB7<0,CE7>CJ7,CE7=CF7,CE7>=50,CF7>=50),"9. Up - F",IF(AND(BC7>BU7,CB7>CC7,CC7<CD7,CB7<0,CE7>CJ7,CE7<CF7,CE7>=50,CF7>=50),"9. Up - D",IF(AND(BC7>BU7,CB7>CC7,CC7<CD7,CB7<0,CE7>CF7,CE7>=50,CF7>=50),"10. Weak Up - R",IF(AND(BC7>BU7,CB7>CC7,CC7<CD7,CB7<0,CE7=CF7,CE7>=50,CF7>=50),"10. Weak Up - F",IF(AND(BC7>BU7,CB7>CC7,CC7<CD7,CB7<0,CE7<CF7,CE7>=50,CF7>=50),"10. Weak Up - D",IF(AND(BC7>BU7,CB7>CC7,CC7<CD7,CB7<0,CE7>CF7,CE7>=50,CF7<50),"11. Extra Weak Up",IF(AND(BC7>BU7,CB7>CC7,CC7>CD7,CE7>CF7,CE7<50,CF7<50),"12. Very Weak Up - R",IF(AND(BC7>BU7,CB7>CC7,CC7>CD7,CE7=CF7,CE7<50,CF7<50),"12. Very Weak Up - F",IF(AND(BC7>BU7,CB7>CC7,CC7>CD7,CE7<CF7,CE7<50,CF7<50),"12. Very Weak Up - D",IF(AND(BC7<BU7,CB7<CC7,CC7<CD7,CB7<=0,CE7<CJ7,CE7<CF7,CE7<50,CF7<50),"1. Ultimate Dn - D",IF(AND(BC7<BU7,CB7<CC7,CC7<CD7,CB7<=0,CE7<CJ7,CE7=CF7,CE7<50,CF7<50),"1. Ultimate Dn - F",IF(AND(BC7<BU7,CB7<CC7,CC7<CD7,CB7<=0,CE7<CJ7,CE7>CF7,CE7<50,CF7<50),"1. Ultimate Up - R",IF(AND(BC7<BU7,CB7<CC7,CC7<CD7,CB7>0,CE7<CJ7,CE7<CF7,CE7<50,CF7<50),"2. Extreme Dn - D",IF(AND(BC7<BU7,CB7<CC7,CC7<CD7,CB7>0,CE7<CJ7,CE7=CF7,CE7<50,CF7<50),"2. Extreme Dn - F",IF(AND(BC7<BU7,CB7<CC7,CC7<CD7,CB7>0,CE7<CJ7,CE7>CF7,CE7<50,CF7<50),"2. Extreme Dn - R",IF(AND(BC7<BU7,CB7<CC7,CC7<CD7,CB7<=0,CE7<CJ7,CE7<CF7,CE7<50,CF7>=50),"3. Uber Dn",IF(AND(BC7<BU7,CB7<CC7,CC7<CD7,CB7>0,CE7<CJ7,CE7<CF7,CE7<50,CF7>=50),"4. Ultra Dn",IF(AND(BC7<BU7,CB7<CC7,CC7<CD7,CB7<=0,CE7<CJ7,CE7<CF7,CE7>=50),"5. Hyper Dn - D",IF(AND(BC7<BU7,CB7<CC7,CC7<CD7,CB7<=0,CE7<CJ7,CE7=CF7,CE7>=50),"5. Hyper Dn - F",IF(AND(BC7<BU7,CB7<CC7,CC7<CD7,CB7<=0,CE7<CJ7,CE7>CF7,CE7>=50),"5. Hyper Dn - R",IF(AND(BC7<BU7,CB7<CC7,CC7<CD7,CB7>0,CE7<CJ7,CE7<CF7,CE7>=50),"6. Super Dn - D",IF(AND(BC7<BU7,CB7<CC7,CC7<CD7,CB7>0,CE7<CJ7,CE7=CF7,CE7>=50),"6. Super Dn - F",IF(AND(BC7<BU7,CB7<CC7,CC7<CD7,CB7>0,CE7<CJ7,CE7>CF7,CE7>=50),"6. Super Dn - R",IF(AND(BC7<BU7,CB7<CC7,CC7>CD7,CB7<=0,CE7<CF7,CE7<50,CF7<50),"7. Extra Strong Dn - D",IF(AND(BC7<BU7,CB7<CC7,CC7>CD7,CB7<=0,CE7=CF7,CE7<50,CF7<50),"7. Extra Strong Dn - F",IF(AND(BC7<BU7,CB7<CC7,CC7>CD7,CB7<=0,CE7>CF7,CE7<50,CF7<50),"7. Extra Strong Dn - R",IF(AND(BC7<BU7,CB7<CC7,CC7>CD7,CB7<=0,CE7<CF7,CE7<50,CF7>=50),"8. Strong Dn",IF(AND(BC7<BU7,CB7<CC7,CC7>CD7,CB7>0,CE7<CJ7,CE7<CF7,CE7<50,CF7<50),"9. Dn - D",IF(AND(BC7<BU7,CB7<CC7,CC7>CD7,CB7>0,CE7<CJ7,CE7=CF7,CE7<50,CF7<50),"9. Dn - F",IF(AND(BC7<BU7,CB7<CC7,CC7>CD7,CB7>0,CE7<CJ7,CE7>CF7,CE7<50,CF7<50),"9. Dn - R",IF(AND(BC7<BU7,CB7<CC7,CC7>CD7,CB7>0,CE7<CF7,CE7<50,CF7<50),"10. Weak Dn - D",IF(AND(BC7<BU7,CB7<CC7,CC7>CD7,CB7>0,CE7=CF7,CE7<50,CF7<50),"10. Weak Dn - F",IF(AND(BC7<BU7,CB7<CC7,CC7>CD7,CB7>0,CE7>CF7,CE7<50,CF7<50),"10. Weak Dn - R",IF(AND(BC7<BU7,CB7<CC7,CC7>CD7,CB7>0,CE7<CF7,CE7<50,CF7>=50),"11. Extra Weak Dn",IF(AND(BC7<BU7,CB7<CC7,CC7<CD7,CE7<CF7,CE7>=50,CF7>=50),"12. Very Weak Dn - D",IF(AND(BC7<BU7,CB7<CC7,CC7<CD7,CE7=CF7,CE7>=50,CF7>=50),"12. Very Weak Dn - F",IF(AND(BC7<BU7,CB7<CC7,CC7<CD7,CE7>CF7,CE7>=50,CF7>=50),"12. Very Weak Dn - R","No Trend")))))))))))))))))))))))))))))))))))))))))))))))))))))))))) -> 1. Ultimate Up - R | AG7: =IF(BQ7>BR7,1,0) -> 1 | AH7: =DH7 -> 0 | AK7: =IF(AI7="","",IF(AI7>0,(C7-AI7),IF(AI7<0,(-AI7-C7),"Check"))) | AL7: =IF(AI7="","",(AY7-AX7)) | AM7: =IF(AI7<>"",AL7/AO7,"") | AO7: =IF(AI7<>"",(BF7*AH7),"") | AP7: =(C7*AH7*BE7) -> 0 | AQ7: =IF(AI7="","",(AP7*'Base Data'!$C$26*2)) | AR7: =IF(AI7="","",(AP7*'Base Data'!$D$26*2)) | AS7: =IF(AI7="","",((AQ7+AR7)*'Base Data'!$E$26)+(((AQ7+AR7)*'Base Data'!$E$26)*'Base Data'!$F$26)+(((AQ7+AR7)*'Base Data'!$E$26)*'Base Data'!$G$26)) | AT7: =IF(AI7="","",(AP7*'Base Data'!$H$27*2)) | AU7: =IF(AI7="","",(AP7*'Base Data'!$I$26*2)) | AV7: =IF(AI7="","",(AP7*'Base Data'!$J$26)) | AW7: =IF(AI7="","",(AP7*'Base Data'!$K$26*2)) | AX7: =IF(AI7="","",SUM(AQ7:AW7)) | AY7: =IF(AI7="","",IF(AI7>0,((C7-AI7)*AH7*BE7),IF(AI7<0,((-AI7-C7)*AH7*BE7),"Check"))) | AZ7: =IF(AI7="","",IF(AI7>0,1,IF(AI7<0,2,0))) | BA7: =CONCATENATE(B7,'Base Data'!$D$1) -> Nifty18NovFut | BB7: =VLOOKUP(BA7,[2]Sheet1!$A:$D,2,FALSE) -> 10618 | BC7: =VLOOKUP(BA7,[2]Sheet1!$A:$D,3,FALSE) -> 10619.8 | BD7: =VLOOKUP(BA7,[2]Sheet1!$A:$D,4,FALSE) -> 10619.8 | BE7: =VLOOKUP(B7,'[3]Margin - NSE Fut (5Paisa)'!$A:$K,2,FALSE) -> 75 | BF7: =VLOOKUP(B7,'[3]Margin - NSE Fut (5Paisa)'!$A:$K,11,FALSE) -> 76212.887 | BG7: =VLOOKUP(BA7,[2]Sheet1!$A:$L,9,FALSE) -> 10601 | BH7: =VLOOKUP(BA7,[2]Sheet1!$A:$L,10,FALSE) -> 10643.95 | BI7: =VLOOKUP(BA7,[2]Sheet1!$A:$L,11,FALSE) -> 10571.1 | BJ7: ='BNF-Nifty'!$T$67 -> 9660.15 | BK7: ='BNF-Nifty'!$U$67 -> 9672 | BL7: ='BNF-Nifty'!$V$67 -> 9643.2 | BM7: ='BNF-Nifty'!$W$67 -> 9652.6 | BN7: =(BG7-BM7) -> 948.4 | BO7: =(BG7-BM7)/BM7 -> 0.09825332 | BP7: ='BNF-Nifty'!$AC$69 -> 1 | BQ7: ='BNF-Nifty'!$X$69 -> 120113 | BR7: ='BNF-Nifty'!$X$73 -> 110474.9 | BS7: ='BNF-Nifty'!$AW$69 -> 0.1421066 | BT7: ='BNF-Nifty'!$AW$73 -> 0.13531035 | BU7: ='BNF-Nifty'!$BA$69 -> 9322.5794 | BV7: ='BNF-Nifty'!$BL$69 -> 9673.2394 | BW7: ='BNF-Nifty'!$BL$67 -> 9503.0505 | BX7: ='BNF-Nifty'!$BQ$69 -> 9996.6574 | BY7: ='BNF-Nifty'!$BQ$67 -> 9592.903 | BZ7: =IF(BX7="","",(BC7-BX7)/BX7) -> 0.0623351 | CA7: =IF(BY7="","",(BM7-BY7)/BY7) -> 0.0062230414 | CB7: ='BNF-Nifty'!$CY$69 -> 79.196764 | CC7: ='BNF-Nifty'!$CY$67 -> 9.0270957 | CD7: ='BNF-Nifty'!$CY$66 -> 6.7447966 | CE7: ='BNF-Nifty'!$DO$69 -> 69.940468 | CF7: ='BNF-Nifty'!$DO$67 -> 64.29137 | CG7: ='BNF-Nifty'!$DO$66 -> 60.69472 | CH7: ='BNF-Nifty'!$DM$73 -> 77 | CI7: ='BNF-Nifty'!$DP$73 -> 31 | CJ7: ='BNF-Nifty'!$DP$69 -> 57.031464 | CK7: ='BNF-Nifty'!$DP$67 -> 56.281433 | CL7: ='BNF-Nifty'!$DP$66 -> 55.852217 | CM7: ='BNF-Nifty'!$DQ$69 -> 59.912579 | CN7: ='BNF-Nifty'!$DQ$67 -> 59.708349 | CO7: =IF(AND(BC7>BU7,CG7<CL7,CF7>CK7,CE7>CJ7,CE7>CF7,CJ7>CK7),"M34-1",IF(AND(BC7<BU7,CG7>CL7,CF7<CK7,CE7<CJ7,CE7<CF7,CJ7<CK7),"M34-2",0)) -> 0 | CP7: =IF(AI7="",0,IF(AND(AJ7="M34-1",CF7>CN7,CE7<CM7),"Exit-Long",IF(AND(AJ7="M34-2",CF7<CN7,CE7>CM7),"Exit-Short","Hold"))) -> 0 | CQ7: ='BNF-Nifty'!$CE$69 -> 9416.3593 | CR7: ='BNF-Nifty'!$CE$67 -> 9373.7556 | CS7: ='BNF-Nifty'!$CF$69 -> 9541.0905 | CT7: ='BNF-Nifty'!$CF$67 -> 9458.3208 | CU7: ='BNF-Nifty'!$CG$69 -> 9624.6759 | CV7: ='BNF-Nifty'!$CG$67 -> 9542.1021 | CW7: ='BNF-Nifty'!$CB$69 -> 9575.9034 | CX7: ='BNF-Nifty'!$CB$67 -> 9491.4507 | CY7: ='BNF-Nifty'!$CC$69 -> 9872.9021 | CZ7: ='BNF-Nifty'!$CC$67 -> 9586.8301 | DA7: ='BNF-Nifty'!$CD$69 -> 9922.475 | DB7: ='BNF-Nifty'!$CD$67 -> 9645.0047 | DC7: =IF(AND(BC7>BU7,BM7<CR7,BC7>CQ7,BC7>BM7),"P34-1",IF(AND(BC7<BU7,BM7>CR7,BC7<CQ7,BC7<BM7),"P34-2",IF(AND(BC7>BU7,BM7<CX7,BC7>CW7,BC7>BM7),"P13-1",IF(AND(BC7<BU7,BM7>CX7,BC7<CW7,BC7<BM7),"P13-2",0)))) -> 0 | DD7: =IF(AI7="",0,IF(OR(AND(AJ7="P34-1",BM7>CT7,BC7<CS7),AND(AJ7="P13-1",BM7>CZ7,BC7<CY7)),"Exit-Long",IF(OR(AND(AJ7="P34-2",BM7<CV7,BC7>CU7),AND(AJ7="P13-2",BM7<DB7,BC7>DA7)),"Exit-Short","Hold"))) -> 0 | DE7: =IF(AND(BC7>BU7,CG7<CL7,CF7>CK7,CE7>CJ7,CE7>CF7,CJ7>CK7),"M34-1",IF(AND(BC7<BU7,CG7>CL7,CF7<CK7,CE7<CJ7,CE7<CF7,CJ7<CK7),"M34-2",IF(AND(BC7>BU7,BM7<CR7,BC7>CQ7,BC7>BM7),"P34-1",IF(AND(BC7<BU7,BM7>CR7,BC7<CQ7,BC7<BM7),"P34-2",IF(AND(BC7>BU7,BM7<CX7,BC7>CW7,BC7>BM7),"P13-1",IF(AND(BC7<BU7,BM7>CX7,BC7<CW7,BC7<BM7),"P13-2",0)))))) -> 0 | DF7: =IF(AI7="",0,IF(OR(AND(AJ7="M34-1",CF7>CK7,CE7<CJ7),AND(AJ7="P34-1",BM7>CT7,BC7<CS7),AND(AJ7="P13-1",BM7>CZ7,BC7<CY7)),"Exit-Long",IF(OR(AND(AJ7="M34-2",CF7<CK7,CE7>CJ7),AND(AJ7="P34-2",BM7<CV7,BC7>CU7),AND(AJ7="P13-2",BM7<DB7,BC7>DA7)),"Exit-Short","Hold"))) -> 0 | DG7: ='BNF-Nifty'!$EE$69 -> 168.65257 | DH7: ='BNF-Nifty'!$EH$69 -> 0 | DI7: =IF(AI7="","-",'Base Data'!$D$10*DG7) -> - | DJ7: =IF(DK7="-","-",IF(AI7>0,(DK7-AI7),IF(AI7<0,(DK7+AI7),"Check"))) -> - | DK7: =IF(AI7="","-",IF(AI7>0,(AI7-DI7),IF(AI7<0,(-AI7+DI7),"Check"))) -> - | DL7: =IF(AI7="","-",IF(AI7>0,(AI7+(1*'Base Data'!$D$12*DG7)),IF(AI7<0,(-AI7-(1*'Base Data'!$D$12*DG7)),"Check"))) -> - | DM7: =IF(AI7="","-",IF(AI7>0,(AI7+(2*'Base Data'!$D$12*DG7)),IF(AI7<0,(-AI7-(2*'Base Data'!$D$12*DG7)),"Check"))) -> - | DN7: =IF(AI7="","-",IF(AI7>0,(AI7+(3*'Base Data'!$D$12*DG7)),IF(AI7<0,(-AI7-(3*'Base Data'!$D$12*DG7)),"Check"))) -> - | DO7: =IF(AI7="","-",IF(AI7>0,(AI7+(4*'Base Data'!$D$12*DG7)),IF(AI7<0,(-AI7-(4*'Base Data'!$D$12*DG7)),"Check"))) -> - | DP7: =IF(AI7="","-",IF(AI7>0,(AI7+DI7),IF(AI7<0,(-AI7-DI7),"Check"))) -> - | DQ7: =IF(DP7="-","-",IF(AI7>0,(DP7-AI7),IF(AI7<0,(DP7+AI7),"Check"))) -> - | DR7: ='BNF-Nifty'!$EW$69 -> 305.12346 | DS7: ='BNF-Nifty'!$EZ$69 -> 0 | DT7: =IF(AI7="","-",'Base Data'!$D$13*DR7) -> - | DU7: =IF(DV7="-","-",IF(AI7>0,(DV7-AI7),IF(AI7<0,(DV7+AI7),"Check"))) -> - | DV7: =IF(AI7="","-",IF(AI7>0,(AI7-DT7),IF(AI7<0,(-AI7+DT7),"Check"))) -> - | DW7: =IF(AI7="","-",IF(AI7>0,(AI7+DT7),IF(AI7<0,(-AI7-DT7),"Check"))) -> - | DX7: =IF(DW7="-","-",IF(AI7>0,(DW7-AI7),IF(AI7<0,(DW7+AI7),"Check"))) -> - | EE7: =IF(AI7="","",IF(AL7>0,AL7,0)) | EF7: =IF(AI7="","",IF(AL7<=0,AL7,0)) | EG7: =IF(AI7="","",IF(AI7>0,(BF7*AH7),0)) | EH7: =IF(AI7="","",IF(AI7<=0,(BF7*AH7),0)) | EI7: =IF(AI7="","",IF(AI7>0,(BF7*S7),0)) | EJ7: =IF(AI7="","",IF(AI7<=0,(BF7*S7),0)) | EK7: =IF(AI7="","",IF(AL7>0,1,0)) | EL7: =IF(AI7="","",IF(AL7<=0,1,0)) | EM7: =IF(AND(EN7=1,OR(AND(ER7>=0.5%,ER7<=1.5%),AND(ER7<=-0.5%,ER7>=-1.5%)),ES7>=0.5%),CONCATENATE("Long ",B7),IF(AND(EN7=2,OR(AND(ER7>=0.5%,ER7<=1.5%),AND(ER7<=-0.5%,ER7>=-1.5%)),ES7>=0.5%),CONCATENATE("Short ",B7),"Do Not Trade")) -> Do Not Trade | EN7: =IF(OR(EO7="",EP7=""),"",IF(BC7>=(EO7+'Base Data'!$D$14),1,IF(BC7<=(EP7-'Base Data'!$D$14),2,0))) -> 0 | EO7: =BH7 -> 10643.95 | EP7: =BI7 -> 10571.1 | EQ7: =IF(AI7="","",IF(AI7>0,IF(BC7<EP7,"Exit Long & Go Short",IF(BC7>(AI7+(EO7-EP7)),"Exit - TP","Hold")),IF(AI7<0,IF(BC7>EO7,"Exit Short & Go Long",IF(BC7<(-AI7-(EO7-EP7)),"Exit - TP","Hold"))))) | ER7: =(BC7-BM7)/BM7 -> 0.10020098 | ES7: =IF(OR(EO7<>"",EP7<>""),(EO7-EP7)/BG7,(BH7-BI7)/BG7) -> 0.0068719932 | ET7: =IF(AND(EU7="",EV7="",EW7="",EX7=""),"",IF(AND(EU7<(80%*EX7),EV7<(80%*EX7),EW7<(80%*EX7)),0,IF(AND(EU7>=(80%*EX7),EV7<(80%*EX7),EW7<(80%*EX7)),5,IF(AND(EU7<(80%*EX7),EV7>=(80%*EX7),EW7<(80%*EX7)),10,IF(AND(EU7<(80%*EX7),EV7<(80%*EX7),EW7>=(80%*EX7)),15,IF(AND(EU7>=(80%*EX7),EV7>=(80%*EX7),EW7<(80%*EX7)),20,IF(AND(EU7>=(80%*EX7),EV7<(80%*EX7),EW7>=(80%*EX7)),25,IF(AND(EU7<(80%*EX7),EV7>=(80%*EX7),EW7>=(80%*EX7)),30,IF(AND(EU7>=(80%*EX7),EV7>=(80%*EX7),EW7>=(80%*EX7)),35,"Check"))))))))) -> 35 | EU7: ='BNF-Nifty'!$FM$69 -> 0.0075649755 | EV7: ='BNF-Nifty'!$FN$69 -> 0.0076803294 | EW7: ='BNF-Nifty'!$FO$69 -> 0.0067478588 | EX7: ='BNF-Nifty'!$FL$73 -> 0.0064854968 | EY7: =IF(OR(AND(EN7=1,OR(AND(ER7>=0.5%,ER7<=1.5%),AND(ER7<=-0.5%,ER7>=-1.5%)),ES7>=0.5%),AND(EN7=2,OR(AND(ER7>=0.5%,ER7<=1.5%),AND(ER7<=-0.5%,ER7>=-1.5%)),ES7>=0.5%)),1,0) -> 0 | EZ7: =IF(OR(EQ7="Exit Long & Go Short",EQ7="Exit Short & Go Long"),1,0) -> 0
A9: =A7+1 -> 3 | B9: AshokLey | C9: =IF(AND(I9=1,BD9<>0),BD9,IF(AND(I9=2,BB9<>0),BB9,BC9)) -> 94.4 | D9: =(BC9-BG9) -> 1.4 | E9: =(BC9-BM9) -> 1 | I9: =IF(OR(J9=0,K9=0),0,IF(AND(M9=1,N9="Up-BO"),IF(OR(AND(J9="PGDn",K9="D-CL"),AND(J9="FGDn",K9="D-L"),AND(J9="PGDn",K9="U-CO"),AND(J9="PGDn",K9="U-OL"),AND(J9="PGUp",K9="U-HC"),AND(J9="PGUp",K9="D-OC"),AND(J9="PGUp",K9="D-HO"),AND(J9="FGDn",K9="U-L")),1,IF(AND(M9=2,N9="Dn-BO"),IF(OR(AND(J9="PGDUp",K9="U-HC"),AND(J9="FGUp",K9="U-H"),AND(J9="PGUp",K9="D-OC"),AND(J9="PGUp",K9="D-HO"),AND(J9="PGDn",K9="D-CL"),AND(J9="PGDn",K9="U-CO"),AND(J9="PGDn",K9="U-OL"),AND(J9="FGUp",K9="D-H")),2,IF(AND(M9=1,N9="Dn2Up-BO"),1,IF(AND(M9=2,N9="Up2Dn-BO"),2,0))),0)),IF(AND(M9=1,N9="Up-BO"),IF(OR(AND(J9="PGDn",K9="D-CL"),AND(J9="FGDn",K9="D-L"),AND(J9="PGDn",K9="U-CO"),AND(J9="PGDn",K9="U-OL"),AND(J9="PGUp",K9="U-HC"),AND(J9="PGUp",K9="D-OC"),AND(J9="PGUp",K9="D-HO"),AND(J9="FGDn",K9="U-L")),1,IF(AND(M9=2,N9="Dn-BO"),IF(OR(AND(J9="PGDUp",K9="U-HC"),AND(J9="FGUp",K9="U-H"),AND(J9="PGUp",K9="D-OC"),AND(J9="PGUp",K9="D-HO"),AND(J9="PGDn",K9="D-CL"),AND(J9="PGDn",K9="U-CO"),AND(J9="PGDn",K9="U-OL"),AND(J9="FGUp",K9="D-H")),2,IF(AND(M9=1,N9="Dn2Up-BO"),1,IF(AND(M9=2,N9="Up2Dn-BO"),2,0))),0)),0))) -> 0 | J9: =IF(AND(BG9>BM9,BG9<=BK9),"PGUp",IF(AND(BG9>BM9,BG9>BK9),"FGUp",IF(AND(BG9<BM9,BG9>=BL9),"PGDn",IF(AND(BG9<BM9,BG9<BL9),"FGDn",0)))) -> PGDn | K9: =IF(BM9>BJ9,IF(BG9>BK9,"U-H",IF(AND(BG9<=BK9,BG9>BM9),"U-HC",IF(AND(BG9<BM9,BG9>=BJ9),"U-CO",IF(AND(BG9<BJ9,BG9>=BL9),"U-OL",IF(BG9<BL9,"U-L",0))))),IF(BM9<BJ9,IF(BG9>BK9,"D-H",IF(AND(BG9<=BK9,BG9>BJ9),"D-HO",IF(AND(BG9<=BJ9,BG9>BM9),"D-OC",IF(AND(BG9<BM9,BG9>=BL9),"D-CL",IF(BG9<BL9,"D-L",0))))),0)) -> U-CO | L9: =IF(BM9>BJ9,IF(BG9>BK9,"Fade-Short",IF(AND(BG9<=BK9,BG9>BM9),"Fade-Short",IF(AND(BG9<BM9,BG9>=BJ9),"Fade-Long",IF(AND(BG9<BJ9,BG9>=BL9),"Fade-Long",IF(BG9<BL9,"GA-Short",0))))),IF(BM9<BJ9,IF(BG9>BK9,"GA-Long",IF(AND(BG9<=BK9,BG9>BJ9),"Fade-Short",IF(AND(BG9<=BJ9,BG9>BM9),"Fade-Short",IF(AND(BG9<BM9,BG9>=BL9),"Fade-Long",IF(BG9<BL9,"Fade-Long",0))))),0)) -> Fade-Long | M9: =IF(BG9=BI9,1,IF(BG9=BH9,2,0)) -> 0 | N9: =IF(AND(BG9<BK9,BC9>BK9),"Up-BO",IF(AND(BG9>BL9,BC9<BL9),"Dn-BO",IF(AND(J9="FGDn",BC9>BL9),"Dn2Up-BO",IF(AND(J9="FGUp",BC9<BK9),"Up2Dn-BO",0)))) -> Up-BO | O9: =IF(AND((IF(BV9>BW9,1,-1)>0),(IF(CB9>CC9,1,-1)>0)),1,IF(AND((IF(BV9>BW9,1,-1)<0),(IF(CB9>CC9,1,-1)<0)),2,0)) -> 0 | P9: =IF(BC9>(BH9-(BG9*0.5%)),1,IF(BC9<(BI9+(BG9*0.5%)),2,0)) -> 1 | Q9: =IF(C9>((BG9+BK9+BL9+BM9)/4),1,IF(C9<((BG9+BK9+BL9+BM9)/4),2,0)) -> 1 | R9: =IF((BS9>BT9),1,0) -> 1 | S9: =DS9 -> 0 | T9: ='Ashok-AsianP'!$ES$69 -> 0.98020726 | U9: =IF(S9<>0,T9,"-") -> - | V9: =IF(U9="-","-",_xlfn.RANK.EQ(U9,$U$5:$U$12,0)) -> - | W9: =IF(U9="-","-",_xlfn.RANK.EQ(U9,$U$5:$U$12,1)) -> - | X9: ='Ashok-AsianP'!$FI$69 -> T-R | Y9: ='Ashok-AsianP'!$FF$69 -> 2 | Z9: ='Ashok-AsianP'!$DP$69 -> 0.039765198 | AA9: ='Ashok-AsianP'!$EH$69 -> 0.040639285 | AB9: ='Ashok-AsianP'!$ER$69 -> 1.8626455 | AC9: =_xlfn.RANK.AVG(AB9,$AB$5:$AB$12,0) -> 3 | AD9: =_xlfn.RANK.AVG(AB9,$AB$5:$AB$12,1) -> 2 | AE9: =IF(AND(BC9>BU9,BC9>BV9,BZ9>=CA9,BX9>BY9),"1. Strong Up-R",IF(AND(BC9>BU9,BC9>BV9,BZ9>=CA9,BX9=BY9),"1. Strong Up-F",IF(AND(BC9>BU9,BC9>BV9,BZ9>=CA9,BX9<BY9),"1. Strong Up-D",IF(AND(BC9>BU9,BC9>BV9,BZ9<CA9,BX9>BY9),"2. Weak Up-R",IF(AND(BC9>BU9,BC9>BV9,BZ9<CA9,BX9=BY9),"2. Weak Up-F",IF(AND(BC9>BU9,BC9>BV9,BZ9<CA9,BX9<BY9),"2. Weak Up-D",IF(AND(BC9<BU9,BC9<BV9,BZ9<=CA9,BX9<BY9),"1. Strong Dn-D",IF(AND(BC9<BU9,BC9<BV9,BZ9<=CA9,BX9=BY9),"1. Strong Dn-F",IF(AND(BC9<BU9,BC9<BV9,BZ9<=CA9,BX9>BY9),"1. Strong Dn-R",IF(AND(BC9<BU9,BC9<BV9,BZ9>CA9,BX9<BY9),"2. Weak Dn-D",IF(AND(BC9<BU9,BC9<BV9,BZ9>CA9,BX9=BY9),"2. Weak Dn-F",IF(AND(BC9<BU9,BC9<BV9,BZ9>CA9,BX9>BY9),"2. Weak Dn-R","-")))))))))))) -> 1. Strong Up-R | AF9: =IF(CE9>CH9,"MFI Nr. Max. Level",IF(CE9<CI9,"MFI Nr. Min. Level",IF(AND(BC9>BU9,CB9>CC9,CC9>CD9,CB9>=0,CE9>CJ9,CE9>CF9,CE9>=50,CF9>=50),"1. Ultimate Up - R",IF(AND(BC9>BU9,CB9>CC9,CC9>CD9,CB9>=0,CE9>CJ9,CE9=CF9,CE9>=50,CF9>=50),"1. Ultimate Up - F",IF(AND(BC9>BU9,CB9>CC9,CC9>CD9,CB9>=0,CE9>CJ9,CE9<CF9,CE9>=50,CF9>=50),"1. Ultimate Up - D",IF(AND(BC9>BU9,CB9>CC9,CC9>CD9,CB9<0,CE9>CJ9,CE9>CF9,CE9>=50,CF9>=50),"2. Extreme Up - R",IF(AND(BC9>BU9,CB9>CC9,CC9>CD9,CB9<0,CE9>CJ9,CE9=CF9,CE9>=50,CF9>=50),"2. Extreme Up - F",IF(AND(BC9>BU9,CB9>CC9,CC9>CD9,CB9<0,CE9>CJ9,CE9<CF9,CE9>=50,CF9>=50),"2. Extreme Up - D",IF(AND(BC9>BU9,CB9>CC9,CC9>CD9,CB9>=0,CE9>CJ9,CE9>CF9,CE9>=50,CF9<50),"3. Uber Up",IF(AND(BC9>BU9,CB9>CC9,CC9>CD9,CB9<0,CE9>CJ9,CE9>CF9,CE9>=50,CF9<50),"4. Ultra Up",IF(AND(BC9>BU9,CB9>CC9,CC9>CD9,CB9>=0,CE9>CJ9,CE9>CF9,CE9<50),"5. Hyper Up - R",IF(AND(BC9>BU9,CB9>CC9,CC9>CD9,CB9>=0,CE9>CJ9,CE9=CF9,CE9<50),"5. Hyper Up - F",IF(AND(BC9>BU9,CB9>CC9,CC9>CD9,CB9>=0,CE9>CJ9,CE9<CF9,CE9<50),"5. Hyper Up - D",IF(AND(BC9>BU9,CB9>CC9,CC9>CD9,CB9<0,CE9>CJ9,CE9>CF9,CE9<50),"6. Super Up - R",IF(AND(BC9>BU9,CB9>CC9,CC9>CD9,CB9<0,CE9>CJ9,CE9=CF9,CE9<50),"6. Super Up - F",IF(AND(BC9>BU9,CB9>CC9,CC9>CD9,CB9<0,CE9>CJ9,CE9<CF9,CE9<50),"6. Super Up - D",IF(AND(BC9>BU9,CB9>CC9,CC9<CD9,CB9>=0,CE9>CF9,CE9>=50,CF9>=50),"7. Extra Strong Up - R",IF(AND(BC9>BU9,CB9>CC9,CC9<CD9,CB9>=0,CE9=CF9,CE9>=50,CF9>=50),"7. Extra Strong Up - F",IF(AND(BC9>BU9,CB9>CC9,CC9<CD9,CB9>=0,CE9<CF9,CE9>=50,CF9>=50),"7. Extra Strong Up - D",IF(AND(BC9>BU9,CB9>CC9,CC9<CD9,CB9>=0,CE9>CF9,CE9>=50,CF9<50),"8. Strong Up",IF(AND(BC9>BU9,CB9>CC9,CC9<CD9,CB9<0,CE9>CJ9,CE9>CF9,CE9>=50,CF9>=50),"9. Up - R",IF(AND(BC9>BU9,CB9>CC9,CC9<CD9,CB9<0,CE9>CJ9,CE9=CF9,CE9>=50,CF9>=50),"9. Up - F",IF(AND(BC9>BU9,CB9>CC9,CC9<CD9,CB9<0,CE9>CJ9,CE9<CF9,CE9>=50,CF9>=50),"9. Up - D",IF(AND(BC9>BU9,CB9>CC9,CC9<CD9,CB9<0,CE9>CF9,CE9>=50,CF9>=50),"10. Weak Up - R",IF(AND(BC9>BU9,CB9>CC9,CC9<CD9,CB9<0,CE9=CF9,CE9>=50,CF9>=50),"10. Weak Up - F",IF(AND(BC9>BU9,CB9>CC9,CC9<CD9,CB9<0,CE9<CF9,CE9>=50,CF9>=50),"10. Weak Up - D",IF(AND(BC9>BU9,CB9>CC9,CC9<CD9,CB9<0,CE9>CF9,CE9>=50,CF9<50),"11. Extra Weak Up",IF(AND(BC9>BU9,CB9>CC9,CC9>CD9,CE9>CF9,CE9<50,CF9<50),"12. Very Weak Up - R",IF(AND(BC9>BU9,CB9>CC9,CC9>CD9,CE9=CF9,CE9<50,CF9<50),"12. Very Weak Up - F",IF(AND(BC9>BU9,CB9>CC9,CC9>CD9,CE9<CF9,CE9<50,CF9<50),"12. Very Weak Up - D",IF(AND(BC9<BU9,CB9<CC9,CC9<CD9,CB9<=0,CE9<CJ9,CE9<CF9,CE9<50,CF9<50),"1. Ultimate Dn - D",IF(AND(BC9<BU9,CB9<CC9,CC9<CD9,CB9<=0,CE9<CJ9,CE9=CF9,CE9<50,CF9<50),"1. Ultimate Dn - F",IF(AND(BC9<BU9,CB9<CC9,CC9<CD9,CB9<=0,CE9<CJ9,CE9>CF9,CE9<50,CF9<50),"1. Ultimate Up - R",IF(AND(BC9<BU9,CB9<CC9,CC9<CD9,CB9>0,CE9<CJ9,CE9<CF9,CE9<50,CF9<50),"2. Extreme Dn - D",IF(AND(BC9<BU9,CB9<CC9,CC9<CD9,CB9>0,CE9<CJ9,CE9=CF9,CE9<50,CF9<50),"2. Extreme Dn - F",IF(AND(BC9<BU9,CB9<CC9,CC9<CD9,CB9>0,CE9<CJ9,CE9>CF9,CE9<50,CF9<50),"2. Extreme Dn - R",IF(AND(BC9<BU9,CB9<CC9,CC9<CD9,CB9<=0,CE9<CJ9,CE9<CF9,CE9<50,CF9>=50),"3. Uber Dn",IF(AND(BC9<BU9,CB9<CC9,CC9<CD9,CB9>0,CE9<CJ9,CE9<CF9,CE9<50,CF9>=50),"4. Ultra Dn",IF(AND(BC9<BU9,CB9<CC9,CC9<CD9,CB9<=0,CE9<CJ9,CE9<CF9,CE9>=50),"5. Hyper Dn - D",IF(AND(BC9<BU9,CB9<CC9,CC9<CD9,CB9<=0,CE9<CJ9,CE9=CF9,CE9>=50),"5. Hyper Dn - F",IF(AND(BC9<BU9,CB9<CC9,CC9<CD9,CB9<=0,CE9<CJ9,CE9>CF9,CE9>=50),"5. Hyper Dn - R",IF(AND(BC9<BU9,CB9<CC9,CC9<CD9,CB9>0,CE9<CJ9,CE9<CF9,CE9>=50),"6. Super Dn - D",IF(AND(BC9<BU9,CB9<CC9,CC9<CD9,CB9>0,CE9<CJ9,CE9=CF9,CE9>=50),"6. Super Dn - F",IF(AND(BC9<BU9,CB9<CC9,CC9<CD9,CB9>0,CE9<CJ9,CE9>CF9,CE9>=50),"6. Super Dn - R",IF(AND(BC9<BU9,CB9<CC9,CC9>CD9,CB9<=0,CE9<CF9,CE9<50,CF9<50),"7. Extra Strong Dn - D",IF(AND(BC9<BU9,CB9<CC9,CC9>CD9,CB9<=0,CE9=CF9,CE9<50,CF9<50),"7. Extra Strong Dn - F",IF(AND(BC9<BU9,CB9<CC9,CC9>CD9,CB9<=0,CE9>CF9,CE9<50,CF9<50),"7. Extra Strong Dn - R",IF(AND(BC9<BU9,CB9<CC9,CC9>CD9,CB9<=0,CE9<CF9,CE9<50,CF9>=50),"8. Strong Dn",IF(AND(BC9<BU9,CB9<CC9,CC9>CD9,CB9>0,CE9<CJ9,CE9<CF9,CE9<50,CF9<50),"9. Dn - D",IF(AND(BC9<BU9,CB9<CC9,CC9>CD9,CB9>0,CE9<CJ9,CE9=CF9,CE9<50,CF9<50),"9. Dn - F",IF(AND(BC9<BU9,CB9<CC9,CC9>CD9,CB9>0,CE9<CJ9,CE9>CF9,CE9<50,CF9<50),"9. Dn - R",IF(AND(BC9<BU9,CB9<CC9,CC9>CD9,CB9>0,CE9<CF9,CE9<50,CF9<50),"10. Weak Dn - D",IF(AND(BC9<BU9,CB9<CC9,CC9>CD9,CB9>0,CE9=CF9,CE9<50,CF9<50),"10. Weak Dn - F",IF(AND(BC9<BU9,CB9<CC9,CC9>CD9,CB9>0,CE9>CF9,CE9<50,CF9<50),"10. Weak Dn - R",IF(AND(BC9<BU9,CB9<CC9,CC9>CD9,CB9>0,CE9<CF9,CE9<50,CF9>=50),"11. Extra Weak Dn",IF(AND(BC9<BU9,CB9<CC9,CC9<CD9,CE9<CF9,CE9>=50,CF9>=50),"12. Very Weak Dn - D",IF(AND(BC9<BU9,CB9<CC9,CC9<CD9,CE9=CF9,CE9>=50,CF9>=50),"12. Very Weak Dn - F",IF(AND(BC9<BU9,CB9<CC9,CC9<CD9,CE9>CF9,CE9>=50,CF9>=50),"12. Very Weak Dn - R","No Trend")))))))))))))))))))))))))))))))))))))))))))))))))))))))))) -> No Trend | AG9: =IF(BQ9>BR9,1,0) -> 0 | AH9: =DH9 -> 0 | AK9: =IF(AI9="","",IF(AI9>0,(C9-AI9),IF(AI9<0,(-AI9-C9),"Check"))) | AL9: =IF(AI9="","",(AY9-AX9)) | AM9: =IF(AI9<>"",AL9/AO9,"") | AO9: =IF(AI9<>"",(BF9*AH9),"") | AP9: =(C9*AH9*BE9) -> 0 | AQ9: =IF(AI9="","",(AP9*'Base Data'!$C$26*2)) | AR9: =IF(AI9="","",(AP9*'Base Data'!$D$26*2)) | AS9: =IF(AI9="","",((AQ9+AR9)*'Base Data'!$E$26)+(((AQ9+AR9)*'Base Data'!$E$26)*'Base Data'!$F$26)+(((AQ9+AR9)*'Base Data'!$E$26)*'Base Data'!$G$26)) | AT9: =IF(AI9="","",(AP9*'Base Data'!$H$27*2)) | AU9: =IF(AI9="","",(AP9*'Base Data'!$I$26*2)) | AV9: =IF(AI9="","",(AP9*'Base Data'!$J$26)) | AW9: =IF(AI9="","",(AP9*'Base Data'!$K$26*2)) | AX9: =IF(AI9="","",SUM(AQ9:AW9)) | AY9: =IF(AI9="","",IF(AI9>0,((C9-AI9)*AH9*BE9),IF(AI9<0,((-AI9-C9)*AH9*BE9),"Check"))) | AZ9: =IF(AI9="","",IF(AI9>0,1,IF(AI9<0,2,0))) | BA9: =CONCATENATE(B9,'Base Data'!$D$1) -> AshokLey18NovFut | BB9: 94.6 | BC9: 94.4 | BD9: 94.8 | BE9: =VLOOKUP(B9,'[3]Margin - NSE Fut (5Paisa)'!$A:$K,2,FALSE) -> 4000 | BF9: =VLOOKUP(B9,'[3]Margin - NSE Fut (5Paisa)'!$A:$K,11,FALSE) -> 70890 | BG9: ='Ashok-AsianP'!N69 -> 93 | BH9: ='Ashok-AsianP'!O69 -> 94.8 | BI9: ='Ashok-AsianP'!P69 -> 92.65 | BJ9: ='Ashok-AsianP'!$N$67 -> 92 | BK9: ='Ashok-AsianP'!$O$67 -> 93.8 | BL9: ='Ashok-AsianP'!$P$67 -> 91.65 | BM9: ='Ashok-AsianP'!$Q$67 -> 93.4 | BN9: =(BG9-BM9) -> -0.4 | BO9: =(BG9-BM9)/BM9 -> -0.0042826552 | BP9: ='Ashok-AsianP'!$AB$69 -> 0.24141069 | BQ9: ='Ashok-AsianP'!$R$69 -> 4000 | BR9: ='Ashok-AsianP'!$R$73 -> 4493.1905 | BS9: ='Ashok-AsianP'!$AO$69 -> 0.60350919 | BT9: ='Ashok-AsianP'!$AO$73 -> 0.50677009 | BU9: ='Ashok-AsianP'!$AU$69 -> 87.048785 | BV9: ='Ashok-AsianP'!$AZ$69 -> 90.188119 | BW9: ='Ashok-AsianP'!$AZ$67 -> 89.838461 | BX9: ='Ashok-AsianP'!$BE$69 -> 92.641307 | BY9: ='Ashok-AsianP'!$BE$67 -> 92.162392 | BZ9: =IF(BX9="","",(BC9-BX9)/BX9) -> 0.018983892 | CA9: =IF(BY9="","",(BM9-BY9)/BY9) -> 0.013428557 | CB9: ='Ashok-AsianP'!$CF$69 -> 0.59567751 | CC9: ='Ashok-AsianP'!$CF$67 -> 0.64363946 | CD9: ='Ashok-AsianP'!$CF$66 -> 0.75672579 | CE9: ='Ashok-AsianP'!$CV$69 -> 69.987294 | CF9: ='Ashok-AsianP'!$CV$67 -> 66.355511 | CG9: ='Ashok-AsianP'!$CV$66 -> 62.9643 | CH9: ='Ashok-AsianP'!$CT$73 -> 75 | CI9: ='Ashok-AsianP'!$CW$73 -> 27 | CJ9: ='Ashok-AsianP'!$CW$69 -> 52.995639 | CK9: ='Ashok-AsianP'!$CW$67 -> 52.246161 | CL9: ='Ashok-AsianP'!$CW$66 -> 51.453433 | CM9: ='Ashok-AsianP'!$CX$69 -> 56.956051 | CN9: ='Ashok-AsianP'!$CX$67 -> 55.673738 | CO9: =IF(AND(BC9>BU9,CG9<CL9,CF9>CK9,CE9>CJ9,CE9>CF9,CJ9>CK9),"M34-1",IF(AND(BC9<BU9,CG9>CL9,CF9<CK9,CE9<CJ9,CE9<CF9,CJ9<CK9),"M34-2",0)) -> 0 | CP9: =IF(AI9="",0,IF(AND(AJ9="M34-1",CF9>CN9,CE9<CM9),"Exit-Long",IF(AND(AJ9="M34-2",CF9<CN9,CE9>CM9),"Exit-Short","Hold"))) -> 0 | CQ9: ='Ashok-AsianP'!$BQ$69 -> 87.419748 | CR9: ='Ashok-AsianP'!$BQ$67 -> 87.182338 | CS9: ='Ashok-AsianP'!$BR$69 -> 89.687796 | CT9: ='Ashok-AsianP'!$BR$67 -> 89.351441 | CW9: ='Ashok-AsianP'!$BO$69 -> 88.987695 | CX9: ='Ashok-AsianP'!$BO$67 -> 88.70244 | CY9: ='Ashok-AsianP'!$BP$69 -> 93.531406 | CZ9: ='Ashok-AsianP'!$BP$67 -> 93.104412 | DC9: =IF(AND(BC9>BU9,BM9<CR9,BC9>CQ9,BC9>BM9),"P34-1",IF(AND(BC9<BU9,BM9>CR9,BC9<CQ9,BC9<BM9),"P34-2",IF(AND(BC9>BU9,BM9<CX9,BC9>CW9,BC9>BM9),"P13-1",IF(AND(BC9<BU9,BM9>CX9,BC9<CW9,BC9<BM9),"P13-2",0)))) -> 0 | DD9: =IF(AI9="",0,IF(OR(AND(AJ9="P34-1",BM9>CT9,BC9<CS9),AND(AJ9="P13-1",BM9>CZ9,BC9<CY9)),"Exit-Long",IF(OR(AND(AJ9="P34-2",BM9<CV9,BC9>CU9),AND(AJ9="P13-2",BM9<DB9,BC9>DA9)),"Exit-Short","Hold"))) -> 0 | DE9: =IF(AND(BC9>BU9,CG9<CL9,CF9>CK9,CE9>CJ9,CE9>CF9,CJ9>CK9),"M34-1",IF(AND(BC9<BU9,CG9>CL9,CF9<CK9,CE9<CJ9,CE9<CF9,CJ9<CK9),"M34-2",IF(AND(BC9>BU9,BM9<CR9,BC9>CQ9,BC9>BM9),"P34-1",IF(AND(BC9<BU9,BM9>CR9,BC9<CQ9,BC9<BM9),"P34-2",IF(AND(BC9>BU9,BM9<CX9,BC9>CW9,BC9>BM9),"P13-1",IF(AND(BC9<BU9,BM9>CX9,BC9<CW9,BC9<BM9),"P13-2",0)))))) -> 0 | DF9: =IF(AI9="",0,IF(OR(AND(AJ9="M34-1",CF9>CK9,CE9<CJ9),AND(AJ9="P34-1",BM9>CT9,BC9<CS9),AND(AJ9="P13-1",BM9>CZ9,BC9<CY9)),"Exit-Long",IF(OR(AND(AJ9="M34-2",CF9<CK9,CE9>CJ9),AND(AJ9="P34-2",BM9<CV9,BC9>CU9),AND(AJ9="P13-2",BM9<DB9,BC9>DA9)),"Exit-Short","Hold"))) -> 0 | DG9: ='Ashok-AsianP'!$DL$69 -> 3.7538347 | DH9: ='Ashok-AsianP'!$DO$69 -> 0 | DI9: =IF(AI9="","-",'Base Data'!$D$10*DG9) -> - | DJ9: =IF(DK9="-","-",IF(AI9>0,(DK9-AI9),IF(AI9<0,(DK9+AI9),"Check"))) -> - | DK9: =IF(AI9="","-",IF(AI9>0,(AI9-DI9),IF(AI9<0,(-AI9+DI9),"Check"))) -> - | DL9: =IF(AI9="","-",IF(AI9>0,(AI9+(1*'Base Data'!$D$12*DG9)),IF(AI9<0,(-AI9-(1*'Base Data'!$D$12*DG9)),"Check"))) -> - | DM9: =IF(AI9="","-",IF(AI9>0,(AI9+(2*'Base Data'!$D$12*DG9)),IF(AI9<0,(-AI9-(2*'Base Data'!$D$12*DG9)),"Check"))) -> - | DN9: =IF(AI9="","-",IF(AI9>0,(AI9+(3*'Base Data'!$D$12*DG9)),IF(AI9<0,(-AI9-(3*'Base Data'!$D$12*DG9)),"Check"))) -> - | DO9: =IF(AI9="","-",IF(AI9>0,(AI9+(4*'Base Data'!$D$12*DG9)),IF(AI9<0,(-AI9-(4*'Base Data'!$D$12*DG9)),"Check"))) -> - | DP9: =IF(AI9="","-",IF(AI9>0,(AI9+DI9),IF(AI9<0,(-AI9-DI9),"Check"))) -> - | DQ9: =IF(DP9="-","-",IF(AI9>0,(DP9-AI9),IF(AI9<0,(DP9+AI9),"Check"))) -> - | DR9: ='Ashok-AsianP'!$ED$69 -> 3.8363485 | DS9: ='Ashok-AsianP'!$EG$69 -> 0 | DT9: =IF(AI9="","-",'Base Data'!$D$13*DR9) -> - | DU9: =IF(DV9="-","-",IF(AI9>0,(DV9-AI9),IF(AI9<0,(DV9+AI9),"Check"))) -> - | DV9: =IF(AI9="","-",IF(AI9>0,(AI9-DT9),IF(AI9<0,(-AI9+DT9),"Check"))) -> - | DW9: =IF(AI9="","-",IF(AI9>0,(AI9+DT9),IF(AI9<0,(-AI9-DT9),"Check"))) -> - | DX9: =IF(DW9="-","-",IF(AI9>0,(DW9-AI9),IF(AI9<0,(DW9+AI9),"Check"))) -> - | EE9: =IF(AI9="","",IF(AL9>0,AL9,0)) | EF9: =IF(AI9="","",IF(AL9<=0,AL9,0)) | EG9: =IF(AI9="","",IF(AI9>0,(BF9*AH9),0)) | EH9: =IF(AI9="","",IF(AI9<=0,(BF9*AH9),0)) | EI9: =IF(AI9="","",IF(AI9>0,(BF9*S9),0)) | EJ9: =IF(AI9="","",IF(AI9<=0,(BF9*S9),0)) | EK9: =IF(AI9="","",IF(AL9>0,1,0)) | EL9: =IF(AI9="","",IF(AL9<=0,1,0)) | EM9: =IF(AND(EN9=1,OR(AND(ER9>=0.5%,ER9<=1.5%),AND(ER9<=-0.5%,ER9>=-1.5%)),ES9>=0.5%),CONCATENATE("Long ",B9),IF(AND(EN9=2,OR(AND(ER9>=0.5%,ER9<=1.5%),AND(ER9<=-0.5%,ER9>=-1.5%)),ES9>=0.5%),CONCATENATE("Short ",B9),"Do Not Trade")) -> Do Not Trade | EN9: =IF(OR(EO9="",EP9=""),"",IF(BC9>=(EO9+'Base Data'!$D$14),1,IF(BC9<=(EP9-'Base Data'!$D$14),2,0))) -> 0 | EO9: =BH9 -> 94.8 | EP9: =BI9 -> 92.65 | EQ9: =IF(AI9="","",IF(AI9>0,IF(BC9<EP9,"Exit Long & Go Short",IF(BC9>(AI9+(EO9-EP9)),"Exit - TP","Hold")),IF(AI9<0,IF(BC9>EO9,"Exit Short & Go Long",IF(BC9<(-AI9-(EO9-EP9)),"Exit - TP","Hold"))))) | ER9: =(BC9-BM9)/BM9 -> 0.010706638 | ES9: =IF(OR(EO9<>"",EP9<>""),(EO9-EP9)/BG9,(BH9-BI9)/BG9) -> 0.02311828 | ET9: =IF(AND(EU9="",EV9="",EW9="",EX9=""),"",IF(AND(EU9<(80%*EX9),EV9<(80%*EX9),EW9<(80%*EX9)),0,IF(AND(EU9>=(80%*EX9),EV9<(80%*EX9),EW9<(80%*EX9)),5,IF(AND(EU9<(80%*EX9),EV9>=(80%*EX9),EW9<(80%*EX9)),10,IF(AND(EU9<(80%*EX9),EV9<(80%*EX9),EW9>=(80%*EX9)),15,IF(AND(EU9>=(80%*EX9),EV9>=(80%*EX9),EW9<(80%*EX9)),20,IF(AND(EU9>=(80%*EX9),EV9<(80%*EX9),EW9>=(80%*EX9)),25,IF(AND(EU9<(80%*EX9),EV9>=(80%*EX9),EW9>=(80%*EX9)),30,IF(AND(EU9>=(80%*EX9),EV9>=(80%*EX9),EW9>=(80%*EX9)),35,"Check"))))))))) -> 35 | EU9: ='Ashok-AsianP'!$EX$69 -> 0.038418909 | EV9: ='Ashok-AsianP'!$EY$69 -> 0.035183383 | EW9: ='Ashok-AsianP'!$EZ$69 -> 0.029175952 | EX9: ='Ashok-AsianP'!$EW$73 -> 0.024366132 | EY9: =IF(OR(AND(EN9=1,OR(AND(ER9>=0.5%,ER9<=1.5%),AND(ER9<=-0.5%,ER9>=-1.5%)),ES9>=0.5%),AND(EN9=2,OR(AND(ER9>=0.5%,ER9<=1.5%),AND(ER9<=-0.5%,ER9>=-1.5%)),ES9>=0.5%)),1,0) -> 0 | EZ9: =IF(OR(EQ9="Exit Long & Go Short",EQ9="Exit Short & Go Long"),1,0) -> 0
A11: =A9+1 -> 4 | B11: AsianPaint | C11: =IF(AND(I11=1,BD11<>0),BD11,IF(AND(I11=2,BB11<>0),BB11,BC11)) -> 1172.55 | D11: =(BC11-BG11) -> 3.4 | E11: =(BC11-BM11) -> 10 | J11: =IF(AND(BG11>BM11,BG11<=BK11),"PGUp",IF(AND(BG11>BM11,BG11>BK11),"FGUp",IF(AND(BG11<BM11,BG11>=BL11),"PGDn",IF(AND(BG11<BM11,BG11<BL11),"FGDn",0)))) -> PGUp | K11: =IF(BM11>BJ11,IF(BG11>BK11,"U-H",IF(AND(BG11<=BK11,BG11>BM11),"U-HC",IF(AND(BG11<BM11,BG11>=BJ11),"U-CO",IF(AND(BG11<BJ11,BG11>=BL11),"U-OL",IF(BG11<BL11,"U-L",0))))),IF(BM11<BJ11,IF(BG11>BK11,"D-H",IF(AND(BG11<=BK11,BG11>BJ11),"D-HO",IF(AND(BG11<=BJ11,BG11>BM11),"D-OC",IF(AND(BG11<BM11,BG11>=BL11),"D-CL",IF(BG11<BL11,"D-L",0))))),0)) -> U-HC | L11: =IF(BM11>BJ11,IF(BG11>BK11,"Fade-Short",IF(AND(BG11<=BK11,BG11>BM11),"Fade-Short",IF(AND(BG11<BM11,BG11>=BJ11),"Fade-Long",IF(AND(BG11<BJ11,BG11>=BL11),"Fade-Long",IF(BG11<BL11,"GA-Short",0))))),IF(BM11<BJ11,IF(BG11>BK11,"GA-Long",IF(AND(BG11<=BK11,BG11>BJ11),"Fade-Short",IF(AND(BG11<=BJ11,BG11>BM11),"Fade-Short",IF(AND(BG11<BM11,BG11>=BL11),"Fade-Long",IF(BG11<BL11,"Fade-Long",0))))),0)) -> Fade-Short | M11: =IF(BG11=BI11,1,IF(BG11=BH11,2,0)) -> 0 | N11: =IF(AND(BG11<BK11,BC11>BK11),"Up-BO",IF(AND(BG11>BL11,BC11<BL11),"Dn-BO",IF(AND(J11="FGDn",BC11>BL11),"Dn2Up-BO",IF(AND(J11="FGUp",BC11<BK11),"Up2Dn-BO",0)))) -> Up-BO | O11: =IF(AND((IF(BV11>BW11,1,-1)>0),(IF(CB11>CC11,1,-1)>0)),1,IF(AND((IF(BV11>BW11,1,-1)<0),(IF(CB11>CC11,1,-1)<0)),2,0)) -> 1 | P11: =IF(BC11>(BH11-(BG11*0.5%)),1,IF(BC11<(BI11+(BG11*0.5%)),2,0)) -> 2 | Q11: =IF(C11>((BG11+BK11+BL11+BM11)/4),1,IF(C11<((BG11+BK11+BL11+BM11)/4),2,0)) -> 1 | R11: =IF((BS11>BT11),1,0) -> 0 | S11: =DS11 -> 1 | T11: ='Ashok-AsianP'!$EU$69 -> 1.5090027 | U11: =IF(S11<>0,T11,"-") -> 1.5090027 | V11: =IF(U11="-","-",_xlfn.RANK.EQ(U11,$U$5:$U$12,0)) -> 1 | W11: =IF(U11="-","-",_xlfn.RANK.EQ(U11,$U$5:$U$12,1)) -> 1 | X11: ='Ashok-AsianP'!$FK$69 -> C-D | Y11: ='Ashok-AsianP'!$FG$69 -> 2 | Z11: ='Ashok-AsianP'!$DY$69 -> 0.022347519 | AA11: ='Ashok-AsianP'!$EQ$69 -> 0.019680846 | AB11: ='Ashok-AsianP'!$ET$69 -> 1.1105654 | AC11: =_xlfn.RANK.AVG(AB11,$AB$5:$AB$12,0) -> 4 | AD11: =_xlfn.RANK.AVG(AB11,$AB$5:$AB$12,1) -> 1 | AE11: =IF(AND(BC11>BU11,BC11>BV11,BZ11>=CA11,BX11>BY11),"1. Strong Up-R",IF(AND(BC11>BU11,BC11>BV11,BZ11>=CA11,BX11=BY11),"1. Strong Up-F",IF(AND(BC11>BU11,BC11>BV11,BZ11>=CA11,BX11<BY11),"1. Strong Up-D",IF(AND(BC11>BU11,BC11>BV11,BZ11<CA11,BX11>BY11),"2. Weak Up-R",IF(AND(BC11>BU11,BC11>BV11,BZ11<CA11,BX11=BY11),"2. Weak Up-F",IF(AND(BC11>BU11,BC11>BV11,BZ11<CA11,BX11<BY11),"2. Weak Up-D",IF(AND(BC11<BU11,BC11<BV11,BZ11<=CA11,BX11<BY11),"1. Strong Dn-D",IF(AND(BC11<BU11,BC11<BV11,BZ11<=CA11,BX11=BY11),"1. Strong Dn-F",IF(AND(BC11<BU11,BC11<BV11,BZ11<=CA11,BX11>BY11),"1. Strong Dn-R",IF(AND(BC11<BU11,BC11<BV11,BZ11>CA11,BX11<BY11),"2. Weak Dn-D",IF(AND(BC11<BU11,BC11<BV11,BZ11>CA11,BX11=BY11),"2. Weak Dn-F",IF(AND(BC11<BU11,BC11<BV11,BZ11>CA11,BX11>BY11),"2. Weak Dn-R","-")))))))))))) -> 1. Strong Up-R | AF11: =IF(CE11>CH11,"MFI Nr. Max. Level",IF(CE11<CI11,"MFI Nr. Min. Level",IF(AND(BC11>BU11,CB11>CC11,CC11>CD11,CB11>=0,CE11>CJ11,CE11>CF11,CE11>=50,CF11>=50),"1. Ultimate Up - R",IF(AND(BC11>BU11,CB11>CC11,CC11>CD11,CB11>=0,CE11>CJ11,CE11=CF11,CE11>=50,CF11>=50),"1. Ultimate Up - F",IF(AND(BC11>BU11,CB11>CC11,CC11>CD11,CB11>=0,CE11>CJ11,CE11<CF11,CE11>=50,CF11>=50),"1. Ultimate Up - D",IF(AND(BC11>BU11,CB11>CC11,CC11>CD11,CB11<0,CE11>CJ11,CE11>CF11,CE11>=50,CF11>=50),"2. Extreme Up - R",IF(AND(BC11>BU11,CB11>CC11,CC11>CD11,CB11<0,CE11>CJ11,CE11=CF11,CE11>=50,CF11>=50),"2. Extreme Up - F",IF(AND(BC11>BU11,CB11>CC11,CC11>CD11,CB11<0,CE11>CJ11,CE11<CF11,CE11>=50,CF11>=50),"2. Extreme Up - D",IF(AND(BC11>BU11,CB11>CC11,CC11>CD11,CB11>=0,CE11>CJ11,CE11>CF11,CE11>=50,CF11<50),"3. Uber Up",IF(AND(BC11>BU11,CB11>CC11,CC11>CD11,CB11<0,CE11>CJ11,CE11>CF11,CE11>=50,CF11<50),"4. Ultra Up",IF(AND(BC11>BU11,CB11>CC11,CC11>CD11,CB11>=0,CE11>CJ11,CE11>CF11,CE11<50),"5. Hyper Up - R",IF(AND(BC11>BU11,CB11>CC11,CC11>CD11,CB11>=0,CE11>CJ11,CE11=CF11,CE11<50),"5. Hyper Up - F",IF(AND(BC11>BU11,CB11>CC11,CC11>CD11,CB11>=0,CE11>CJ11,CE11<CF11,CE11<50),"5. Hyper Up - D",IF(AND(BC11>BU11,CB11>CC11,CC11>CD11,CB11<0,CE11>CJ11,CE11>CF11,CE11<50),"6. Super Up - R",IF(AND(BC11>BU11,CB11>CC11,CC11>CD11,CB11<0,CE11>CJ11,CE11=CF11,CE11<50),"6. Super Up - F",IF(AND(BC11>BU11,CB11>CC11,CC11>CD11,CB11<0,CE11>CJ11,CE11<CF11,CE11<50),"6. Super Up - D",IF(AND(BC11>BU11,CB11>CC11,CC11<CD11,CB11>=0,CE11>CF11,CE11>=50,CF11>=50),"7. Extra Strong Up - R",IF(AND(BC11>BU11,CB11>CC11,CC11<CD11,CB11>=0,CE11=CF11,CE11>=50,CF11>=50),"7. Extra Strong Up - F",IF(AND(BC11>BU11,CB11>CC11,CC11<CD11,CB11>=0,CE11<CF11,CE11>=50,CF11>=50),"7. Extra Strong Up - D",IF(AND(BC11>BU11,CB11>CC11,CC11<CD11,CB11>=0,CE11>CF11,CE11>=50,CF11<50),"8. Strong Up",IF(AND(BC11>BU11,CB11>CC11,CC11<CD11,CB11<0,CE11>CJ11,CE11>CF11,CE11>=50,CF11>=50),"9. Up - R",IF(AND(BC11>BU11,CB11>CC11,CC11<CD11,CB11<0,CE11>CJ11,CE11=CF11,CE11>=50,CF11>=50),"9. Up - F",IF(AND(BC11>BU11,CB11>CC11,CC11<CD11,CB11<0,CE11>CJ11,CE11<CF11,CE11>=50,CF11>=50),"9. Up - D",IF(AND(BC11>BU11,CB11>CC11,CC11<CD11,CB11<0,CE11>CF11,CE11>=50,CF11>=50),"10. Weak Up - R",IF(AND(BC11>BU11,CB11>CC11,CC11<CD11,CB11<0,CE11=CF11,CE11>=50,CF11>=50),"10. Weak Up - F",IF(AND(BC11>BU11,CB11>CC11,CC11<CD11,CB11<0,CE11<CF11,CE11>=50,CF11>=50),"10. Weak Up - D",IF(AND(BC11>BU11,CB11>CC11,CC11<CD11,CB11<0,CE11>CF11,CE11>=50,CF11<50),"11. Extra Weak Up",IF(AND(BC11>BU11,CB11>CC11,CC11>CD11,CE11>CF11,CE11<50,CF11<50),"12. Very Weak Up - R",IF(AND(BC11>BU11,CB11>CC11,CC11>CD11,CE11=CF11,CE11<50,CF11<50),"12. Very Weak Up - F",IF(AND(BC11>BU11,CB11>CC11,CC11>CD11,CE11<CF11,CE11<50,CF11<50),"12. Very Weak Up - D",IF(AND(BC11<BU11,CB11<CC11,CC11<CD11,CB11<=0,CE11<CJ11,CE11<CF11,CE11<50,CF11<50),"1. Ultimate Dn - D",IF(AND(BC11<BU11,CB11<CC11,CC11<CD11,CB11<=0,CE11<CJ11,CE11=CF11,CE11<50,CF11<50),"1. Ultimate Dn - F",IF(AND(BC11<BU11,CB11<CC11,CC11<CD11,CB11<=0,CE11<CJ11,CE11>CF11,CE11<50,CF11<50),"1. Ultimate Up - R",IF(AND(BC11<BU11,CB11<CC11,CC11<CD11,CB11>0,CE11<CJ11,CE11<CF11,CE11<50,CF11<50),"2. Extreme Dn - D",IF(AND(BC11<BU11,CB11<CC11,CC11<CD11,CB11>0,CE11<CJ11,CE11=CF11,CE11<50,CF11<50),"2. Extreme Dn - F",IF(AND(BC11<BU11,CB11<CC11,CC11<CD11,CB11>0,CE11<CJ11,CE11>CF11,CE11<50,CF11<50),"2. Extreme Dn - R",IF(AND(BC11<BU11,CB11<CC11,CC11<CD11,CB11<=0,CE11<CJ11,CE11<CF11,CE11<50,CF11>=50),"3. Uber Dn",IF(AND(BC11<BU11,CB11<CC11,CC11<CD11,CB11>0,CE11<CJ11,CE11<CF11,CE11<50,CF11>=50),"4. Ultra Dn",IF(AND(BC11<BU11,CB11<CC11,CC11<CD11,CB11<=0,CE11<CJ11,CE11<CF11,CE11>=50),"5. Hyper Dn - D",IF(AND(BC11<BU11,CB11<CC11,CC11<CD11,CB11<=0,CE11<CJ11,CE11=CF11,CE11>=50),"5. Hyper Dn - F",IF(AND(BC11<BU11,CB11<CC11,CC11<CD11,CB11<=0,CE11<CJ11,CE11>CF11,CE11>=50),"5. Hyper Dn - R",IF(AND(BC11<BU11,CB11<CC11,CC11<CD11,CB11>0,CE11<CJ11,CE11<CF11,CE11>=50),"6. Super Dn - D",IF(AND(BC11<BU11,CB11<CC11,CC11<CD11,CB11>0,CE11<CJ11,CE11=CF11,CE11>=50),"6. Super Dn - F",IF(AND(BC11<BU11,CB11<CC11,CC11<CD11,CB11>0,CE11<CJ11,CE11>CF11,CE11>=50),"6. Super Dn - R",IF(AND(BC11<BU11,CB11<CC11,CC11>CD11,CB11<=0,CE11<CF11,CE11<50,CF11<50),"7. Extra Strong Dn - D",IF(AND(BC11<BU11,CB11<CC11,CC11>CD11,CB11<=0,CE11=CF11,CE11<50,CF11<50),"7. Extra Strong Dn - F",IF(AND(BC11<BU11,CB11<CC11,CC11>CD11,CB11<=0,CE11>CF11,CE11<50,CF11<50),"7. Extra Strong Dn - R",IF(AND(BC11<BU11,CB11<CC11,CC11>CD11,CB11<=0,CE11<CF11,CE11<50,CF11>=50),"8. Strong Dn",IF(AND(BC11<BU11,CB11<CC11,CC11>CD11,CB11>0,CE11<CJ11,CE11<CF11,CE11<50,CF11<50),"9. Dn - D",IF(AND(BC11<BU11,CB11<CC11,CC11>CD11,CB11>0,CE11<CJ11,CE11=CF11,CE11<50,CF11<50),"9. Dn - F",IF(AND(BC11<BU11,CB11<CC11,CC11>CD11,CB11>0,CE11<CJ11,CE11>CF11,CE11<50,CF11<50),"9. Dn - R",IF(AND(BC11<BU11,CB11<CC11,CC11>CD11,CB11>0,CE11<CF11,CE11<50,CF11<50),"10. Weak Dn - D",IF(AND(BC11<BU11,CB11<CC11,CC11>CD11,CB11>0,CE11=CF11,CE11<50,CF11<50),"10. Weak Dn - F",IF(AND(BC11<BU11,CB11<CC11,CC11>CD11,CB11>0,CE11>CF11,CE11<50,CF11<50),"10. Weak Dn - R",IF(AND(BC11<BU11,CB11<CC11,CC11>CD11,CB11>0,CE11<CF11,CE11<50,CF11>=50),"11. Extra Weak Dn",IF(AND(BC11<BU11,CB11<CC11,CC11<CD11,CE11<CF11,CE11>=50,CF11>=50),"12. Very Weak Dn - D",IF(AND(BC11<BU11,CB11<CC11,CC11<CD11,CE11=CF11,CE11>=50,CF11>=50),"12. Very Weak Dn - F",IF(AND(BC11<BU11,CB11<CC11,CC11<CD11,CE11>CF11,CE11>=50,CF11>=50),"12. Very Weak Dn - R","No Trend")))))))))))))))))))))))))))))))))))))))))))))))))))))))))) -> 1. Ultimate Up - R | AG11: =IF(BQ11>BR11,1,0) -> 0 | AH11: =DH11 -> 0 | AK11: =IF(AI11="","",IF(AI11>0,(C11-AI11),IF(AI11<0,(-AI11-C11),"Check"))) | AL11: =IF(AI11="","",(AY11-AX11)) | AM11: =IF(AI11<>"",AL11/AO11,"") | AO11: =IF(AI11<>"",(BF11*AH11),"") | AP11: =(C11*AH11*BE11) -> 0 | AQ11: =IF(AI11="","",(AP11*'Base Data'!$C$26*2)) | AR11: =IF(AI11="","",(AP11*'Base Data'!$D$26*2)) | AS11: =IF(AI11="","",((AQ11+AR11)*'Base Data'!$E$26)+(((AQ11+AR11)*'Base Data'!$E$26)*'Base Data'!$F$26)+(((AQ11+AR11)*'Base Data'!$E$26)*'Base Data'!$G$26)) | AT11: =IF(AI11="","",(AP11*'Base Data'!$H$27*2)) | AU11: =IF(AI11="","",(AP11*'Base Data'!$I$26*2)) | AV11: =IF(AI11="","",(AP11*'Base Data'!$J$26)) | AW11: =IF(AI11="","",(AP11*'Base Data'!$K$26*2)) | AX11: =IF(AI11="","",SUM(AQ11:AW11)) | AY11: =IF(AI11="","",IF(AI11>0,((C11-AI11)*AH11*BE11),IF(AI11<0,((-AI11-C11)*AH11*BE11),"Check"))) | AZ11: =IF(AI11="","",IF(AI11>0,1,IF(AI11<0,2,0))) | BA11: =CONCATENATE(B11,'Base Data'!$D$1) -> AsianPaint18NovFut | BB11: 1174 | BC11: 1172.55 | BD11: 1176 | BE11: =VLOOKUP(B11,'[3]Margin - NSE Fut (5Paisa)'!$A:$K,2,FALSE) -> 600 | BF11: =VLOOKUP(B11,'[3]Margin - NSE Fut (5Paisa)'!$A:$K,11,FALSE) -> 127848 | BG11: ='Ashok-AsianP'!T69 -> 1169.15 | BH11: ='Ashok-AsianP'!U69 -> 1182.35 | BI11: ='Ashok-AsianP'!V69 -> 1169 | BJ11: ='Ashok-AsianP'!$T$67 -> 1159.15 | BK11: ='Ashok-AsianP'!$U$67 -> 1172.35 | BL11: ='Ashok-AsianP'!$V$67 -> 1159 | BM11: ='Ashok-AsianP'!$W$67 -> 1162.55 | BN11: =(BG11-BM11) -> 6.6 | BO11: =(BG11-BM11)/BM11 -> 0.0056771752 | BP11: ='Ashok-AsianP'!$AC$69 -> 0.13592105 | BQ11: ='Ashok-AsianP'!$X$69 -> 3000 | BR11: ='Ashok-AsianP'!$X$73 -> 3270.0952 | BS11: ='Ashok-AsianP'!$AS$69 -> 0.3937778 | BT11: ='Ashok-AsianP'!$AS$73 -> 0.4001177 | BU11: ='Ashok-AsianP'!$AW$69 -> 1108.326 | BV11: ='Ashok-AsianP'!$BH$69 -> 1142.305 | BW11: ='Ashok-AsianP'!$BH$67 -> 1137.4401 | BX11: ='Ashok-AsianP'!$BM$69 -> 1159.2425 | BY11: ='Ashok-AsianP'!$BM$67 -> 1149.5578 | BZ11: =IF(BX11="","",(BC11-BX11)/BX11) -> 0.011479463 | CA11: =IF(BY11="","",(BM11-BY11)/BY11) -> 0.01130187 | CB11: ='Ashok-AsianP'!$CO$69 -> 2.5742273 | CC11: ='Ashok-AsianP'!$CO$67 -> 0.77226194 | CD11: ='Ashok-AsianP'!$CO$66 -> -0.47039641 | CE11: ='Ashok-AsianP'!$DE$69 -> 58.185333 | CF11: ='Ashok-AsianP'!$DE$67 -> 51.04509 | CG11: ='Ashok-AsianP'!$DE$66 -> 45.330989 | CH11: ='Ashok-AsianP'!$DC$73 -> 83 | CI11: ='Ashok-AsianP'!$DF$73 -> 33 | CJ11: ='Ashok-AsianP'!$DF$69 -> 56.454643 | CK11: ='Ashok-AsianP'!$DF$67 -> 56.617248 | CL11: ='Ashok-AsianP'!$DF$66 -> 56.909436 | CM11: ='Ashok-AsianP'!$DG$69 -> 54.682912 | CN11: ='Ashok-AsianP'!$DG$67 -> 55.545673 | CO11: =IF(AND(BC11>BU11,CG11<CL11,CF11>CK11,CE11>CJ11,CE11>CF11,CJ11>CK11),"M34-1",IF(AND(BC11<BU11,CG11>CL11,CF11<CK11,CE11<CJ11,CE11<CF11,CJ11<CK11),"M34-2",0)) -> 0 | CP11: =IF(AI11="",0,IF(AND(AJ11="M34-1",CF11>CN11,CE11<CM11),"Exit-Long",IF(AND(AJ11="M34-2",CF11<CN11,CE11>CM11),"Exit-Short","Hold"))) -> 0 | CQ11: ='Ashok-AsianP'!$BV$69 -> 1125.9313 | CR11: ='Ashok-AsianP'!$BV$67 -> 1124.0925 | CS11: ='Ashok-AsianP'!$BW$69 -> 1135.5281 | CT11: ='Ashok-AsianP'!$BW$67 -> 1132.9402 | CW11: ='Ashok-AsianP'!$BT$69 -> 1133.9714 | CX11: ='Ashok-AsianP'!$BT$67 -> 1131.7769 | CY11: ='Ashok-AsianP'!$BU$69 -> 1161.0819 | CZ11: ='Ashok-AsianP'!$BU$67 -> 1154.9597 | DC11: =IF(AND(BC11>BU11,BM11<CR11,BC11>CQ11,BC11>BM11),"P34-1",IF(AND(BC11<BU11,BM11>CR11,BC11<CQ11,BC11<BM11),"P34-2",IF(AND(BC11>BU11,BM11<CX11,BC11>CW11,BC11>BM11),"P13-1",IF(AND(BC11<BU11,BM11>CX11,BC11<CW11,BC11<BM11),"P13-2",0)))) -> 0 | DD11: =IF(AI11="",0,IF(OR(AND(AJ11="P34-1",BM11>CT11,BC11<CS11),AND(AJ11="P13-1",BM11>CZ11,BC11<CY11)),"Exit-Long",IF(OR(AND(AJ11="P34-2",BM11<CV11,BC11>CU11),AND(AJ11="P13-2",BM11<DB11,BC11>DA11)),"Exit-Short","Hold"))) -> 0 | DE11: =IF(AND(BC11>BU11,CG11<CL11,CF11>CK11,CE11>CJ11,CE11>CF11,CJ11>CK11),"M34-1",IF(AND(BC11<BU11,CG11>CL11,CF11<CK11,CE11<CJ11,CE11<CF11,CJ11<CK11),"M34-2",IF(AND(BC11>BU11,BM11<CR11,BC11>CQ11,BC11>BM11),"P34-1",IF(AND(BC11<BU11,BM11>CR11,BC11<CQ11,BC11<BM11),"P34-2",IF(AND(BC11>BU11,BM11<CX11,BC11>CW11,BC11>BM11),"P13-1",IF(AND(BC11<BU11,BM11>CX11,BC11<CW11,BC11<BM11),"P13-2",0)))))) -> 0 | DF11: =IF(AI11="",0,IF(OR(AND(AJ11="M34-1",CF11>CK11,CE11<CJ11),AND(AJ11="P34-1",BM11>CT11,BC11<CS11),AND(AJ11="P13-1",BM11>CZ11,BC11<CY11)),"Exit-Long",IF(OR(AND(AJ11="M34-2",CF11<CK11,CE11>CJ11),AND(AJ11="P34-2",BM11<CV11,BC11>CU11),AND(AJ11="P13-2",BM11<DB11,BC11>DA11)),"Exit-Short","Hold"))) -> 0 | DG11: ='Ashok-AsianP'!$DU$69 -> 26.203584 | DH11: ='Ashok-AsianP'!$DX$69 -> 0 | DI11: =IF(AI11="","-",'Base Data'!$D$10*DG11) -> - | DJ11: =IF(DK11="-","-",IF(AI11>0,(DK11-AI11),IF(AI11<0,(DK11+AI11),"Check"))) -> - | DK11: =IF(AI11="","-",IF(AI11>0,(AI11-DI11),IF(AI11<0,(-AI11+DI11),"Check"))) -> - | DL11: =IF(AI11="","-",IF(AI11>0,(AI11+(1*'Base Data'!$D$12*DG11)),IF(AI11<0,(-AI11-(1*'Base Data'!$D$12*DG11)),"Check"))) -> - | DM11: =IF(AI11="","-",IF(AI11>0,(AI11+(2*'Base Data'!$D$12*DG11)),IF(AI11<0,(-AI11-(2*'Base Data'!$D$12*DG11)),"Check"))) -> - | DN11: =IF(AI11="","-",IF(AI11>0,(AI11+(3*'Base Data'!$D$12*DG11)),IF(AI11<0,(-AI11-(3*'Base Data'!$D$12*DG11)),"Check"))) -> - | DO11: =IF(AI11="","-",IF(AI11>0,(AI11+(4*'Base Data'!$D$12*DG11)),IF(AI11<0,(-AI11-(4*'Base Data'!$D$12*DG11)),"Check"))) -> - | DP11: =IF(AI11="","-",IF(AI11>0,(AI11+DI11),IF(AI11<0,(-AI11-DI11),"Check"))) -> - | DQ11: =IF(DP11="-","-",IF(AI11>0,(DP11-AI11),IF(AI11<0,(DP11+AI11),"Check"))) -> - | DR11: ='Ashok-AsianP'!$EM$69 -> 23.076776 | DS11: ='Ashok-AsianP'!$EP$69 -> 1 | DT11: =IF(AI11="","-",'Base Data'!$D$13*DR11) -> - | DU11: =IF(DV11="-","-",IF(AI11>0,(DV11-AI11),IF(AI11<0,(DV11+AI11),"Check"))) -> - | DV11: =IF(AI11="","-",IF(AI11>0,(AI11-DT11),IF(AI11<0,(-AI11+DT11),"Check"))) -> - | DW11: =IF(AI11="","-",IF(AI11>0,(AI11+DT11),IF(AI11<0,(-AI11-DT11),"Check"))) -> - | DX11: =IF(DW11="-","-",IF(AI11>0,(DW11-AI11),IF(AI11<0,(DW11+AI11),"Check"))) -> - | EE11: =IF(AI11="","",IF(AL11>0,AL11,0)) | EF11: =IF(AI11="","",IF(AL11<=0,AL11,0)) | EG11: =IF(AI11="","",IF(AI11>0,(BF11*AH11),0)) | EH11: =IF(AI11="","",IF(AI11<=0,(BF11*AH11),0)) | EI11: =IF(AI11="","",IF(AI11>0,(BF11*S11),0)) | EJ11: =IF(AI11="","",IF(AI11<=0,(BF11*S11),0)) | EK11: =IF(AI11="","",IF(AL11>0,1,0)) | EL11: =IF(AI11="","",IF(AL11<=0,1,0)) | EM11: =IF(AND(EN11=1,OR(AND(ER11>=0.5%,ER11<=1.5%),AND(ER11<=-0.5%,ER11>=-1.5%)),ES11>=0.5%),CONCATENATE("Long ",B11),IF(AND(EN11=2,OR(AND(ER11>=0.5%,ER11<=1.5%),AND(ER11<=-0.5%,ER11>=-1.5%)),ES11>=0.5%),CONCATENATE("Short ",B11),"Do Not Trade")) -> Do Not Trade | EN11: =IF(OR(EO11="",EP11=""),"",IF(BC11>=(EO11+'Base Data'!$D$14),1,IF(BC11<=(EP11-'Base Data'!$D$14),2,0))) -> 0 | EO11: =BH11 -> 1182.35 | EP11: =BI11 -> 1169 | EQ11: =IF(AI11="","",IF(AI11>0,IF(BC11<EP11,"Exit Long & Go Short",IF(BC11>(AI11+(EO11-EP11)),"Exit - TP","Hold")),IF(AI11<0,IF(BC11>EO11,"Exit Short & Go Long",IF(BC11<(-AI11-(EO11-EP11)),"Exit - TP","Hold"))))) | ER11: =(BC11-BM11)/BM11 -> 0.0086017806 | ES11: =IF(OR(EO11<>"",EP11<>""),(EO11-EP11)/BG11,(BH11-BI11)/BG11) -> 0.011418552 | ET11: =IF(AND(EU11="",EV11="",EW11="",EX11=""),"",IF(AND(EU11<(80%*EX11),EV11<(80%*EX11),EW11<(80%*EX11)),0,IF(AND(EU11>=(80%*EX11),EV11<(80%*EX11),EW11<(80%*EX11)),5,IF(AND(EU11<(80%*EX11),EV11>=(80%*EX11),EW11<(80%*EX11)),10,IF(AND(EU11<(80%*EX11),EV11<(80%*EX11),EW11>=(80%*EX11)),15,IF(AND(EU11>=(80%*EX11),EV11>=(80%*EX11),EW11<(80%*EX11)),20,IF(AND(EU11>=(80%*EX11),EV11<(80%*EX11),EW11>=(80%*EX11)),25,IF(AND(EU11<(80%*EX11),EV11>=(80%*EX11),EW11>=(80%*EX11)),30,IF(AND(EU11>=(80%*EX11),EV11>=(80%*EX11),EW11>=(80%*EX11)),35,"Check"))))))))) -> 35 | EU11: ='Ashok-AsianP'!$FC$69 -> 0.018124864 | EV11: ='Ashok-AsianP'!$FD$69 -> 0.019959042 | EW11: ='Ashok-AsianP'!$FE$69 -> 0.021117019 | EX11: ='Ashok-AsianP'!$FB$73 -> 0.018602491 | EY11: =IF(OR(AND(EN11=1,OR(AND(ER11>=0.5%,ER11<=1.5%),AND(ER11<=-0.5%,ER11>=-1.5%)),ES11>=0.5%),AND(EN11=2,OR(AND(ER11>=0.5%,ER11<=1.5%),AND(ER11<=-0.5%,ER11>=-1.5%)),ES11>=0.5%)),1,0) -> 0 | EZ11: =IF(OR(EQ11="Exit Long & Go Short",EQ11="Exit Short & Go Long"),1,0) -> 0

Sheet BNF-Nifty
A1: Directional Trading System : | D1: BankNifty | E1: Nifty | F1: BNF | G1: Nifty | L1: Sr. No. | M1: =CONCATENATE($F$1," - Open, High, Low & Close") -> BNF - Open, High, Low & Close | S1: =CONCATENATE($G$1," - Open, High, Low & Close") -> Nifty - Open, High, Low & Close | Z1: =CONCATENATE($F$1," - %Chg") -> BNF - %Chg | AA1: =CONCATENATE($G$1," - %Chg") -> Nifty - %Chg | AB1: Beta vis-à-vis Market | AD1: =CONCATENATE($F$1," - AutoCorrelation") -> BNF - AutoCorrelation | AF1: =CONCATENATE($G$1," - AutoCorrelation") -> Nifty - AutoCorrelation | AH1: =CONCATENATE($F$1," - Historical Annual Volatility (NSE Method)") -> BNF - Historical Annual Volatility (NSE Method) | AL1: =CONCATENATE($G$1," - Historical Annual Volatility (NSE Method)") -> Nifty - Historical Annual Volatility (NSE Method) | AP1: =CONCATENATE($F$1," - Intraday Annual Volatility") -> BNF - Intraday Annual Volatility | AT1: =CONCATENATE($G$1," - Intraday Annual Volatility") -> Nifty - Intraday Annual Volatility | AX1: =CONCATENATE($F$1," - VW SMA (Trend Finder)") -> BNF - VW SMA (Trend Finder) | AZ1: =CONCATENATE($G$1," - VW SMA (Trend Finder)") -> Nifty - VW SMA (Trend Finder) | BB1: =CONCATENATE($F$1," - Volume Weighted EMA (Trend Finder)") -> BNF - Volume Weighted EMA (Trend Finder) | BJ1: =CONCATENATE($G$1," - Volume Weighted EMA (Trend Finder)") -> Nifty - Volume Weighted EMA (Trend Finder) | BR1: =CONCATENATE($F$1," - Volume Weighted SMA Crossover (Entries & Exits)") -> BNF - Volume Weighted SMA Crossover (Entries & Exits) | BZ1: =CONCATENATE($G$1," - Volume Weighted SMA Crossover (Entries & Exits)") -> Nifty - Volume Weighted SMA Crossover (Entries & Exits) | CH1: =CONCATENATE($F$1," - Volume Weighted MACD (12,26,9)") -> BNF - Volume Weighted MACD (12,26,9) | CQ1: =CONCATENATE($G$1," - Volume Weighted MACD (12,26,9)") -> Nifty - Volume Weighted MACD (12,26,9) | CZ1: =CONCATENATE($F$1," - Volume Weighted Money Flow Index [MFI] (14) [with Entries & Exits]") -> BNF - Volume Weighted Money Flow Index [MFI] (14) [with Entries & Exits] | DI1: =CONCATENATE($G$1," - Volume Weighted Money Flow Index [MFI] (14) [with Entries & Exits]") -> Nifty - Volume Weighted Money Flow Index [MFI] (14) [with Entries & Exits] | DR1: =CONCATENATE($F$1," - MM (Market Normalisation) with Volume Weighted ATR (21) for Positional Trades") -> BNF - MM (Market Normalisation) with Volume Weighted ATR (21) for Positional Trades | EA1: =CONCATENATE($G$1," - MM (Market Normalisation) with Volume Weighted ATR (21) for Positional Trades") -> Nifty - MM (Market Normalisation) with Volume Weighted ATR (21) for Positional Trades | EJ1: =CONCATENATE($F$1," - MM (Market Normalisation) with Volume Weighted ATR (8) for IntraDay Trades") -> BNF - MM (Market Normalisation) with Volume Weighted ATR (8) for IntraDay Trades | ES1: =CONCATENATE($G$1," - MM (Market Normalisation) with Volume Weighted ATR (8) for IntraDay Trades") -> Nifty - MM (Market Normalisation) with Volume Weighted ATR (8) for IntraDay Trades | FB1: =CONCATENATE($F$1," - Strength /Weakness") -> BNF - Strength /Weakness | FD1: =CONCATENATE($G$1," - Strength /Weakness") -> Nifty - Strength /Weakness | FF1: =CONCATENATE($F$1," - High-Low Range Average for ORB") -> BNF - High-Low Range Average for ORB | FK1: =CONCATENATE($G$1," - High-Low Range Average for ORB") -> Nifty - High-Low Range Average for ORB | FP1: =CONCATENATE($F$1," - B/SED") -> BNF - B/SED | FQ1: =CONCATENATE($G$1," - B/SED") -> Nifty - B/SED | FR1: =CONCATENATE($F$1," - CMI") -> BNF - CMI | FT1: =CONCATENATE($G$1," - CMI") -> Nifty - CMI | FV1: =CONCATENATE($F$1," - CMI") -> BNF - CMI | FX1: =CONCATENATE($G$1," - CMI") -> Nifty - CMI
A2: Particulars | D2: EOD Data | F2: Real Time Data | M2: Date | N2: =CONCATENATE($F$1," Open") -> BNF Open | O2: =CONCATENATE($F$1," High") -> BNF High | P2: =CONCATENATE($F$1," Low") -> BNF Low | Q2: =CONCATENATE($F$1," Close") -> BNF Close | R2: =CONCATENATE($F$1," Volume") -> BNF Volume | S2: Date | T2: =CONCATENATE($G$1," Open") -> Nifty Open | U2: =CONCATENATE($G$1," High") -> Nifty High | V2: =CONCATENATE($G$1," Low") -> Nifty Low | W2: =CONCATENATE($G$1," Close") -> Nifty Close | X2: =CONCATENATE($G$1," Volume") -> Nifty Volume | Z2: =CONCATENATE($F$1," Log (Curr. Close / Prev. Close) [% Change (Close)]") -> BNF Log (Curr. Close / Prev. Close) [% Change (Close)] | AA2: =CONCATENATE($G$1," Log (Curr. Close / Prev. Close) [% Change (Close)]") -> Nifty Log (Curr. Close / Prev. Close) [% Change (Close)] | AB2: =CONCATENATE($F$1," & Nifty (21 Day)") -> BNF & Nifty (21 Day) | AC2: =CONCATENATE($G$1," & Nifty (21 Day)") -> Nifty & Nifty (21 Day) | AD2: =CONCATENATE($F$1," % Change with (-1) Lag (Close)") -> BNF % Change with (-1) Lag (Close) | AE2: =CONCATENATE($F$1," Autocorrelation (21 Day)") -> BNF Autocorrelation (21 Day) | AF2: =CONCATENATE($G$1," % Change with (-1) Lag (Close)") -> Nifty % Change with (-1) Lag (Close) | AG2: =CONCATENATE($G$1," Autocorrelation (21 Day)") -> Nifty Autocorrelation (21 Day) | AH2: Log (Curr. Close / Prev. Close) | AI2: Prev. Day's Daily Volatility | AJ2: Curr. Day's Daily Volatility | AK2: Historical Annual Volatility (2 Day) | AL2: Log (Curr. Close / Prev. Close) | AM2: Prev. Day's Daily Volatility | AN2: Curr. Day's Daily Volatility | AO2: Historical Annual Volatility (2 Day) | AP2: Log (High / Low) | AQ2: Prev. Day's Daily Volatility | AR2: Curr. Day's Daily Volatility | AS2: Intraday Annual Volatility (2 Day) | AT2: Log (High / Low) | AU2: Prev. Day's Daily Volatility | AV2: Curr. Day's Daily Volatility | AW2: Intraday Annual Volatility (2 Day) | AX2: Open x Volume | AY2: Entry VW SMA (Open) [55 Day] | AZ2: Open x Volume | BA2: Entry VW SMA (Open) [55 Day] | BB2: EMA (Open x Volume) [13 Day] | BC2: EMA (Volume) [13 Day] | BD2: VW EMA (Open) [13 Day] | BE2: HLC Average | BF2: HLC Average x Volume | BG2: EMA (HLC Average x Volume) [5 Day] | BH2: EMA (Volume) [5 Day] | BI2: VW EMA (HLC Avg.) [5 Day] | BJ2: EMA (Open x Volume) [13 Day] | BK2: EMA (Volume) [13 Day] | BL2: VW EMA (Open) [13 Day] | BM2: HLC Average | BN2: HLC Average x Volume | BO2: EMA (HLC Average x Volume) [5 Day] | BP2: EMA (Volume) [5 Day] | BQ2: VW EMA (HLC Avg.) [5 Day] | BR2: Low x Volume | BS2: High x Volume | BT2: Entry VW SMA (Open) [13 Day] | BU2: Exit VW SMA (Low) [5 Day] | BV2: Exit VW SMA (High) [5 Day] | BW2: Entry VW SMA (Open) [34 Day] | BX2: Exit VW SMA (Low) [13 Day] | BY2: Exit VW SMA (High) [13 Day] | BZ2: Low x Volume | CA2: High x Volume | CB2: Entry VW SMA (Open) [13 Day] | CC2: Exit VW SMA (Low) [5 Day] | CD2: Exit VW SMA (High) [5 Day] | CE2: Entry VW SMA (Open) [34 Day] | CF2: Exit VW SMA (Low) [13 Day] | CG2: Exit VW SMA (High) [13 Day] | CH2: EMA (HLC Average x Volume) [12 Day] | CI2: EMA (Volume) [12 Day] | CJ2: VM EMA (HLC Avg.) [12 Day] | CK2: EMA (HLC Average x Volume) [26 Day] | CL2: EMA (Volume) [26 Day] | CM2: VM EMA (HLC Avg.) [26 Day] | CN2: VW MACD Line (HLC Avg.) | CO2: VW Signal Line (HLC Avg.) [9 Day EMA of VW MACD] | CP2: VW MACD Histogram (HLC Avg.) | CQ2: EMA (HLC Average x Volume) [12 Day] | CR2: EMA of (Volume) [12 Day] | CS2: VW EMA (HLC Avg.) [12 Day] | CT2: EMA (HLC Average x Volume) [26 Day] | CU2: EMA of (Volume) [26 Day] | CV2: VW EMA (HLC Avg.) [26 Day] | CW2: VW MACD Line (HLC Avg.) | CX2: VW Signal Line (HLC Avg.) [9 Day EMA of VW MACD] | CY2: VW MACD Histogram (HLC Avg.) | CZ2: HLC Average Price Change | DA2: Positive Money Flow (HLC Average x Volume) | DB2: Negative Money Flow (HLC Average x Volume) | DC2: VW EMA (Positive Money Flow) (HLC Avg.) [14 Day] | DD2: VW EMA (Negative Money Flow) (HLC Avg.) [14 Day] | DE2: Relative Strength of Money Flow (Money Flow Ratio) [14 Day] | DF2: Money Flow Index (MFI) (HLC Avg.) [14 Day] | DG2: Entry VW SMA (MFI 14) (HLC Avg.) [34 Day] | DH2: Exit VW SMA (MFI 14) (HLC Avg.) [21 Day] | DI2: HLC Average Price Change | DJ2: Positive Money Flow (HLC Average x Volume) | DK2: Negative Money Flow (HLC Average x Volume) | DL2: VW EMA (Positive Money Flow) (HLC Avg.) [14 Day] | DM2: VW EMA (Negative Money Flow) (HLC Avg.) [14 Day] | DN2: Relative Strength of Money Flow (Money Flow Ratio) [14 Day] | DO2: Money Flow Index (MFI) (HLC Avg.) [14 Day] | DP2: Entry VW SMA (MFI 14) (HLC Avg.) [34 Day] | DQ2: Exit VW SMA (MFI 14) (HLC Avg.) [21 Day] | DR2: True Range | DS2: True Range x Volume | DT2: VW EMA (True Range x Volume) [21 Day] | DU2: VW EMA (Volume) [21 Day] | DV2: Volume Weighted Averate True Range (21) [N] | DW2: Rupee Volatility / Risk [N x Lot Size] | DX2: =CONCATENATE("Contract Risk (Unit) [",'Base Data'!$D$10,"N]") -> Contract Risk (Unit) [2N] | DY2: =CONCATENATE("Max. Lots that can be Traded with a Unit of Rs. ",'Base Data'!$D$7," [No. of Lots]") -> Max. Lots that can be Traded with a Unit of Rs. 10500 [No. of Lots] | DZ2: Average True Range Percent (21) | EA2: True Range | EB2: True Range x Volume | EC2: VW EMA (True Range x Volume) [21 Day] | ED2: VW EMA (Volume) [21 Day] | EE2: Volume Weighted Averate True Range (21) [N] | EF2: Rupee Volatility / Risk [N x Lot Size] | EG2: =CONCATENATE("Contract Risk (Unit) [",'Base Data'!$D$10,"N]") -> Contract Risk (Unit) [2N] | EH2: =CONCATENATE("Max. Lots that can be Traded with a Unit of Rs. ",'Base Data'!$D$7," [No. of Lots]") -> Max. Lots that can be Traded with a Unit of Rs. 10500 [No. of Lots] | EI2: Average True Range Percent (21) | EJ2: True Range | EK2: True Range x Volume | EL2: VW EMA (True Range x Volume) [8 Day] | EM2: VW EMA (Volume) [8 Day] | EN2: Volume Weighted Averate True Range (8) [N] | EO2: Rupee Volatility / Risk [N x Lot Size] | EP2: =CONCATENATE("Contract Risk (Unit) [",'Base Data'!$D$13,"N]") -> Contract Risk (Unit) [0.75N] | EQ2: =CONCATENATE("Max. Lots that can be Traded with a Unit of Rs. ",'Base Data'!$D$7," [No. of Lots]") -> Max. Lots that can be Traded with a Unit of Rs. 10500 [No. of Lots] | ER2: Average True Range Percent (8) | ES2: True Range | ET2: True Range x Volume | EU2: VW EMA (True Range x Volume) [8 Day] | EV2: VW EMA (Volume) [8 Day] | EW2: Volume Weighted Averate True Range (8) [N] | EX2: Rupee Volatility / Risk [N x Lot Size] | EY2: =CONCATENATE("Contract Risk (Unit) [",'Base Data'!$D$13,"N]") -> Contract Risk (Unit) [0.75N] | EZ2: =CONCATENATE("Max. Lots that can be Traded with a Unit of Rs. ",'Base Data'!$D$7," [No. of Lots]") -> Max. Lots that can be Traded with a Unit of Rs. 10500 [No. of Lots] | FA2: Average True Range Percent (8) | FB2: Strength / Weakness (Based on Avg. HLC & ATR) (Positional) [21 Day] | FC2: Strength / Weakness (Based on Avg. HLC & ATR) (IntraDay) [8 Day] | FD2: Strength / Weakness (Based on Avg. HLC & ATR) (Positional) [21 Day] | FE2: Strength / Weakness (Based on Avg. HLC & ATR) (IntraDay) [8 Day] | FF2: High-Low Range | FG2: % Change (High-Low Range with Open) | FH2: Avg. % Change (SMA) [8 Day] | FI2: Avg. % Change (SMA) [13 Day] | FJ2: Avg. % Change (SMA) [21 Day] | FK2: High-Low Range | FL2: % Change (High-Low Range with Open) | FM2: Avg. % Change (SMA) [8 Day] | FN2: Avg. % Change (SMA) [13 Day] | FO2: Avg. % Change (SMA) [21 Day] | FP2: 1 - Buy Easier Day 2 - Sell Easier Day | FQ2: 1 - Buy Easier Day 2 - Sell Easier Day | FR2: Choppy Market Index [21 Day] | FS2: Market Mode (Trending / Choppy) | FT2: Choppy Market Index [21 Day] | FU2: Market Mode (Trending / Choppy) | FV2: Choppy Market Index [8 Day] | FW2: Market Mode (Trending / Choppy) | FX2: Choppy Market Index [8 Day] | FY2: Market Mode (Trending / Choppy) | GA2: Elder Ray Index | GB2: Keltner Channels
D3: =$F$1 -> BNF | E3: =$G$1 -> Nifty | F3: =$F$1 -> BNF | G3: =$G$1 -> Nifty
A4: Last Traded Price / Lot Size | D4: =$Q$69 -> 25845.55 | E4: =$W$69 -> 10619.8 | F4: =VLOOKUP(D1,'[3]Margin - NSE Fut (5Paisa)'!$A:$K,2,FALSE) -> 20 | G4: =VLOOKUP(E1,'[3]Margin - NSE Fut (5Paisa)'!$A:$K,2,FALSE) -> 75 | L4: 1 | M4: ='[4]BANKNIFTY-I'!C20 -> 42794 | N4: ='[4]BANKNIFTY-I'!D20 -> 20680.1 | O4: ='[4]BANKNIFTY-I'!E20 -> 20746.6 | P4: ='[4]BANKNIFTY-I'!F20 -> 20635.1 | Q4: ='[4]BANKNIFTY-I'!G20 -> 20681.45 | R4: ='[4]BANKNIFTY-I'!H20 -> 45510 | S4: ='[5]NIFTY-I'!C20 -> 42794 | T4: ='[5]NIFTY-I'!D20 -> 8921.5 | U4: ='[5]NIFTY-I'!E20 -> 8938.45 | V4: ='[5]NIFTY-I'!F20 -> 8884.15 | W4: ='[5]NIFTY-I'!G20 -> 8909.35 | X4: ='[5]NIFTY-I'!H20 -> 88565 | Z4: 0 | AA4: 0 | AB4: 0 | AC4: 0 | AD4: =Z5 -> 0.0079704913 | AE4: - | AF4: =AA5 -> 0.0074586321 | AG4: - | AH4: 0 | AI4: 0 | AJ4: 0 | AK4: 0 | AL4: 0 | AM4: 0 | AN4: 0 | AO4: 0 | AP4: =IF(P4=0,0,LN(O4/P4)) -> 0.0053888685 | AQ4: 0 | AR4: 0 | AS4: 0 | AT4: =IF(V4=0,0,LN(U4/V4)) -> 0.0060934059 | AU4: 0 | AV4: 0 | AW4: 0 | AX4: =(N4*R4) -> 9.4115135e+08 | AY4: 0 | AZ4: =(T4*X4) -> 7.9013265e+08 | BA4: 0 | BB4: 0 | BC4: 0 | BD4: 0 | BE4: =(O4+P4+Q4)/3 -> 20687.717 | BF4: =(BE4*R4) -> 9.4149799e+08 | BG4: 0 | BH4: 0 | BI4: 0 | BJ4: 0 | BK4: 0 | BL4: 0 | BM4: =(U4+V4+W4)/3 -> 8910.65 | BN4: =(BM4*X4) -> 7.8917172e+08 | BO4: 0 | BP4: 0 | BQ4: 0 | BR4: =(P4*R4) -> 9.391034e+08 | BS4: =(O4*R4) -> 9.4417777e+08 | BT4: 0 | BU4: 0 | BW4: 0 | BX4: 0 | BZ4: =(V4*X4) -> 7.8682474e+08 | CA4: =(U4*X4) -> 7.9163382e+08 | CB4: 0 | CC4: 0 | CE4: 0 | CF4: 0 | CH4: 0 | CI4: 0 | CJ4: 0 | CK4: 0 | CL4: 0 | CM4: 0 | CN4: 0 | CO4: 0 | CP4: 0 | CQ4: 0 | CR4: 0 | CS4: 0 | CV4: 0 | CW4: 0 | CX4: 0 | CY4: 0 | CZ4: 0 | DA4: 0 | DB4: 0 | DC4: 0 | DD4: 0 | DE4: 0 | DF4: 0 | DG4: 0 | DH4: 0 | DI4: 0 | DJ4: 0 | DK4: 0 | DL4: 0 | DM4: 0 | DN4: 0 | DO4: 0 | DP4: 0 | DQ4: 0 | DR4: 0 | DT4: 0 | DU4: 0 | DV4: 0 | DW4: 0 | DX4: 0 | DY4: 0 | DZ4: 0 | EA4: 0 | EC4: 0 | ED4: 0 | EE4: 0 | EF4: 0 | EG4: 0 | EH4: 0 | EI4: 0 | EJ4: 0 | EL4: 0 | EM4: 0 | EN4: 0 | EO4: 0 | EP4: 0 | EQ4: - | ES4: 0 | EU4: 0 | EV4: 0 | EW4: 0 | EX4: 0 | EY4: 0 | EZ4: - | FB4: 0 | FC4: 0 | FD4: 0 | FE4: 0 | FF4: =(O4-P4) -> 111.5 | FG4: =FF4/N4 -> 0.0053916567 | FH4: - | FI4: - | FJ4: - | FK4: =(U4-V4) -> 54.3 | FL4: =FK4/T4 -> 0.0060864204 | FM4: - | FN4: - | FO4: - | FP4: - | FQ4: - | FR4: 0 | FS4: - | FT4: 0 | FU4: - | FV4: 0 | FW4: - | FX4: 0 | FY4: -
A5: Scrip Name with Expiry | D5: =CONCATENATE($D$1,$F$5) -> BankNifty18NovFut | E5: =CONCATENATE($E$1,$F$5) -> Nifty18NovFut | F5: ='Base Data'!$D$1 -> 18NovFut | L5: =L4+1 -> 2 | M5: ='[4]BANKNIFTY-I'!C21 -> 42795 | N5: ='[4]BANKNIFTY-I'!D21 -> 20755.05 | O5: ='[4]BANKNIFTY-I'!E21 -> 20900.4 | P5: ='[4]BANKNIFTY-I'!F21 -> 20725.05 | Q5: ='[4]BANKNIFTY-I'!G21 -> 20846.95 | R5: ='[4]BANKNIFTY-I'!H21 -> 59898 | S5: ='[5]NIFTY-I'!C21 -> 42795 | T5: ='[5]NIFTY-I'!D21 -> 8924 | U5: ='[5]NIFTY-I'!E21 -> 8994 | V5: ='[5]NIFTY-I'!F21 -> 8921.7 | W5: ='[5]NIFTY-I'!G21 -> 8976.05 | X5: ='[5]NIFTY-I'!H21 -> 113075 | Z5: =IF(OR(Q4=0,Q5=0),0,LN(Q5/Q4)) -> 0.0079704913 | AA5: =IF(OR(W4=0,W5=0),0,LN(W5/W4)) -> 0.0074586321 | AB5: 0 | AC5: 0 | AD5: =Z6 -> -0.010400738 | AE5: - | AF5: =AA6 -> -0.0065779232 | AG5: - | AH5: =IF(OR(Q4=0,Q5=0),0,LN(Q5/Q4)) -> 0.0079704913 | AI5: =AJ4 -> 0 | AJ5: =SQRT((0.94*(AI5^2))+(0.06*(AH5^2))) -> 0.0019523637 | AK5: =AJ5*SQRT(365) -> 0.037299856 | AL5: =IF(OR(W4=0,W5=0),0,LN(W5/W4)) -> 0.0074586321 | AM5: =AN4 -> 0 | AN5: =SQRT((0.94*(AM5^2))+(0.06*(AL5^2))) -> 0.0018269843 | AO5: =AN5*SQRT(365) -> 0.034904486 | AP5: =IF(P5=0,0,LN(O5/P5)) -> 0.008425184 | AQ5: =AR4 -> 0 | AR5: =SQRT((0.94*(AQ5^2))+(0.06*(AP5^2))) -> 0.0020637402 | AS5: =AR5*SQRT(365) -> 0.039427701 | AT5: =IF(V5=0,0,LN(U5/V5)) -> 0.008071177 | AU5: =AV4 -> 0 | AV5: =SQRT((0.94*(AU5^2))+(0.06*(AT5^2))) -> 0.0019770265 | AW5: =AV5*SQRT(365) -> 0.037771039 | AX5: =(N5*R5) -> 1.243186e+09 | AY5: 0 | AZ5: =(T5*X5) -> 1009081300 | BA5: 0 | BB5: 0 | BC5: 0 | BD5: 0 | BE5: =(O5+P5+Q5)/3 -> 20824.133 | BF5: =(BE5*R5) -> 1.2473239e+09 | BG5: 0 | BH5: 0 | BI5: 0 | BJ5: 0 | BK5: 0 | BL5: 0 | BM5: =(U5+V5+W5)/3 -> 8963.9167 | BN5: =(BM5*X5) -> 1.0135949e+09 | BO5: 0 | BP5: 0 | BQ5: 0 | BR5: =(P5*R5) -> 1.241389e+09 | BS5: =(O5*R5) -> 1.2518922e+09 | BT5: 0 | BU5: 0 | BW5: 0 | BX5: 0 | BZ5: =(V5*X5) -> 1.0088212e+09 | CA5: =(U5*X5) -> 1016996550 | CB5: 0 | CC5: 0 | CE5: 0 | CF5: 0 | CH5: 0 | CI5: 0 | CJ5: 0 | CK5: 0 | CL5: 0 | CM5: 0 | CN5: 0 | CO5: 0 | CP5: 0 | CQ5: 0 | CR5: 0 | CS5: 0 | CV5: 0 | CW5: 0 | CX5: 0 | CY5: 0 | CZ5: =(BE5-BE4) -> 136.41667 | DA5: =IF(CZ5>=0,BF5,0) -> 1.2473239e+09 | DB5: =IF(CZ5<0,BF5,0) -> 0 | DC5: 0 | DD5: 0 | DE5: 0 | DF5: 0 | DG5: 0 | DH5: 0 | DI5: =(BM5-BM4) -> 53.266667 | DJ5: =IF(DI5>=0,BN5,0) -> 1.0135949e+09 | DK5: =IF(DI5<0,BN5,0) -> 0 | DL5: 0 | DM5: 0 | DN5: 0 | DO5: 0 | DP5: 0 | DQ5: 0 | DR5: =MAX(O5-P5,ABS(O5-Q4),ABS(Q4-P5)) -> 218.95 | DS5: =(DR5*R5) -> 13114667 | DT5: 0 | DU5: 0 | DV5: 0 | DW5: 0 | DX5: 0 | DY5: 0 | DZ5: 0 | EA5: =MAX(U5-V5,ABS(U5-W4),ABS(W4-V5)) -> 84.65 | EB5: =(EA5*X5) -> 9571798.7 | EC5: 0 | ED5: 0 | EE5: 0 | EF5: 0 | EG5: 0 | EH5: 0 | EI5: 0 | EJ5: =MAX(O5-P5,ABS(O5-Q4),ABS(Q4-P5)) -> 218.95 | EK5: =(EJ5*R5) -> 13114667 | EL5: 0 | EM5: 0 | EN5: 0 | EO5: 0 | EP5: 0 | EQ5: - | ES5: =MAX(U5-V5,ABS(U5-W4),ABS(W4-V5)) -> 84.65 | ET5: =(ES5*X5) -> 9571798.7 | EU5: 0 | EV5: 0 | EW5: 0 | EX5: 0 | EY5: 0 | EZ5: - | FB5: 0 | FC5: 0 | FD5: 0 | FE5: 0 | FF5: =(O5-P5) -> 175.35 | FG5: =FF5/N5 -> 0.0084485463 | FH5: - | FI5: - | FJ5: - | FK5: =(U5-V5) -> 72.3 | FL5: =FK5/T5 -> 0.0081017481 | FM5: - | FN5: - | FO5: - | FP5: - | FQ5: - | FR5: 0 | FS5: - | FT5: 0 | FU5: - | FV5: 0 | FW5: - | FX5: 0 | FY5: -
L6: =L5+1 -> 3 | M6: ='[4]BANKNIFTY-I'!C22 -> 42796 | N6: ='[4]BANKNIFTY-I'!D22 -> 20925.35 | O6: ='[4]BANKNIFTY-I'!E22 -> 20957.9 | P6: ='[4]BANKNIFTY-I'!F22 -> 20581.45 | Q6: ='[4]BANKNIFTY-I'!G22 -> 20631.25 | R6: ='[4]BANKNIFTY-I'!H22 -> 105646 | S6: ='[5]NIFTY-I'!C22 -> 42796 | T6: ='[5]NIFTY-I'!D22 -> 9001 | U6: ='[5]NIFTY-I'!E22 -> 9018.3 | V6: ='[5]NIFTY-I'!F22 -> 8898.25 | W6: ='[5]NIFTY-I'!G22 -> 8917.2 | X6: ='[5]NIFTY-I'!H22 -> 146853 | Z6: =IF(OR(Q5=0,Q6=0),0,LN(Q6/Q5)) -> -0.010400738 | AA6: =IF(OR(W5=0,W6=0),0,LN(W6/W5)) -> -0.0065779232 | AB6: 0 | AC6: 0 | AD6: =Z7 -> -0.0024920453 | AE6: - | AF6: =AA7 -> 0.00062780271 | AG6: - | AH6: =IF(OR(Q5=0,Q6=0),0,LN(Q6/Q5)) -> -0.010400738 | AI6: =AJ5 -> 0.0019523637 | AJ6: =SQRT((0.94*(AI6^2))+(0.06*(AH6^2))) -> 0.0031738843 | AK6: =AJ6*SQRT(365) -> 0.060636974 | AL6: =IF(OR(W5=0,W6=0),0,LN(W6/W5)) -> -0.0065779232 | AM6: =AN5 -> 0.0018269843 | AN6: =SQRT((0.94*(AM6^2))+(0.06*(AL6^2))) -> 0.0023945237 | AO6: =AN6*SQRT(365) -> 0.045747311 | AP6: =IF(P6=0,0,LN(O6/P6)) -> 0.018125479 | AQ6: =AR5 -> 0.0020637402 | AR6: =SQRT((0.94*(AQ6^2))+(0.06*(AP6^2))) -> 0.0048698523 | AS6: =AR6*SQRT(365) -> 0.093038397 | AT6: =IF(V6=0,0,LN(U6/V6)) -> 0.013401218 | AU6: =AV5 -> 0.0019770265 | AV6: =SQRT((0.94*(AU6^2))+(0.06*(AT6^2))) -> 0.0038012728 | AW6: =AV6*SQRT(365) -> 0.072623214 | AX6: =(N6*R6) -> 2.2106795e+09 | AY6: 0 | AZ6: =(T6*X6) -> 1321823853 | BA6: 0 | BB6: 0 | BC6: 0 | BD6: 0 | BE6: =(O6+P6+Q6)/3 -> 20723.533 | BF6: =(BE6*R6) -> 2.1893584e+09 | BG6: 0 | BH6: 0 | BI6: 0 | BJ6: 0 | BK6: 0 | BL6: 0 | BM6: =(U6+V6+W6)/3 -> 8944.5833 | BN6: =(BM6*X6) -> 1.3135389e+09 | BO6: 0 | BP6: 0 | BQ6: 0 | BR6: =(P6*R6) -> 2.1743479e+09 | BS6: =(O6*R6) -> 2.2141183e+09 | BT6: 0 | BU6: 0 | BW6: 0 | BX6: 0 | BZ6: =(V6*X6) -> 1.3067347e+09 | CA6: =(U6*X6) -> 1.3243644e+09 | CB6: 0 | CC6: 0 | CE6: 0 | CF6: 0 | CH6: 0 | CI6: 0 | CJ6: 0 | CK6: 0 | CL6: 0 | CM6: 0 | CN6: 0 | CO6: 0 | CP6: 0 | CQ6: 0 | CR6: 0 | CS6: 0 | CV6: 0 | CW6: 0 | CX6: 0 | CY6: 0 | CZ6: =(BE6-BE5) -> -100.6 | DA6: =IF(CZ6>=0,BF6,0) -> 0 | DB6: =IF(CZ6<0,BF6,0) -> 2.1893584e+09 | DC6: 0 | DD6: 0 | DE6: 0 | DF6: 0 | DG6: 0 | DH6: 0 | DI6: =(BM6-BM5) -> -19.333333 | DJ6: =IF(DI6>=0,BN6,0) -> 0 | DK6: =IF(DI6<0,BN6,0) -> 1.3135389e+09 | DL6: 0 | DM6: 0 | DN6: 0 | DO6: 0 | DP6: 0 | DQ6: 0 | DR6: =MAX(O6-P6,ABS(O6-Q5),ABS(Q5-P6)) -> 376.45 | DS6: =(DR6*R6) -> 39770437 | DT6: 0 | DU6: 0 | DV6: 0 | DW6: 0 | DX6: 0 | DY6: 0 | DZ6: 0 | EA6: =MAX(U6-V6,ABS(U6-W5),ABS(W5-V6)) -> 120.05 | EB6: =(EA6*X6) -> 17629703 | EC6: 0 | ED6: 0 | EE6: 0 | EF6: 0 | EG6: 0 | EH6: 0 | EI6: 0 | EJ6: =MAX(O6-P6,ABS(O6-Q5),ABS(Q5-P6)) -> 376.45 | EK6: =(EJ6*R6) -> 39770437 | EL6: 0 | EM6: 0 | EN6: 0 | EO6: 0 | EP6: 0 | EQ6: - | ES6: =MAX(U6-V6,ABS(U6-W5),ABS(W5-V6)) -> 120.05 | ET6: =(ES6*X6) -> 17629703 | EU6: 0 | EV6: 0 | EW6: 0 | EX6: 0 | EY6: 0 | EZ6: - | FB6: 0 | FC6: 0 | FD6: 0 | FE6: 0 | FF6: =(O6-P6) -> 376.45 | FG6: =FF6/N6 -> 0.017990141 | FH6: - | FI6: - | FJ6: - | FK6: =(U6-V6) -> 120.05 | FL6: =FK6/T6 -> 0.013337407 | FM6: - | FN6: - | FO6: - | FP6: =IF(Q5<((O4+P4+Q4)/3),1,IF(Q5>((O4+P4+Q4)/3),2,0)) -> 2 | FQ6: =IF(W5<((U4+V4+W4)/3),1,IF(W5>((U4+V4+W4)/3),2,0)) -> 2 | FR6: 0 | FS6: - | FT6: 0 | FU6: - | FV6: 0 | FW6: - | FX6: 0 | FY6: -
L7: =L6+1 -> 4 | M7: ='[4]BANKNIFTY-I'!C23 -> 42797 | N7: ='[4]BANKNIFTY-I'!D23 -> 20511.1 | O7: ='[4]BANKNIFTY-I'!E23 -> 20619.85 | P7: ='[4]BANKNIFTY-I'!F23 -> 20494.6 | Q7: ='[4]BANKNIFTY-I'!G23 -> 20579.9 | R7: ='[4]BANKNIFTY-I'!H23 -> 53163 | S7: ='[5]NIFTY-I'!C23 -> 42797 | T7: ='[5]NIFTY-I'!D23 -> 8884 | U7: ='[5]NIFTY-I'!E23 -> 8933 | V7: ='[5]NIFTY-I'!F23 -> 8872.7 | W7: ='[5]NIFTY-I'!G23 -> 8922.8 | X7: ='[5]NIFTY-I'!H23 -> 110827 | Z7: =IF(OR(Q6=0,Q7=0),0,LN(Q7/Q6)) -> -0.0024920453 | AA7: =IF(OR(W6=0,W7=0),0,LN(W7/W6)) -> 0.00062780271 | AB7: 0 | AC7: 0 | AD7: =Z8 -> 0.0074672281 | AE7: - | AF7: =AA8 -> 0.0062954244 | AG7: - | AH7: =IF(OR(Q6=0,Q7=0),0,LN(Q7/Q6)) -> -0.0024920453 | AI7: =AJ6 -> 0.0031738843 | AJ7: =SQRT((0.94*(AI7^2))+(0.06*(AH7^2))) -> 0.0031371558 | AK7: =AJ7*SQRT(365) -> 0.059935277 | AL7: =IF(OR(W6=0,W7=0),0,LN(W7/W6)) -> 0.00062780271 | AM7: =AN6 -> 0.0023945237 | AN7: =SQRT((0.94*(AM7^2))+(0.06*(AL7^2))) -> 0.0023266644 | AO7: =AN7*SQRT(365) -> 0.044450861 | AP7: =IF(P7=0,0,LN(O7/P7)) -> 0.0060927673 | AQ7: =AR6 -> 0.0048698523 | AR7: =SQRT((0.94*(AQ7^2))+(0.06*(AP7^2))) -> 0.0049517514 | AS7: =AR7*SQRT(365) -> 0.094603078 | AT7: =IF(V7=0,0,LN(U7/V7)) -> 0.0067731379 | AU7: =AV6 -> 0.0038012728 | AV7: =SQRT((0.94*(AU7^2))+(0.06*(AT7^2))) -> 0.004041685 | AW7: =AV7*SQRT(365) -> 0.077216284 | AX7: =(N7*R7) -> 1.0904316e+09 | AY7: 0 | AZ7: =(T7*X7) -> 984587068 | BA7: 0 | BB7: 0 | BC7: 0 | BD7: 0 | BE7: =(O7+P7+Q7)/3 -> 20564.783 | BF7: =(BE7*R7) -> 1.0932856e+09 | BG7: 0 | BH7: 0 | BI7: 0 | BJ7: 0 | BK7: 0 | BL7: 0 | BM7: =(U7+V7+W7)/3 -> 8909.5 | BN7: =(BM7*X7) -> 9.8741316e+08 | BO7: 0 | BP7: 0 | BQ7: 0 | BR7: =(P7*R7) -> 1.0895544e+09 | BS7: =(O7*R7) -> 1.0962131e+09 | BT7: 0 | BU7: 0 | BW7: 0 | BX7: 0 | BZ7: =(V7*X7) -> 9.8333472e+08 | CA7: =(U7*X7) -> 990017591 | CB7: 0 | CC7: 0 | CE7: 0 | CF7: 0 | CH7: 0 | CI7: 0 | CJ7: 0 | CK7: 0 | CL7: 0 | CM7: 0 | CN7: 0 | CO7: 0 | CP7: 0 | CQ7: 0 | CR7: 0 | CS7: 0 | CV7: 0 | CW7: 0 | CX7: 0 | CY7: 0 | CZ7: =(BE7-BE6) -> -158.75 | DA7: =IF(CZ7>=0,BF7,0) -> 0 | DB7: =IF(CZ7<0,BF7,0) -> 1.0932856e+09 | DC7: 0 | DD7: 0 | DE7: 0 | DF7: 0 | DG7: 0 | DH7: 0 | DI7: =(BM7-BM6) -> -35.083333 | DJ7: =IF(DI7>=0,BN7,0) -> 0 | DK7: =IF(DI7<0,BN7,0) -> 9.8741316e+08 | DL7: 0 | DM7: 0 | DN7: 0 | DO7: 0 | DP7: 0 | DQ7: 0 | DR7: =MAX(O7-P7,ABS(O7-Q6),ABS(Q6-P7)) -> 136.65 | DS7: =(DR7*R7) -> 7264724 | DT7: 0 | DU7: 0 | DV7: 0 | DW7: 0 | DX7: 0 | DY7: 0 | DZ7: 0 | EA7: =MAX(U7-V7,ABS(U7-W6),ABS(W6-V7)) -> 60.3 | EB7: =(EA7*X7) -> 6682868.1 | EC7: 0 | ED7: 0 | EE7: 0 | EF7: 0 | EG7: 0 | EH7: 0 | EI7: 0 | EJ7: =MAX(O7-P7,ABS(O7-Q6),ABS(Q6-P7)) -> 136.65 | EK7: =(EJ7*R7) -> 7264724 | EL7: 0 | EM7: 0 | EN7: 0 | EO7: 0 | EP7: 0 | EQ7: - | ES7: =MAX(U7-V7,ABS(U7-W6),ABS(W6-V7)) -> 60.3 | ET7: =(ES7*X7) -> 6682868.1 | EU7: 0 | EV7: 0 | EW7: 0 | EX7: 0 | EY7: 0 | EZ7: - | FB7: 0 | FC7: 0 | FD7: 0 | FE7: 0 | FF7: =(O7-P7) -> 125.25 | FG7: =FF7/N7 -> 0.0061064497 | FH7: - | FI7: - | FJ7: - | FK7: =(U7-V7) -> 60.3 | FL7: =FK7/T7 -> 0.0067874831 | FM7: - | FN7: - | FO7: - | FP7: =IF(Q6<((O5+P5+Q5)/3),1,IF(Q6>((O5+P5+Q5)/3),2,0)) -> 1 | FQ7: =IF(W6<((U5+V5+W5)/3),1,IF(W6>((U5+V5+W5)/3),2,0)) -> 1 | FR7: 0 | FS7: - | FT7: 0 | FU7: - | FV7: 0 | FW7: - | FX7: 0 | FY7: -
A8: =CONCATENATE("Gann Angle - ",$F$1) -> Gann Angle - BNF | B8: Open | D8: High | E8: Low | F8: Close | G8: Trade Type (I=0/P=1) | L8: =L7+1 -> 5 | M8: ='[4]BANKNIFTY-I'!C24 -> 42800 | N8: ='[4]BANKNIFTY-I'!D24 -> 20625.75 | O8: ='[4]BANKNIFTY-I'!E24 -> 20803.4 | P8: ='[4]BANKNIFTY-I'!F24 -> 20610.2 | Q8: ='[4]BANKNIFTY-I'!G24 -> 20734.15 | R8: ='[4]BANKNIFTY-I'!H24 -> 59768 | S8: ='[5]NIFTY-I'!C24 -> 42800 | T8: ='[5]NIFTY-I'!D24 -> 8935 | U8: ='[5]NIFTY-I'!E24 -> 8985 | V8: ='[5]NIFTY-I'!F24 -> 8928.45 | W8: ='[5]NIFTY-I'!G24 -> 8979.15 | X8: ='[5]NIFTY-I'!H24 -> 92519 | Z8: =IF(OR(Q7=0,Q8=0),0,LN(Q8/Q7)) -> 0.0074672281 | AA8: =IF(OR(W7=0,W8=0),0,LN(W8/W7)) -> 0.0062954244 | AB8: 0 | AC8: 0 | AD8: =Z9 -> -0.00077679838 | AE8: - | AF8: =AA9 -> -0.00056257225 | AG8: - | AH8: =IF(OR(Q7=0,Q8=0),0,LN(Q8/Q7)) -> 0.0074672281 | AI8: =AJ7 -> 0.0031371558 | AJ8: =SQRT((0.94*(AI8^2))+(0.06*(AH8^2))) -> 0.0035491987 | AK8: =AJ8*SQRT(365) -> 0.067807346 | AL8: =IF(OR(W7=0,W8=0),0,LN(W8/W7)) -> 0.0062954244 | AM8: =AN7 -> 0.0023266644 | AN8: =SQRT((0.94*(AM8^2))+(0.06*(AL8^2))) -> 0.002732491 | AO8: =AN8*SQRT(365) -> 0.052204168 | AP8: =IF(P8=0,0,LN(O8/P8)) -> 0.009330336 | AQ8: =AR7 -> 0.0049517514 | AR8: =SQRT((0.94*(AQ8^2))+(0.06*(AP8^2))) -> 0.0053171385 | AS8: =AR8*SQRT(365) -> 0.10158379 | AT8: =IF(V8=0,0,LN(U8/V8)) -> 0.0063137126 | AU8: =AV7 -> 0.004041685 | AV8: =SQRT((0.94*(AU8^2))+(0.06*(AT8^2))) -> 0.0042127049 | AW8: =AV8*SQRT(365) -> 0.080483615 | AX8: =(N8*R8) -> 1232759826 | AY8: 0 | AZ8: =(T8*X8) -> 826657265 | BA8: 0 | BB8: 0 | BC8: 0 | BD8: 0 | BE8: =(O8+P8+Q8)/3 -> 20715.917 | BF8: =(BE8*R8) -> 1.2381489e+09 | BG8: =AVERAGE(BF4:BF8) -> 1.341923e+09 | BH8: =AVERAGE(R4:R8) -> 64797 | BI8: =BG8/BH8 -> 20709.646 | BJ8: 0 | BK8: 0 | BL8: 0 | BM8: =(U8+V8+W8)/3 -> 8964.2 | BN8: =(BM8*X8) -> 8.2935882e+08 | BO8: =AVERAGE(BN4:BN8) -> 9.8661549e+08 | BP8: =AVERAGE(X4:X8) -> 110367.8 | BQ8: =BO8/BP8 -> 8939.3418 | BR8: =(P8*R8) -> 1.2318304e+09 | BS8: =(O8*R8) -> 1.2433776e+09 | BT8: 0 | BU8: =AVERAGE(BR4:BR8)/AVERAGE(R4:R8) -> 20606.587 | BV8: =AVERAGE(BS4:BS8)/AVERAGE(R4:R8) -> 20833.616 | BW8: 0 | BX8: 0 | BZ8: =(V8*X8) -> 8.2605127e+08 | CA8: =(U8*X8) -> 831283215 | CB8: 0 | CC8: =AVERAGE(BZ4:BZ8)/AVERAGE(X4:X8) -> 8900.7241 | CD8: =AVERAGE(CA4:CA8)/AVERAGE(X4:X8) -> 8977.7917 | CE8: 0 | CF8: 0 | CH8: 0 | CI8: 0 | CJ8: 0 | CK8: 0 | CL8: 0 | CM8: 0 | CN8: 0 | CO8: 0 | CP8: 0 | CQ8: 0 | CR8: 0 | CS8: 0 | CV8: 0 | CW8: 0 | CX8: 0 | CY8: 0 | CZ8: =(BE8-BE7) -> 151.13333 | DA8: =IF(CZ8>=0,BF8,0) -> 1.2381489e+09 | DB8: =IF(CZ8<0,BF8,0) -> 0 | DC8: 0 | DD8: 0 | DE8: 0 | DF8: 0 | DG8: 0 | DH8: 0 | DI8: =(BM8-BM7) -> 54.7 | DJ8: =IF(DI8>=0,BN8,0) -> 8.2935882e+08 | DK8: =IF(DI8<0,BN8,0) -> 0 | DL8: 0 | DM8: 0 | DN8: 0 | DO8: 0 | DP8: 0 | DQ8: 0 | DR8: =MAX(O8-P8,ABS(O8-Q7),ABS(Q7-P8)) -> 223.5 | DS8: =(DR8*R8) -> 13358148 | DT8: 0 | DU8: 0 | DV8: 0 | DW8: 0 | DX8: 0 | DY8: 0 | DZ8: 0 | EA8: =MAX(U8-V8,ABS(U8-W7),ABS(W7-V8)) -> 62.2 | EB8: =(EA8*X8) -> 5754681.8 | EC8: 0 | ED8: 0 | EE8: 0 | EF8: 0 | EG8: 0 | EH8: 0 | EI8: 0 | EJ8: =MAX(O8-P8,ABS(O8-Q7),ABS(Q7-P8)) -> 223.5 | EK8: =(EJ8*R8) -> 13358148 | EL8: 0 | EM8: 0 | EN8: 0 | EO8: 0 | EP8: 0 | EQ8: - | ES8: =MAX(U8-V8,ABS(U8-W7),ABS(W7-V8)) -> 62.2 | ET8: =(ES8*X8) -> 5754681.8 | EU8: 0 | EV8: 0 | EW8: 0 | EX8: 0 | EY8: 0 | EZ8: - | FB8: 0 | FC8: 0 | FD8: 0 | FE8: 0 | FF8: =(O8-P8) -> 193.2 | FG8: =FF8/N8 -> 0.0093669321 | FH8: - | FI8: - | FJ8: - | FK8: =(U8-V8) -> 56.55 | FL8: =FK8/T8 -> 0.0063290431 | FM8: - | FN8: - | FO8: - | FP8: =IF(Q7<((O6+P6+Q6)/3),1,IF(Q7>((O6+P6+Q6)/3),2,0)) -> 1 | FQ8: =IF(W7<((U6+V6+W6)/3),1,IF(W7>((U6+V6+W6)/3),2,0)) -> 1 | FR8: 0 | FS8: - | FT8: 0 | FU8: - | FV8: 0 | FW8: - | FX8: 0 | FY8: -
B9: =$N$69 -> 25730 | D9: =$O$69 -> 25880 | E9: =$P$69 -> 25630.1 | F9: =$Q$69 -> 25845.55 | G9: ='Base Data'!$D$17 -> 0 | L9: =L8+1 -> 6 | M9: ='[4]BANKNIFTY-I'!C25 -> 42801 | N9: ='[4]BANKNIFTY-I'!D25 -> 20735.1 | O9: ='[4]BANKNIFTY-I'!E25 -> 20767.35 | P9: ='[4]BANKNIFTY-I'!F25 -> 20660 | Q9: ='[4]BANKNIFTY-I'!G25 -> 20718.05 | R9: ='[4]BANKNIFTY-I'!H25 -> 38252 | S9: ='[5]NIFTY-I'!C25 -> 42801 | T9: ='[5]NIFTY-I'!D25 -> 8986.9 | U9: ='[5]NIFTY-I'!E25 -> 8988.9 | V9: ='[5]NIFTY-I'!F25 -> 8960.05 | W9: ='[5]NIFTY-I'!G25 -> 8974.1 | X9: ='[5]NIFTY-I'!H25 -> 59040 | Z9: =IF(OR(Q8=0,Q9=0),0,LN(Q9/Q8)) -> -0.00077679838 | AA9: =IF(OR(W8=0,W9=0),0,LN(W9/W8)) -> -0.00056257225 | AB9: 0 | AC9: 0 | AD9: =Z10 -> 0.0018589674 | AE9: - | AF9: =AA10 -> -0.0024545092 | AG9: - | AH9: =IF(OR(Q8=0,Q9=0),0,LN(Q9/Q8)) -> -0.00077679838 | AI9: =AJ8 -> 0.0035491987 | AJ9: =SQRT((0.94*(AI9^2))+(0.06*(AH9^2))) -> 0.0034463325 | AK9: =AJ9*SQRT(365) -> 0.06584209 | AL9: =IF(OR(W8=0,W9=0),0,LN(W9/W8)) -> -0.00056257225 | AM9: =AN8 -> 0.002732491 | AN9: =SQRT((0.94*(AM9^2))+(0.06*(AL9^2))) -> 0.0026528298 | AO9: =AN9*SQRT(365) -> 0.050682243 | AP9: =IF(P9=0,0,LN(O9/P9)) -> 0.0051825782 | AQ9: =AR8 -> 0.0053171385 | AR9: =SQRT((0.94*(AQ9^2))+(0.06*(AP9^2))) -> 0.0053091611 | AS9: =AR9*SQRT(365) -> 0.10143138 | AT9: =IF(V9=0,0,LN(U9/V9)) -> 0.0032146755 | AU9: =AV8 -> 0.0042127049 | AV9: =SQRT((0.94*(AU9^2))+(0.06*(AT9^2))) -> 0.0041595815 | AW9: =AV9*SQRT(365) -> 0.079468693 | AX9: =(N9*R9) -> 7.9315905e+08 | AY9: 0 | AZ9: =(T9*X9) -> 530586576 | BA9: 0 | BB9: 0 | BC9: 0 | BD9: 0 | BE9: =(O9+P9+Q9)/3 -> 20715.133 | BF9: =(BE9*R9) -> 7.9239528e+08 | BG9: =((BF9-BG8)*(2/(1+5)))+BG8 -> 1.1587471e+09 | BH9: =((R9-BH8)*(2/(1+5)))+BH8 -> 55948.667 | BI9: =BG9/BH9 -> 20710.897 | BJ9: 0 | BK9: 0 | BL9: 0 | BM9: =(U9+V9+W9)/3 -> 8974.35 | BN9: =(BM9*X9) -> 5.2984562e+08 | BO9: =((BN9-BO8)*(2/(1+5)))+BO8 -> 8.3435887e+08 | BP9: =((X9-BP8)*(2/(1+5)))+BP8 -> 93258.533 | BQ9: =BO9/BP9 -> 8946.7295 | BR9: =(P9*R9) -> 790286320 | BS9: =(O9*R9) -> 7.9439267e+08 | BT9: 0 | BU9: =AVERAGE(BR5:BR9)/AVERAGE(R5:R9) -> 20608.941 | BV9: =AVERAGE(BS5:BS9)/AVERAGE(R5:R9) -> 20838.116 | BW9: 0 | BX9: 0 | BZ9: =(V9*X9) -> 5.2900135e+08 | CA9: =(U9*X9) -> 530704656 | CB9: 0 | CC9: =AVERAGE(BZ5:BZ9)/AVERAGE(X5:X9) -> 8910.2403 | CD9: =AVERAGE(CA5:CA9)/AVERAGE(X5:X9) -> 8985.7182 | CE9: 0 | CF9: 0 | CH9: 0 | CI9: 0 | CJ9: 0 | CK9: 0 | CL9: 0 | CM9: 0 | CN9: 0 | CO9: 0 | CP9: 0 | CQ9: 0 | CR9: 0 | CS9: 0 | CV9: 0 | CW9: 0 | CX9: 0 | CY9: 0 | CZ9: =(BE9-BE8) -> -0.78333333 | DA9: =IF(CZ9>=0,BF9,0) -> 0 | DB9: =IF(CZ9<0,BF9,0) -> 7.9239528e+08 | DC9: 0 | DD9: 0 | DE9: 0 | DF9: 0 | DG9: 0 | DH9: 0 | DI9: =(BM9-BM8) -> 10.15 | DJ9: =IF(DI9>=0,BN9,0) -> 5.2984562e+08 | DK9: =IF(DI9<0,BN9,0) -> 0 | DL9: 0 | DM9: 0 | DN9: 0 | DO9: 0 | DP9: 0 | DQ9: 0 | DR9: =MAX(O9-P9,ABS(O9-Q8),ABS(Q8-P9)) -> 107.35 | DS9: =(DR9*R9) -> 4106352.2 | DT9: 0 | DU9: 0 | DV9: 0 | DW9: 0 | DX9: 0 | DY9: 0 | DZ9: 0 | EA9: =MAX(U9-V9,ABS(U9-W8),ABS(W8-V9)) -> 28.85 | EB9: =(EA9*X9) -> 1703304 | EC9: 0 | ED9: 0 | EE9: 0 | EF9: 0 | EG9: 0 | EH9: 0 | EI9: 0 | EJ9: =MAX(O9-P9,ABS(O9-Q8),ABS(Q8-P9)) -> 107.35 | EK9: =(EJ9*R9) -> 4106352.2 | EL9: 0 | EM9: 0 | EN9: 0 | EO9: 0 | EP9: 0 | EQ9: - | ES9: =MAX(U9-V9,ABS(U9-W8),ABS(W8-V9)) -> 28.85 | ET9: =(ES9*X9) -> 1703304 | EU9: 0 | EV9: 0 | EW9: 0 | EX9: 0 | EY9: 0 | EZ9: - | FB9: 0 | FC9: 0 | FD9: 0 | FE9: 0 | FF9: =(O9-P9) -> 107.35 | FG9: =FF9/N9 -> 0.0051772116 | FH9: - | FI9: - | FJ9: - | FK9: =(U9-V9) -> 28.85 | FL9: =FK9/T9 -> 0.0032102282 | FM9: - | FN9: - | FO9: - | FP9: =IF(Q8<((O7+P7+Q7)/3),1,IF(Q8>((O7+P7+Q7)/3),2,0)) -> 2 | FQ9: =IF(W8<((U7+V7+W7)/3),1,IF(W8>((U7+V7+W7)/3),2,0)) -> 2 | FR9: 0 | FS9: - | FT9: 0 | FU9: - | FV9: 0 | FW9: - | FX9: 0 | FY9: -
L10: =L9+1 -> 7 | M10: ='[4]BANKNIFTY-I'!C26 -> 42802 | N10: ='[4]BANKNIFTY-I'!D26 -> 20699.9 | O10: ='[4]BANKNIFTY-I'!E26 -> 20787.7 | P10: ='[4]BANKNIFTY-I'!F26 -> 20588.1 | Q10: ='[4]BANKNIFTY-I'!G26 -> 20756.6 | R10: ='[4]BANKNIFTY-I'!H26 -> 87761 | S10: ='[5]NIFTY-I'!C26 -> 42802 | T10: ='[5]NIFTY-I'!D26 -> 8974 | U10: ='[5]NIFTY-I'!E26 -> 8980 | V10: ='[5]NIFTY-I'!F26 -> 8907.65 | W10: ='[5]NIFTY-I'!G26 -> 8952.1 | X10: ='[5]NIFTY-I'!H26 -> 118774 | Z10: =IF(OR(Q9=0,Q10=0),0,LN(Q10/Q9)) -> 0.0018589674 | AA10: =IF(OR(W9=0,W10=0),0,LN(W10/W9)) -> -0.0024545092 | AB10: 0 | AC10: 0 | AD10: =Z11 -> 0.0017641464 | AE10: - | AF10: =AA11 -> 0.00026805759 | AG10: - | AH10: =IF(OR(Q9=0,Q10=0),0,LN(Q10/Q9)) -> 0.0018589674 | AI10: =AJ9 -> 0.0034463325 | AJ10: =SQRT((0.94*(AI10^2))+(0.06*(AH10^2))) -> 0.0033722279 | AK10: =AJ10*SQRT(365) -> 0.064426323 | AL10: =IF(OR(W9=0,W10=0),0,LN(W10/W9)) -> -0.0024545092 | AM10: =AN9 -> 0.0026528298 | AN10: =SQRT((0.94*(AM10^2))+(0.06*(AL10^2))) -> 0.0026413505 | AO10: =AN10*SQRT(365) -> 0.050462931 | AP10: =IF(P10=0,0,LN(O10/P10)) -> 0.0096482267 | AQ10: =AR9 -> 0.0053091611 | AR10: =SQRT((0.94*(AQ10^2))+(0.06*(AP10^2))) -> 0.0056640318 | AS10: =AR10*SQRT(365) -> 0.10821118 | AT10: =IF(V10=0,0,LN(U10/V10)) -> 0.0080894242 | AU10: =AV9 -> 0.0041595815 | AV10: =SQRT((0.94*(AU10^2))+(0.06*(AT10^2))) -> 0.0044933638 | AW10: =AV10*SQRT(365) -> 0.085845595 | AX10: =(N10*R10) -> 1.8166439e+09 | AY10: 0 | AZ10: =(T10*X10) -> 1065877876 | BA10: 0 | BB10: 0 | BC10: 0 | BD10: 0 | BE10: =(O10+P10+Q10)/3 -> 20710.8 | BF10: =(BE10*R10) -> 1.8176005e+09 | BG10: =((BF10-BG9)*(2/(1+5)))+BG9 -> 1.3783649e+09 | BH10: =((R10-BH9)*(2/(1+5)))+BH9 -> 66552.778 | BI10: =BG10/BH10 -> 20710.854 | BJ10: 0 | BK10: 0 | BL10: 0 | BM10: =(U10+V10+W10)/3 -> 8946.5833 | BN10: =(BM10*X10) -> 1.0626215e+09 | BO10: =((BN10-BO9)*(2/(1+5)))+BO9 -> 9.1044641e+08 | BP10: =((X10-BP9)*(2/(1+5)))+BP9 -> 101763.69 | BQ10: =BO10/BP10 -> 8946.6726 | BR10: =(P10*R10) -> 1.8068322e+09 | BS10: =(O10*R10) -> 1.8243493e+09 | BT10: 0 | BU10: =AVERAGE(BR6:BR10)/AVERAGE(R6:R10) -> 20583.451 | BV10: =AVERAGE(BS6:BS10)/AVERAGE(R6:R10) -> 20814.449 | BW10: 0 | BX10: 0 | BZ10: =(V10*X10) -> 1.0579972e+09 | CA10: =(U10*X10) -> 1066590520 | CB10: 0 | CC10: =AVERAGE(BZ6:BZ10)/AVERAGE(X6:X10) -> 8907.2036 | CD10: =AVERAGE(CA6:CA10)/AVERAGE(X6:X10) -> 8982.6584 | CE10: 0 | CF10: 0 | CH10: 0 | CI10: 0 | CJ10: 0 | CK10: 0 | CL10: 0 | CM10: 0 | CN10: 0 | CO10: 0 | CP10: 0 | CQ10: 0 | CR10: 0 | CS10: 0 | CV10: 0 | CW10: 0 | CX10: 0 | CY10: 0 | CZ10: =(BE10-BE9) -> -4.3333333 | DA10: =IF(CZ10>=0,BF10,0) -> 0 | DB10: =IF(CZ10<0,BF10,0) -> 1.8176005e+09 | DC10: 0 | DD10: 0 | DE10: 0 | DF10: 0 | DG10: 0 | DH10: 0 | DI10: =(BM10-BM9) -> -27.766667 | DJ10: =IF(DI10>=0,BN10,0) -> 0 | DK10: =IF(DI10<0,BN10,0) -> 1.0626215e+09 | DL10: 0 | DM10: 0 | DN10: 0 | DO10: 0 | DP10: 0 | DQ10: 0 | DR10: =MAX(O10-P10,ABS(O10-Q9),ABS(Q9-P10)) -> 199.6 | DS10: =(DR10*R10) -> 17517096 | DT10: 0 | DU10: 0 | DV10: 0 | DW10: 0 | DX10: 0 | DY10: 0 | DZ10: 0 | EA10: =MAX(U10-V10,ABS(U10-W9),ABS(W9-V10)) -> 72.35 | EB10: =(EA10*X10) -> 8593298.9 | EC10: 0 | ED10: 0 | EE10: 0 | EF10: 0 | EG10: 0 | EH10: 0 | EI10: 0 | EJ10: =MAX(O10-P10,ABS(O10-Q9),ABS(Q9-P10)) -> 199.6 | EK10: =(EJ10*R10) -> 17517096 | EL10: 0 | EM10: 0 | EN10: 0 | EO10: 0 | EP10: 0 | EQ10: - | ES10: =MAX(U10-V10,ABS(U10-W9),ABS(W9-V10)) -> 72.35 | ET10: =(ES10*X10) -> 8593298.9 | EU10: 0 | EV10: 0 | EW10: 0 | EX10: 0 | EY10: 0 | EZ10: - | FB10: 0 | FC10: 0 | FD10: 0 | FE10: 0 | FF10: =(O10-P10) -> 199.6 | FG10: =FF10/N10 -> 0.0096425587 | FH10: - | FI10: - | FJ10: - | FK10: =(U10-V10) -> 72.35 | FL10: =FK10/T10 -> 0.0080621796 | FM10: - | FN10: - | FO10: - | FP10: =IF(Q9<((O8+P8+Q8)/3),1,IF(Q9>((O8+P8+Q8)/3),2,0)) -> 2 | FQ10: =IF(W9<((U8+V8+W8)/3),1,IF(W9>((U8+V8+W8)/3),2,0)) -> 2 | FR10: 0 | FS10: - | FT10: 0 | FU10: - | FV10: 0 | FW10: - | FX10: 0 | FY10: -
A11: Open Price / HL Mid Point : | D11: =IF($H$11=0,IF(AND('Base Data'!$D$20>='Base Data'!$D$19,'Base Data'!$D$20<='Base Data'!$E$19),$B$9,($D$9+$E$9)/2),IF(AND('Base Data'!$D$20>='Base Data'!$D$19,'Base Data'!$D$20<='Base Data'!$E$19),($B$9*1000),((($D$9*1000)+($E$9*1000))/2))) -> 25755.05 | E11: Price Range : | F11: =IF($G$9=0,($D$11*$AR$69),IF($G$9=1,($D$11*$AJ$69*SQRT('Base Data'!$D$18)),"Check 'Base Data D17'")) -> 282.908 | G11: Price is 1 or 2 Digit : | H11: =IF(F9/100>=1,0,1) -> 0 | L11: =L10+1 -> 8 | M11: ='[4]BANKNIFTY-I'!C27 -> 42803 | N11: ='[4]BANKNIFTY-I'!D27 -> 20680 | O11: ='[4]BANKNIFTY-I'!E27 -> 20864.3 | P11: ='[4]BANKNIFTY-I'!F27 -> 20649 | Q11: ='[4]BANKNIFTY-I'!G27 -> 20793.25 | R11: ='[4]BANKNIFTY-I'!H27 -> 62955 | S11: ='[5]NIFTY-I'!C27 -> 42803 | T11: ='[5]NIFTY-I'!D27 -> 8923 | U11: ='[5]NIFTY-I'!E27 -> 8977.8 | V11: ='[5]NIFTY-I'!F27 -> 8912.65 | W11: ='[5]NIFTY-I'!G27 -> 8954.5 | X11: ='[5]NIFTY-I'!H27 -> 93016 | Z11: =IF(OR(Q10=0,Q11=0),0,LN(Q11/Q10)) -> 0.0017641464 | AA11: =IF(OR(W10=0,W11=0),0,LN(W11/W10)) -> 0.00026805759 | AB11: 0 | AC11: 0 | AD11: =Z12 -> 0.00021879707 | AE11: - | AF11: =AA12 -> 0.00046892795 | AG11: - | AH11: =IF(OR(Q10=0,Q11=0),0,LN(Q11/Q10)) -> 0.0017641464 | AI11: =AJ10 -> 0.0033722279 | AJ11: =SQRT((0.94*(AI11^2))+(0.06*(AH11^2))) -> 0.0032979294 | AK11: =AJ11*SQRT(365) -> 0.063006852 | AL11: =IF(OR(W10=0,W11=0),0,LN(W11/W10)) -> 0.00026805759 | AM11: =AN10 -> 0.0026413505 | AN11: =SQRT((0.94*(AM11^2))+(0.06*(AL11^2))) -> 0.002561726 | AO11: =AN11*SQRT(365) -> 0.048941706 | AP11: =IF(P11=0,0,LN(O11/P11)) -> 0.010372672 | AQ11: =AR10 -> 0.0056640318 | AR11: =SQRT((0.94*(AQ11^2))+(0.06*(AP11^2))) -> 0.0060507785 | AS11: =AR11*SQRT(365) -> 0.11559996 | AT11: =IF(V11=0,0,LN(U11/V11)) -> 0.0072832475 | AU11: =AV10 -> 0.0044933638 | AV11: =SQRT((0.94*(AU11^2))+(0.06*(AT11^2))) -> 0.0047076152 | AW11: =AV11*SQRT(365) -> 0.089938862 | AX11: =(N11*R11) -> 1301909400 | AY11: 0 | AZ11: =(T11*X11) -> 829981768 | BA11: 0 | BB11: 0 | BC11: 0 | BD11: 0 | BE11: =(O11+P11+Q11)/3 -> 20768.85 | BF11: =(BE11*R11) -> 1.307503e+09 | BG11: =((BF11-BG10)*(2/(1+5)))+BG10 -> 1.3547442e+09 | BH11: =((R11-BH10)*(2/(1+5)))+BH10 -> 65353.519 | BI11: =BG11/BH11 -> 20729.477 | BJ11: 0 | BK11: 0 | BL11: 0 | BM11: =(U11+V11+W11)/3 -> 8948.3167 | BN11: =(BM11*X11) -> 8.3233662e+08 | BO11: =((BN11-BO10)*(2/(1+5)))+BO10 -> 8.8440981e+08 | BP11: =((X11-BP10)*(2/(1+5)))+BP10 -> 98847.793 | BQ11: =BO11/BP11 -> 8947.1883 | BR11: =(P11*R11) -> 1299957795 | BS11: =(O11*R11) -> 1.313512e+09 | BT11: 0 | BU11: =AVERAGE(BR7:BR11)/AVERAGE(R7:R11) -> 20597.82 | BV11: =AVERAGE(BS7:BS11)/AVERAGE(R7:R11) -> 20774.646 | BW11: 0 | BX11: 0 | BZ11: =(V11*X11) -> 8.2901905e+08 | CA11: =(U11*X11) -> 8.3507904e+08 | CB11: 0 | CC11: =AVERAGE(BZ7:BZ11)/AVERAGE(X7:X11) -> 8911.0449 | CD11: =AVERAGE(CA7:CA11)/AVERAGE(X7:X11) -> 8970.6671 | CE11: 0 | CF11: 0 | CH11: 0 | CI11: 0 | CJ11: 0 | CK11: 0 | CL11: 0 | CM11: 0 | CN11: 0 | CO11: 0 | CP11: 0 | CQ11: 0 | CR11: 0 | CS11: 0 | CV11: 0 | CW11: 0 | CX11: 0 | CY11: 0 | CZ11: =(BE11-BE10) -> 58.05 | DA11: =IF(CZ11>=0,BF11,0) -> 1.307503e+09 | DB11: =IF(CZ11<0,BF11,0) -> 0 | DC11: 0 | DD11: 0 | DE11: 0 | DF11: 0 | DG11: 0 | DH11: 0 | DI11: =(BM11-BM10) -> 1.7333333 | DJ11: =IF(DI11>=0,BN11,0) -> 8.3233662e+08 | DK11: =IF(DI11<0,BN11,0) -> 0 | DL11: 0 | DM11: 0 | DN11: 0 | DO11: 0 | DP11: 0 | DQ11: 0 | DR11: =MAX(O11-P11,ABS(O11-Q10),ABS(Q10-P11)) -> 215.3 | DS11: =(DR11*R11) -> 13554211 | DT11: 0 | DU11: 0 | DV11: 0 | DW11: 0 | DX11: 0 | DY11: 0 | DZ11: 0 | EA11: =MAX(U11-V11,ABS(U11-W10),ABS(W10-V11)) -> 65.15 | EB11: =(EA11*X11) -> 6059992.4 | EC11: 0 | ED11: 0 | EE11: 0 | EF11: 0 | EG11: 0 | EH11: 0 | EI11: 0 | EJ11: =MAX(O11-P11,ABS(O11-Q10),ABS(Q10-P11)) -> 215.3 | EK11: =(EJ11*R11) -> 13554211 | EL11: 0 | EM11: 0 | EN11: 0 | EO11: 0 | EP11: 0 | EQ11: - | ES11: =MAX(U11-V11,ABS(U11-W10),ABS(W10-V11)) -> 65.15 | ET11: =(ES11*X11) -> 6059992.4 | EU11: 0 | EV11: 0 | EW11: 0 | EX11: 0 | EY11: 0 | EZ11: - | FB11: 0 | FC11: 0 | FD11: 0 | FE11: 0 | FF11: =(O11-P11) -> 215.3 | FG11: =FF11/N11 -> 0.010411025 | FH11: =AVERAGE(FG4:FG11) -> 0.0090668152 | FI11: - | FJ11: - | FK11: =(U11-V11) -> 65.15 | FL11: =FK11/T11 -> 0.007301356 | FM11: =AVERAGE(FL4:FL11) -> 0.0074019832 | FN11: - | FO11: - | FP11: =IF(Q10<((O9+P9+Q9)/3),1,IF(Q10>((O9+P9+Q9)/3),2,0)) -> 2 | FQ11: =IF(W10<((U9+V9+W9)/3),1,IF(W10>((U9+V9+W9)/3),2,0)) -> 1 | FR11: 0 | FS11: - | FT11: 0 | FU11: - | FV11: =ABS(Q11-Q4)/(MAX(O4:O11)-MIN(P4:P11))*100 -> 24.131232 | FW11: =IF(AND(FV11<30,FV11>FV10),"C-R",IF(AND(FV11<30,FV11=FV10),"C-F",IF(AND(FV11<30,FV11<FV10),"C-D",IF(AND(FV11>=30,FV11>FV10),"T-R",IF(AND(FV11>=30,FV11=FV10),"T-F",IF(AND(FV11>=30,FV11<FV10),"T-D","Check")))))) -> C-R | FX11: =ABS(W11-W4)/(MAX(U4:U11)-MIN(V4:V11))*100 -> 31.009615 | FY11: =IF(AND(FX11<30,FX11>FX10),"C-R",IF(AND(FX11<30,FX11=FX10),"C-F",IF(AND(FX11<30,FX11<FX10),"C-D",IF(AND(FX11>=30,FX11>FX10),"T-R",IF(AND(FX11>=30,FX11=FX10),"T-F",IF(AND(FX11>=30,FX11<FX10),"T-D","Check")))))) -> T-R
L12: =L11+1 -> 9 | M12: ='[4]BANKNIFTY-I'!C28 -> 42804 | N12: ='[4]BANKNIFTY-I'!D28 -> 20889.4 | O12: ='[4]BANKNIFTY-I'!E28 -> 20933.4 | P12: ='[4]BANKNIFTY-I'!F28 -> 20703.3 | Q12: ='[4]BANKNIFTY-I'!G28 -> 20797.8 | R12: ='[4]BANKNIFTY-I'!H28 -> 67509 | S12: ='[5]NIFTY-I'!C28 -> 42804 | T12: ='[5]NIFTY-I'!D28 -> 8975 | U12: ='[5]NIFTY-I'!E28 -> 9002.9 | V12: ='[5]NIFTY-I'!F28 -> 8916.4 | W12: ='[5]NIFTY-I'!G28 -> 8958.7 | X12: ='[5]NIFTY-I'!H28 -> 115008 | Z12: =IF(OR(Q11=0,Q12=0),0,LN(Q12/Q11)) -> 0.00021879707 | AA12: =IF(OR(W11=0,W12=0),0,LN(W12/W11)) -> 0.00046892795 | AB12: 0 | AC12: 0 | AD12: =Z13 -> 0.016636653 | AE12: - | AF12: =AA13 -> 0.015978902 | AG12: - | AH12: =IF(OR(Q11=0,Q12=0),0,LN(Q12/Q11)) -> 0.00021879707 | AI12: =AJ11 -> 0.0032979294 | AJ12: =SQRT((0.94*(AI12^2))+(0.06*(AH12^2))) -> 0.0031979103 | AK12: =AJ12*SQRT(365) -> 0.06109599 | AL12: =IF(OR(W11=0,W12=0),0,LN(W12/W11)) -> 0.00046892795 | AM12: =AN11 -> 0.002561726 | AN12: =SQRT((0.94*(AM12^2))+(0.06*(AL12^2))) -> 0.0024863401 | AO12: =AN12*SQRT(365) -> 0.047501461 | AP12: =IF(P12=0,0,LN(O12/P12)) -> 0.011052862 | AQ12: =AR11 -> 0.0060507785 | AR12: =SQRT((0.94*(AQ12^2))+(0.06*(AP12^2))) -> 0.0064610487 | AS12: =AR12*SQRT(365) -> 0.12343816 | AT12: =IF(V12=0,0,LN(U12/V12)) -> 0.00965447 | AU12: =AV11 -> 0.0047076152 | AV12: =SQRT((0.94*(AU12^2))+(0.06*(AT12^2))) -> 0.0051404737 | AW12: =AV12*SQRT(365) -> 0.098208612 | AX12: =(N12*R12) -> 1.4102225e+09 | AY12: 0 | AZ12: =(T12*X12) -> 1032196800 | BA12: 0 | BB12: 0 | BC12: 0 | BD12: 0 | BE12: =(O12+P12+Q12)/3 -> 20811.5 | BF12: =(BE12*R12) -> 1.4049636e+09 | BG12: =((BF12-BG11)*(2/(1+5)))+BG11 -> 1.371484e+09 | BH12: =((R12-BH11)*(2/(1+5)))+BH11 -> 66072.012 | BI12: =BG12/BH12 -> 20757.412 | BJ12: 0 | BK12: 0 | BL12: 0 | BM12: =(U12+V12+W12)/3 -> 8959.3333 | BN12: =(BM12*X12) -> 1.030395e+09 | BO12: =((BN12-BO11)*(2/(1+5)))+BO11 -> 9.3307155e+08 | BP12: =((X12-BP11)*(2/(1+5)))+BP11 -> 104234.53 | BQ12: =BO12/BP12 -> 8951.6551 | BR12: =(P12*R12) -> 1.3976591e+09 | BS12: =(O12*R12) -> 1.4131929e+09 | BT12: 0 | BU12: =AVERAGE(BR8:BR12)/AVERAGE(R8:R12) -> 20637.689 | BV12: =AVERAGE(BS8:BS12)/AVERAGE(R8:R12) -> 20834.557 | BW12: 0 | BX12: 0 | BZ12: =(V12*X12) -> 1.0254573e+09 | CA12: =(U12*X12) -> 1.0354055e+09 | CB12: 0 | CC12: =AVERAGE(BZ8:BZ12)/AVERAGE(X8:X12) -> 8921.2162 | CD12: =AVERAGE(CA8:CA12)/AVERAGE(X8:X12) -> 8987.1434 | CE12: 0 | CF12: 0 | CH12: 0 | CI12: 0 | CJ12: 0 | CK12: 0 | CL12: 0 | CM12: 0 | CN12: 0 | CO12: 0 | CP12: 0 | CQ12: 0 | CR12: 0 | CS12: 0 | CV12: 0 | CW12: 0 | CX12: 0 | CY12: 0 | CZ12: =(BE12-BE11) -> 42.65 | DA12: =IF(CZ12>=0,BF12,0) -> 1.4049636e+09 | DB12: =IF(CZ12<0,BF12,0) -> 0 | DC12: 0 | DD12: 0 | DE12: 0 | DF12: 0 | DG12: 0 | DH12: 0 | DI12: =(BM12-BM11) -> 11.016667 | DJ12: =IF(DI12>=0,BN12,0) -> 1.030395e+09 | DK12: =IF(DI12<0,BN12,0) -> 0 | DL12: 0 | DM12: 0 | DN12: 0 | DO12: 0 | DP12: 0 | DQ12: 0 | DR12: =MAX(O12-P12,ABS(O12-Q11),ABS(Q11-P12)) -> 230.1 | DS12: =(DR12*R12) -> 15533821 | DT12: 0 | DU12: 0 | DV12: 0 | DW12: 0 | DX12: 0 | DY12: 0 | DZ12: 0 | EA12: =MAX(U12-V12,ABS(U12-W11),ABS(W11-V12)) -> 86.5 | EB12: =(EA12*X12) -> 9948192 | EC12: 0 | ED12: 0 | EE12: 0 | EF12: 0 | EG12: 0 | EH12: 0 | EI12: 0 | EJ12: =MAX(O12-P12,ABS(O12-Q11),ABS(Q11-P12)) -> 230.1 | EK12: =(EJ12*R12) -> 15533821 | EL12: =AVERAGE(EK5:EK12) -> 15527432 | EM12: =AVERAGE(R5:R12) -> 66869 | EN12: =EL12/EM12 -> 232.20673 | EO12: =EN12*$F$4 -> 4644.1346 | EP12: =EO12*'Base Data'!$D$13 -> 3483.101 | EQ12: =IF(INT(('Base Data'!$D$7)/EP12)=0,0,INT(('Base Data'!$D$7)/EP12)) -> 3 | ER12: =(EN12/Q12) -> 0.011164966 | ES12: =MAX(U12-V12,ABS(U12-W11),ABS(W11-V12)) -> 86.5 | ET12: =(ES12*X12) -> 9948192 | EU12: =AVERAGE(ET5:ET12) -> 8242979.8 | EV12: =AVERAGE(X5:X12) -> 106139 | EW12: =EU12/EV12 -> 77.662121 | EX12: =EW12*$G$4 -> 5824.659 | EY12: =EX12*'Base Data'!$D$13 -> 4368.4943 | EZ12: =IF(INT(('Base Data'!$D$7)/EY12)=0,0,INT(('Base Data'!$D$7)/EY12)) -> 2 | FA12: =(EW12/W12) -> 0.0086689052 | FB12: 0 | FC12: =(Q12-AVERAGE(BE4:BE11))/EN12 -> 0.3614954 | FD12: 0 | FE12: =(W12-AVERAGE(BM4:BM11))/EW12 -> 0.17302515 | FF12: =(O12-P12) -> 230.1 | FG12: =FF12/N12 -> 0.011015156 | FH12: =AVERAGE(FG5:FG12) -> 0.0097697526 | FI12: - | FJ12: - | FK12: =(U12-V12) -> 86.5 | FL12: =FK12/T12 -> 0.009637883 | FM12: =AVERAGE(FL5:FL12) -> 0.007845916 | FN12: - | FO12: - | FP12: =IF(Q11<((O10+P10+Q10)/3),1,IF(Q11>((O10+P10+Q10)/3),2,0)) -> 2 | FQ12: =IF(W11<((U10+V10+W10)/3),1,IF(W11>((U10+V10+W10)/3),2,0)) -> 2 | FR12: 0 | FS12: - | FT12: 0 | FU12: - | FV12: =ABS(Q12-Q5)/(MAX(O5:O12)-MIN(P5:P12))*100 -> 10.608677 | FW12: =IF(AND(FV12<30,FV12>FV11),"C-R",IF(AND(FV12<30,FV12=FV11),"C-F",IF(AND(FV12<30,FV12<FV11),"C-D",IF(AND(FV12>=30,FV12>FV11),"T-R",IF(AND(FV12>=30,FV12=FV11),"T-F",IF(AND(FV12>=30,FV12<FV11),"T-D","Check")))))) -> C-D | FX12: =ABS(W12-W5)/(MAX(U5:U12)-MIN(V5:V12))*100 -> 11.916209 | FY12: =IF(AND(FX12<30,FX12>FX11),"C-R",IF(AND(FX12<30,FX12=FX11),"C-F",IF(AND(FX12<30,FX12<FX11),"C-D",IF(AND(FX12>=30,FX12>FX11),"T-R",IF(AND(FX12>=30,FX12=FX11),"T-F",IF(AND(FX12>=30,FX12<FX11),"T-D","Check")))))) -> C-D
A13: Angle Degree | B13: Degree Factor | C13: Resistance | D13: Trend Lines | E13: Long Entries, SL & Targets | F13: Short Entries, SL & Targets | G13: Trend Lines | H13: Support | I13: Degree Factor | J13: Angle Degree | L13: =L12+1 -> 10 | M13: ='[4]BANKNIFTY-I'!C29 -> 42808 | N13: ='[4]BANKNIFTY-I'!D29 -> 21246 | O13: ='[4]BANKNIFTY-I'!E29 -> 21326.3 | P13: ='[4]BANKNIFTY-I'!F29 -> 21100 | Q13: ='[4]BANKNIFTY-I'!G29 -> 21146.7 | R13: ='[4]BANKNIFTY-I'!H29 -> 78502 | S13: ='[5]NIFTY-I'!C29 -> 42808 | T13: ='[5]NIFTY-I'!D29 -> 9145 | U13: ='[5]NIFTY-I'!E29 -> 9158 | V13: ='[5]NIFTY-I'!F29 -> 9077.6 | W13: ='[5]NIFTY-I'!G29 -> 9103 | X13: ='[5]NIFTY-I'!H29 -> 190327 | Z13: =IF(OR(Q12=0,Q13=0),0,LN(Q13/Q12)) -> 0.016636653 | AA13: =IF(OR(W12=0,W13=0),0,LN(W13/W12)) -> 0.015978902 | AB13: 0 | AC13: 0 | AD13: =Z14 -> 0.0035827866 | AE13: - | AF13: =AA14 -> 0.00069184016 | AG13: - | AH13: =IF(OR(Q12=0,Q13=0),0,LN(Q13/Q12)) -> 0.016636653 | AI13: =AJ12 -> 0.0031979103 | AJ13: =SQRT((0.94*(AI13^2))+(0.06*(AH13^2))) -> 0.0051205201 | AK13: =AJ13*SQRT(365) -> 0.097827399 | AL13: =IF(OR(W12=0,W13=0),0,LN(W13/W12)) -> 0.015978902 | AM13: =AN12 -> 0.0024863401 | AN13: =SQRT((0.94*(AM13^2))+(0.06*(AL13^2))) -> 0.0045967916 | AO13: =AN13*SQRT(365) -> 0.087821581 | AP13: =IF(P13=0,0,LN(O13/P13)) -> 0.010668012 | AQ13: =AR12 -> 0.0064610487 | AR13: =SQRT((0.94*(AQ13^2))+(0.06*(AP13^2))) -> 0.0067874024 | AS13: =AR13*SQRT(365) -> 0.12967314 | AT13: =IF(V13=0,0,LN(U13/V13)) -> 0.0088179737 | AU13: =AV12 -> 0.0051404737 | AV13: =SQRT((0.94*(AU13^2))+(0.06*(AT13^2))) -> 0.0054317954 | AW13: =AV13*SQRT(365) -> 0.10377431 | AX13: =(N13*R13) -> 1667853492 | AY13: 0 | AZ13: =(T13*X13) -> 1740540415 | BA13: 0 | BB13: 0 | BC13: 0 | BD13: 0 | BE13: =(O13+P13+Q13)/3 -> 21191 | BF13: =(BE13*R13) -> 1663535882 | BG13: =((BF13-BG12)*(2/(1+5)))+BG12 -> 1.4688346e+09 | BH13: =((R13-BH12)*(2/(1+5)))+BH12 -> 70215.342 | BI13: =BG13/BH13 -> 20918.999 | BJ13: 0 | BK13: 0 | BL13: 0 | BM13: =(U13+V13+W13)/3 -> 9112.8667 | BN13: =(BM13*X13) -> 1.7344246e+09 | BO13: =((BN13-BO12)*(2/(1+5)))+BO12 -> 1.2001892e+09 | BP13: =((X13-BP12)*(2/(1+5)))+BP12 -> 132932.02 | BQ13: =BO13/BP13 -> 9028.5939 | BR13: =(P13*R13) -> 1656392200 | BS13: =(O13*R13) -> 1.6741572e+09 | BT13: 0 | BU13: =AVERAGE(BR9:BR13)/AVERAGE(R9:R13) -> 20750.936 | BV13: =AVERAGE(BS9:BS13)/AVERAGE(R9:R13) -> 20955.356 | BW13: 0 | BX13: 0 | BZ13: =(V13*X13) -> 1.7277124e+09 | CA13: =(U13*X13) -> 1743014666 | CB13: 0 | CC13: =AVERAGE(BZ9:BZ13)/AVERAGE(X9:X13) -> 8971.7135 | CD13: =AVERAGE(CA9:CA13)/AVERAGE(X9:X13) -> 9043.9274 | CE13: 0 | CF13: 0 | CH13: 0 | CI13: 0 | CJ13: 0 | CK13: 0 | CL13: 0 | CM13: 0 | CN13: 0 | CO13: 0 | CP13: 0 | CQ13: 0 | CR13: 0 | CS13: 0 | CV13: 0 | CW13: 0 | CX13: 0 | CY13: 0 | CZ13: =(BE13-BE12) -> 379.5 | DA13: =IF(CZ13>=0,BF13,0) -> 1663535882 | DB13: =IF(CZ13<0,BF13,0) -> 0 | DC13: 0 | DD13: 0 | DE13: 0 | DF13: 0 | DG13: 0 | DH13: 0 | DI13: =(BM13-BM12) -> 153.53333 | DJ13: =IF(DI13>=0,BN13,0) -> 1.7344246e+09 | DK13: =IF(DI13<0,BN13,0) -> 0 | DL13: 0 | DM13: 0 | DN13: 0 | DO13: 0 | DP13: 0 | DQ13: 0 | DR13: =MAX(O13-P13,ABS(O13-Q12),ABS(Q12-P13)) -> 528.5 | DS13: =(DR13*R13) -> 41488307 | DT13: 0 | DU13: 0 | DV13: 0 | DW13: 0 | DX13: 0 | DY13: 0 | DZ13: 0 | EA13: =MAX(U13-V13,ABS(U13-W12),ABS(W12-V13)) -> 199.3 | EB13: =(EA13*X13) -> 37932171 | EC13: 0 | ED13: 0 | EE13: 0 | EF13: 0 | EG13: 0 | EH13: 0 | EI13: 0 | EJ13: =MAX(O13-P13,ABS(O13-Q12),ABS(Q12-P13)) -> 528.5 | EK13: =(EJ13*R13) -> 41488307 | EL13: =((EK13-EL12)*(2/(1+8)))+EL12 -> 21296515 | EM13: =((R13-EM12)*(2/(1+8)))+EM12 -> 69454.111 | EN13: =EL13/EM13 -> 306.62714 | EO13: =EN13*$F$4 -> 6132.5428 | EP13: =EO13*'Base Data'!$D$13 -> 4599.4071 | EQ13: =IF(INT(('Base Data'!$D$7)/EP13)=0,0,INT(('Base Data'!$D$7)/EP13)) -> 2 | ER13: =(EN13/Q13) -> 0.014499999 | ES13: =MAX(U13-V13,ABS(U13-W12),ABS(W12-V13)) -> 199.3 | ET13: =(ES13*X13) -> 37932171 | EU13: =((ET13-EU12)*(2/(1+8)))+EU12 -> 14840578 | EV13: =((X13-EV12)*(2/(1+8)))+EV12 -> 124847.44 | EW13: =EU13/EV13 -> 118.8697 | EX13: =EW13*$G$4 -> 8915.2273 | EY13: =EX13*'Base Data'!$D$13 -> 6686.4205 | EZ13: =IF(INT(('Base Data'!$D$7)/EY13)=0,0,INT(('Base Data'!$D$7)/EY13)) -> 1 | FA13: =(EW13/W13) -> 0.013058299 | FB13: 0 | FC13: =(Q13-AVERAGE(BE5:BE12))/EN13 -> 1.3611605 | FD13: 0 | FE13: =(W13-AVERAGE(BM5:BM12))/EW13 -> 1.2757842 | FF13: =(O13-P13) -> 226.3 | FG13: =FF13/N13 -> 0.010651417 | FH13: =AVERAGE(FG6:FG13) -> 0.010045111 | FI13: - | FJ13: - | FK13: =(U13-V13) -> 80.4 | FL13: =FK13/T13 -> 0.0087916894 | FM13: =AVERAGE(FL6:FL13) -> 0.0079321587 | FN13: - | FO13: - | FP13: =IF(Q12<((O11+P11+Q11)/3),1,IF(Q12>((O11+P11+Q11)/3),2,0)) -> 2 | FQ13: =IF(W12<((U11+V11+W11)/3),1,IF(W12>((U11+V11+W11)/3),2,0)) -> 2 | FR13: 0 | FS13: - | FT13: 0 | FU13: - | FV13: =ABS(Q13-Q6)/(MAX(O6:O13)-MIN(P6:P13))*100 -> 61.975472 | FW13: =IF(AND(FV13<30,FV13>FV12),"C-R",IF(AND(FV13<30,FV13=FV12),"C-F",IF(AND(FV13<30,FV13<FV12),"C-D",IF(AND(FV13>=30,FV13>FV12),"T-R",IF(AND(FV13>=30,FV13=FV12),"T-F",IF(AND(FV13>=30,FV13<FV12),"T-D","Check")))))) -> T-R | FX13: =ABS(W13-W6)/(MAX(U6:U13)-MIN(V6:V13))*100 -> 65.12443 | FY13: =IF(AND(FX13<30,FX13>FX12),"C-R",IF(AND(FX13<30,FX13=FX12),"C-F",IF(AND(FX13<30,FX13<FX12),"C-D",IF(AND(FX13>=30,FX13>FX12),"T-R",IF(AND(FX13>=30,FX13=FX12),"T-F",IF(AND(FX13>=30,FX13<FX12),"T-D","Check")))))) -> T-R
L14: =L13+1 -> 11 | M14: ='[4]BANKNIFTY-I'!C30 -> 42809 | N14: ='[4]BANKNIFTY-I'!D30 -> 21152.65 | O14: ='[4]BANKNIFTY-I'!E30 -> 21285 | P14: ='[4]BANKNIFTY-I'!F30 -> 21116.65 | Q14: ='[4]BANKNIFTY-I'!G30 -> 21222.6 | R14: ='[4]BANKNIFTY-I'!H30 -> 56198 | S14: ='[5]NIFTY-I'!C30 -> 42809 | T14: ='[5]NIFTY-I'!D30 -> 9116.2 | U14: ='[5]NIFTY-I'!E30 -> 9130 | V14: ='[5]NIFTY-I'!F30 -> 9101.5 | W14: ='[5]NIFTY-I'!G30 -> 9109.3 | X14: ='[5]NIFTY-I'!H30 -> 73550 | Z14: =IF(OR(Q13=0,Q14=0),0,LN(Q14/Q13)) -> 0.0035827866 | AA14: =IF(OR(W13=0,W14=0),0,LN(W14/W13)) -> 0.00069184016 | AB14: 0 | AC14: 0 | AD14: =Z15 -> 0.0041473349 | AE14: - | AF14: =AA15 -> 0.007311857 | AG14: - | AH14: =IF(OR(Q13=0,Q14=0),0,LN(Q14/Q13)) -> 0.0035827866 | AI14: =AJ13 -> 0.0051205201 | AJ14: =SQRT((0.94*(AI14^2))+(0.06*(AH14^2))) -> 0.0050415002 | AK14: =AJ14*SQRT(365) -> 0.096317726 | AL14: =IF(OR(W13=0,W14=0),0,LN(W14/W13)) -> 0.00069184016 | AM14: =AN13 -> 0.0045967916 | AN14: =SQRT((0.94*(AM14^2))+(0.06*(AL14^2))) -> 0.0044599756 | AO14: =AN14*SQRT(365) -> 0.085207714 | AP14: =IF(P14=0,0,LN(O14/P14)) -> 0.0079407704 | AQ14: =AR13 -> 0.0067874024 | AR14: =SQRT((0.94*(AQ14^2))+(0.06*(AP14^2))) -> 0.0068620734 | AS14: =AR14*SQRT(365) -> 0.13109973 | AT14: =IF(V14=0,0,LN(U14/V14)) -> 0.0031264595 | AU14: =AV13 -> 0.0054317954 | AV14: =SQRT((0.94*(AU14^2))+(0.06*(AT14^2))) -> 0.0053217123 | AW14: =AV14*SQRT(365) -> 0.10167117 | AX14: =(N14*R14) -> 1.1887366e+09 | AY14: 0 | AZ14: =(T14*X14) -> 670496510 | BA14: 0 | BB14: 0 | BC14: 0 | BD14: 0 | BE14: =(O14+P14+Q14)/3 -> 21208.083 | BF14: =(BE14*R14) -> 1.1918519e+09 | BG14: =((BF14-BG13)*(2/(1+5)))+BG13 -> 1.376507e+09 | BH14: =((R14-BH13)*(2/(1+5)))+BH13 -> 65542.894 | BI14: =BG14/BH14 -> 21001.621 | BJ14: 0 | BK14: 0 | BL14: 0 | BM14: =(U14+V14+W14)/3 -> 9113.6 | BN14: =(BM14*X14) -> 670305280 | BO14: =((BN14-BO13)*(2/(1+5)))+BO13 -> 1.0235612e+09 | BP14: =((X14-BP13)*(2/(1+5)))+BP13 -> 113138.01 | BQ14: =BO14/BP14 -> 9047.0145 | BR14: =(P14*R14) -> 1.1867135e+09 | BS14: =(O14*R14) -> 1196174430 | BT14: 0 | BU14: =AVERAGE(BR10:BR14)/AVERAGE(R10:R14) -> 20819.026 | BV14: =AVERAGE(BS10:BS14)/AVERAGE(R10:R14) -> 21028.224 | BW14: 0 | BX14: 0 | BZ14: =(V14*X14) -> 669415325 | CA14: =(U14*X14) -> 671511500 | CB14: 0 | CC14: =AVERAGE(BZ10:BZ14)/AVERAGE(X10:X14) -> 8989.0402 | CD14: =AVERAGE(CA10:CA14)/AVERAGE(X10:X14) -> 9060.1452 | CE14: 0 | CF14: 0 | CH14: 0 | CI14: 0 | CJ14: 0 | CK14: 0 | CL14: 0 | CM14: 0 | CN14: 0 | CO14: 0 | CP14: 0 | CQ14: 0 | CR14: 0 | CS14: 0 | CV14: 0 | CW14: 0 | CX14: 0 | CY14: 0 | CZ14: =(BE14-BE13) -> 17.083333 | DA14: =IF(CZ14>=0,BF14,0) -> 1.1918519e+09 | DB14: =IF(CZ14<0,BF14,0) -> 0 | DC14: 0 | DD14: 0 | DE14: 0 | DF14: 0 | DG14: 0 | DH14: 0 | DI14: =(BM14-BM13) -> 0.73333333 | DJ14: =IF(DI14>=0,BN14,0) -> 670305280 | DK14: =IF(DI14<0,BN14,0) -> 0 | DL14: 0 | DM14: 0 | DN14: 0 | DO14: 0 | DP14: 0 | DQ14: 0 | DR14: =MAX(O14-P14,ABS(O14-Q13),ABS(Q13-P14)) -> 168.35 | DS14: =(DR14*R14) -> 9460933.3 | DT14: 0 | DU14: 0 | DV14: 0 | DW14: 0 | DX14: 0 | DY14: 0 | DZ14: 0 | EA14: =MAX(U14-V14,ABS(U14-W13),ABS(W13-V14)) -> 28.5 | EB14: =(EA14*X14) -> 2096175 | EC14: 0 | ED14: 0 | EE14: 0 | EF14: 0 | EG14: 0 | EH14: 0 | EI14: 0 | EJ14: =MAX(O14-P14,ABS(O14-Q13),ABS(Q13-P14)) -> 168.35 | EK14: =(EJ14*R14) -> 9460933.3 | EL14: =((EK14-EL13)*(2/(1+8)))+EL13 -> 18666386 | EM14: =((R14-EM13)*(2/(1+8)))+EM13 -> 66508.309 | EN14: =EL14/EM14 -> 280.66247 | EO14: =EN14*$F$4 -> 5613.2493 | EP14: =EO14*'Base Data'!$D$13 -> 4209.937 | EQ14: =IF(INT(('Base Data'!$D$7)/EP14)=0,0,INT(('Base Data'!$D$7)/EP14)) -> 2 | ER14: =(EN14/Q14) -> 0.013224698 | ES14: =MAX(U14-V14,ABS(U14-W13),ABS(W13-V14)) -> 28.5 | ET14: =(ES14*X14) -> 2096175 | EU14: =((ET14-EU13)*(2/(1+8)))+EU13 -> 12008488 | EV14: =((X14-EV13)*(2/(1+8)))+EV13 -> 113448.01 | EW14: =EU14/EV14 -> 105.85014 | EX14: =EW14*$G$4 -> 7938.7607 | EY14: =EX14*'Base Data'!$D$13 -> 5954.0706 | EZ14: =IF(INT(('Base Data'!$D$7)/EY14)=0,0,INT(('Base Data'!$D$7)/EY14)) -> 1 | FA14: =(EW14/W14) -> 0.011620008 | FB14: 0 | FC14: =(Q14-AVERAGE(BE6:BE13))/EN14 -> 1.5941227 | FD14: 0 | FE14: =(W14-AVERAGE(BM6:BM13))/EW14 -> 1.3163264 | FF14: =(O14-P14) -> 168.35 | FG14: =FF14/N14 -> 0.0079588137 | FH14: =AVERAGE(FG7:FG14) -> 0.0087911955 | FI14: - | FJ14: - | FK14: =(U14-V14) -> 28.5 | FL14: =FK14/T14 -> 0.0031263026 | FM14: =AVERAGE(FL7:FL14) -> 0.0066557706 | FN14: - | FO14: - | FP14: =IF(Q13<((O12+P12+Q12)/3),1,IF(Q13>((O12+P12+Q12)/3),2,0)) -> 2 | FQ14: =IF(W13<((U12+V12+W12)/3),1,IF(W13>((U12+V12+W12)/3),2,0)) -> 2 | FR14: 0 | FS14: - | FT14: 0 | FU14: - | FV14: =ABS(Q14-Q7)/(MAX(O7:O14)-MIN(P7:P14))*100 -> 77.27546 | FW14: =IF(AND(FV14<30,FV14>FV13),"C-R",IF(AND(FV14<30,FV14=FV13),"C-F",IF(AND(FV14<30,FV14<FV13),"C-D",IF(AND(FV14>=30,FV14>FV13),"T-R",IF(AND(FV14>=30,FV14=FV13),"T-F",IF(AND(FV14>=30,FV14<FV13),"T-D","Check")))))) -> T-R | FX14: =ABS(W14-W7)/(MAX(U7:U14)-MIN(V7:V14))*100 -> 65.369786 | FY14: =IF(AND(FX14<30,FX14>FX13),"C-R",IF(AND(FX14<30,FX14=FX13),"C-F",IF(AND(FX14<30,FX14<FX13),"C-D",IF(AND(FX14>=30,FX14>FX13),"T-R",IF(AND(FX14>=30,FX14=FX13),"T-F",IF(AND(FX14>=30,FX14<FX13),"T-D","Check")))))) -> T-R
A15: 86.25 | B15: =A15/180 -> 0.47916667 | C15: =POWER(SQRT($F$11)+B15,2) -> 299.25664 | D15: 16X1 | E15: =$D$11+(C15*B15) -> 25898.444 | F15: =$D$11-(H15*I15) -> 25627.104 | G15: 1X16 | H15: =POWER(SQRT($F$11)-I15,2) -> 267.01856 | I15: =J15/180 -> 0.47916667 | J15: 86.25 | L15: =L14+1 -> 12 | M15: ='[4]BANKNIFTY-I'!C31 -> 42810 | N15: ='[4]BANKNIFTY-I'!D31 -> 21278.65 | O15: ='[4]BANKNIFTY-I'!E31 -> 21347.1 | P15: ='[4]BANKNIFTY-I'!F31 -> 21250.05 | Q15: ='[4]BANKNIFTY-I'!G31 -> 21310.8 | R15: ='[4]BANKNIFTY-I'!H31 -> 55895 | S15: ='[5]NIFTY-I'!C31 -> 42810 | T15: ='[5]NIFTY-I'!D31 -> 9156 | U15: ='[5]NIFTY-I'!E31 -> 9181.25 | V15: ='[5]NIFTY-I'!F31 -> 9152.1 | W15: ='[5]NIFTY-I'!G31 -> 9176.15 | X15: ='[5]NIFTY-I'!H31 -> 99303 | Z15: =IF(OR(Q14=0,Q15=0),0,LN(Q15/Q14)) -> 0.0041473349 | AA15: =IF(OR(W14=0,W15=0),0,LN(W15/W14)) -> 0.007311857 | AB15: 0 | AC15: 0 | AD15: =Z16 -> -0.003586769 | AE15: - | AF15: =AA16 -> -0.00047961893 | AG15: - | AH15: =IF(OR(Q14=0,Q15=0),0,LN(Q15/Q14)) -> 0.0041473349 | AI15: =AJ14 -> 0.0050415002 | AJ15: =SQRT((0.94*(AI15^2))+(0.06*(AH15^2))) -> 0.0049923686 | AK15: =AJ15*SQRT(365) -> 0.095379067 | AL15: =IF(OR(W14=0,W15=0),0,LN(W15/W14)) -> 0.007311857 | AM15: =AN14 -> 0.0044599756 | AN15: =SQRT((0.94*(AM15^2))+(0.06*(AL15^2))) -> 0.004680352 | AO15: =AN15*SQRT(365) -> 0.089417998 | AP15: =IF(P15=0,0,LN(O15/P15)) -> 0.0045566508 | AQ15: =AR14 -> 0.0068620734 | AR15: =SQRT((0.94*(AQ15^2))+(0.06*(AP15^2))) -> 0.0067460027 | AS15: =AR15*SQRT(365) -> 0.1288822 | AT15: =IF(V15=0,0,LN(U15/V15)) -> 0.0031799998 | AU15: =AV14 -> 0.0053217123 | AV15: =SQRT((0.94*(AU15^2))+(0.06*(AT15^2))) -> 0.0052180579 | AW15: =AV15*SQRT(365) -> 0.099690857 | AX15: =(N15*R15) -> 1.1893701e+09 | AY15: 0 | AZ15: =(T15*X15) -> 909218268 | BA15: 0 | BB15: 0 | BC15: 0 | BD15: 0 | BE15: =(O15+P15+Q15)/3 -> 21302.65 | BF15: =(BE15*R15) -> 1.1907116e+09 | BG15: =((BF15-BG14)*(2/(1+5)))+BG14 -> 1.3145752e+09 | BH15: =((R15-BH14)*(2/(1+5)))+BH14 -> 62326.93 | BI15: =BG15/BH15 -> 21091.609 | BJ15: 0 | BK15: 0 | BL15: 0 | BM15: =(U15+V15+W15)/3 -> 9169.8333 | BN15: =(BM15*X15) -> 9.1059196e+08 | BO15: =((BN15-BO14)*(2/(1+5)))+BO14 -> 9.8590481e+08 | BP15: =((X15-BP14)*(2/(1+5)))+BP14 -> 108526.34 | BQ15: =BO15/BP15 -> 9084.4748 | BR15: =(P15*R15) -> 1.1877715e+09 | BS15: =(O15*R15) -> 1.1931962e+09 | BT15: 0 | BU15: =AVERAGE(BR11:BR15)/AVERAGE(R11:R15) -> 20957.189 | BV15: =AVERAGE(BS11:BS15)/AVERAGE(R11:R15) -> 21149.486 | BW15: 0 | BX15: 0 | BZ15: =(V15*X15) -> 9.0883099e+08 | CA15: =(U15*X15) -> 9.1172567e+08 | CB15: 0 | CC15: =AVERAGE(BZ11:BZ15)/AVERAGE(X11:X15) -> 9034.3119 | CD15: =AVERAGE(CA11:CA15)/AVERAGE(X11:X15) -> 9097.8642 | CE15: 0 | CF15: 0 | CH15: =AVERAGE(BF4:BF15) -> 1.339848e+09 | CI15: =AVERAGE(R4:R15) -> 64254.75 | CJ15: =CH15/CI15 -> 20852.124 | CK15: 0 | CL15: 0 | CM15: 0 | CN15: 0 | CO15: 0 | CP15: 0 | CQ15: =AVERAGE(BN4:BN15) -> 9.7529984e+08 | CR15: =AVERAGE(X4:X15) -> 108404.75 | CS15: =CQ15/CR15 -> 8996.8367 | CV15: 0 | CW15: 0 | CX15: 0 | CY15: 0 | CZ15: =(BE15-BE14) -> 94.566667 | DA15: =IF(CZ15>=0,BF15,0) -> 1.1907116e+09 | DB15: =IF(CZ15<0,BF15,0) -> 0 | DC15: 0 | DD15: 0 | DE15: 0 | DF15: 0 | DG15: 0 | DH15: 0 | DI15: =(BM15-BM14) -> 56.233333 | DJ15: =IF(DI15>=0,BN15,0) -> 9.1059196e+08 | DK15: =IF(DI15<0,BN15,0) -> 0 | DL15: 0 | DM15: 0 | DN15: 0 | DO15: 0 | DP15: 0 | DQ15: 0 | DR15: =MAX(O15-P15,ABS(O15-Q14),ABS(Q14-P15)) -> 124.5 | DS15: =(DR15*R15) -> 6958927.5 | DT15: 0 | DU15: 0 | DV15: 0 | DW15: 0 | DX15: 0 | DY15: 0 | DZ15: 0 | EA15: =MAX(U15-V15,ABS(U15-W14),ABS(W14-V15)) -> 71.95 | EB15: =(EA15*X15) -> 7144850.9 | EC15: 0 | ED15: 0 | EE15: 0 | EF15: 0 | EG15: 0 | EH15: 0 | EI15: 0 | EJ15: =MAX(O15-P15,ABS(O15-Q14),ABS(Q14-P15)) -> 124.5 | EK15: =(EJ15*R15) -> 6958927.5 | EL15: =((EK15-EL14)*(2/(1+8)))+EL14 -> 16064729 | EM15: =((R15-EM14)*(2/(1+8)))+EM14 -> 64149.796 | EN15: =EL15/EM15 -> 250.42525 | EO15: =EN15*$F$4 -> 5008.505 | EP15: =EO15*'Base Data'!$D$13 -> 3756.3787 | EQ15: =IF(INT(('Base Data'!$D$7)/EP15)=0,0,INT(('Base Data'!$D$7)/EP15)) -> 2 | ER15: =(EN15/Q15) -> 0.011751096 | ES15: =MAX(U15-V15,ABS(U15-W14),ABS(W14-V15)) -> 71.95 | ET15: =(ES15*X15) -> 7144850.9 | EU15: =((ET15-EU14)*(2/(1+8)))+EU14 -> 10927680 | EV15: =((X15-EV14)*(2/(1+8)))+EV14 -> 110304.68 | EW15: =EU15/EV15 -> 99.068148 | EX15: =EW15*$G$4 -> 7430.1111 | EY15: =EX15*'Base Data'!$D$13 -> 5572.5833 | EZ15: =IF(INT(('Base Data'!$D$7)/EY15)=0,0,INT(('Base Data'!$D$7)/EY15)) -> 1 | FA15: =(EW15/W15) -> 0.010796265 | FB15: 0 | FC15: =(Q15-AVERAGE(BE7:BE14))/EN15 -> 1.89694 | FD15: 0 | FE15: =(W15-AVERAGE(BM7:BM14))/EW15 -> 1.8679692 | FF15: =(O15-P15) -> 97.05 | FG15: =FF15/N15 -> 0.0045609096 | FH15: =AVERAGE(FG8:FG15) -> 0.0085980029 | FI15: - | FJ15: - | FK15: =(U15-V15) -> 29.15 | FL15: =FK15/T15 -> 0.0031837047 | FM15: =AVERAGE(FL8:FL15) -> 0.0062052983 | FN15: - | FO15: - | FP15: =IF(Q14<((O13+P13+Q13)/3),1,IF(Q14>((O13+P13+Q13)/3),2,0)) -> 2 | FQ15: =IF(W14<((U13+V13+W13)/3),1,IF(W14>((U13+V13+W13)/3),2,0)) -> 1 | FR15: 0 | FS15: - | FT15: 0 | FU15: - | FV15: =ABS(Q15-Q8)/(MAX(O8:O15)-MIN(P8:P15))*100 -> 75.974967 | FW15: =IF(AND(FV15<30,FV15>FV14),"C-R",IF(AND(FV15<30,FV15=FV14),"C-F",IF(AND(FV15<30,FV15<FV14),"C-D",IF(AND(FV15>=30,FV15>FV14),"T-R",IF(AND(FV15>=30,FV15=FV14),"T-F",IF(AND(FV15>=30,FV15<FV14),"T-D","Check")))))) -> T-D | FX15: =ABS(W15-W8)/(MAX(U8:U15)-MIN(V8:V15))*100 -> 72.002924 | FY15: =IF(AND(FX15<30,FX15>FX14),"C-R",IF(AND(FX15<30,FX15=FX14),"C-F",IF(AND(FX15<30,FX15<FX14),"C-D",IF(AND(FX15>=30,FX15>FX14),"T-R",IF(AND(FX15>=30,FX15=FX14),"T-F",IF(AND(FX15>=30,FX15<FX14),"T-D","Check")))))) -> T-R
A16: 82.5 | B16: =A16/180 -> 0.45833333 | C16: =POWER(SQRT($F$11)+B16,2) -> 298.53628 | D16: 8X1 | E16: =$D$11+(C16*B16) -> 25891.879 | F16: =$D$11-(H16*I16) -> 25632.354 | G16: 1X8 | H16: =POWER(SQRT($F$11)-I16,2) -> 267.69985 | I16: =J16/180 -> 0.45833333 | J16: 82.5 | L16: =L15+1 -> 13 | M16: ='[4]BANKNIFTY-I'!C32 -> 42811 | N16: ='[4]BANKNIFTY-I'!D32 -> 21678.5 | O16: ='[4]BANKNIFTY-I'!E32 -> 21678.5 | P16: ='[4]BANKNIFTY-I'!F32 -> 21190.95 | Q16: ='[4]BANKNIFTY-I'!G32 -> 21234.5 | R16: ='[4]BANKNIFTY-I'!H32 -> 55505 | S16: ='[5]NIFTY-I'!C32 -> 42811 | T16: ='[5]NIFTY-I'!D32 -> 9212.85 | U16: ='[5]NIFTY-I'!E32 -> 9212.85 | V16: ='[5]NIFTY-I'!F32 -> 9165.3 | W16: ='[5]NIFTY-I'!G32 -> 9171.75 | X16: ='[5]NIFTY-I'!H32 -> 111152 | Z16: =IF(OR(Q15=0,Q16=0),0,LN(Q16/Q15)) -> -0.003586769 | AA16: =IF(OR(W15=0,W16=0),0,LN(W16/W15)) -> -0.00047961893 | AB16: 0 | AC16: 0 | AD16: =Z17 -> -0.0024494879 | AE16: - | AF16: =AA17 -> -0.0019863256 | AG16: - | AH16: =IF(OR(Q15=0,Q16=0),0,LN(Q16/Q15)) -> -0.003586769 | AI16: =AJ15 -> 0.0049923686 | AJ16: =SQRT((0.94*(AI16^2))+(0.06*(AH16^2))) -> 0.0049193713 | AK16: =AJ16*SQRT(365) -> 0.093984456 | AL16: =IF(OR(W15=0,W16=0),0,LN(W16/W15)) -> -0.00047961893 | AM16: =AN15 -> 0.004680352 | AN16: =SQRT((0.94*(AM16^2))+(0.06*(AL16^2))) -> 0.0045392901 | AO16: =AN16*SQRT(365) -> 0.086723016 | AP16: =IF(P16=0,0,LN(O16/P16)) -> 0.022746782 | AQ16: =AR15 -> 0.0067460027 | AR16: =SQRT((0.94*(AQ16^2))+(0.06*(AP16^2))) -> 0.0085920315 | AS16: =AR16*SQRT(365) -> 0.16415053 | AT16: =IF(V16=0,0,LN(U16/V16)) -> 0.0051746347 | AU16: =AV15 -> 0.0052180579 | AV16: =SQRT((0.94*(AU16^2))+(0.06*(AT16^2))) -> 0.0052154627 | AW16: =AV16*SQRT(365) -> 0.099641276 | AX16: =(N16*R16) -> 1.2032651e+09 | AY16: 0 | AZ16: =(T16*X16) -> 1.0240267e+09 | BA16: 0 | BB16: =AVERAGE(AX4:AX16) -> 1.3299514e+09 | BC16: =AVERAGE(R4:R16) -> 63581.692 | BD16: =BB16/BC16 -> 20917.207 | BE16: =(O16+P16+Q16)/3 -> 21367.983 | BF16: =(BE16*R16) -> 1.1860299e+09 | BG16: =((BF16-BG15)*(2/(1+5)))+BG15 -> 1.2717268e+09 | BH16: =((R16-BH15)*(2/(1+5)))+BH15 -> 60052.953 | BI16: =BG16/BH16 -> 21176.757 | BJ16: =AVERAGE(AZ4:AZ16) -> 9.7963131e+08 | BK16: =AVERAGE(X4:X16) -> 108616.08 | BL16: =BJ16/BK16 -> 9019.211 | BM16: =(U16+V16+W16)/3 -> 9183.3 | BN16: =(BM16*X16) -> 1.0207422e+09 | BO16: =((BN16-BO15)*(2/(1+5)))+BO15 -> 9.9751726e+08 | BP16: =((X16-BP15)*(2/(1+5)))+BP15 -> 109401.56 | BQ16: =BO16/BP16 -> 9117.9436 | BR16: =(P16*R16) -> 1.1762037e+09 | BS16: =(O16*R16) -> 1.2032651e+09 | BT16: =AVERAGE(AX4:AX16)/AVERAGE(R4:R16) -> 20917.207 | BU16: =AVERAGE(BR12:BR16)/AVERAGE(R12:R16) -> 21060.429 | BV16: =AVERAGE(BS12:BS16)/AVERAGE(R12:R16) -> 21300.364 | BW16: 0 | BX16: =AVERAGE(BR4:BR16)/AVERAGE(R4:R16) -> 20782.52 | BY16: =AVERAGE(BS4:BS16)/AVERAGE(R4:R16) -> 21005.102 | BZ16: =(V16*X16) -> 1.0187414e+09 | CA16: =(U16*X16) -> 1.0240267e+09 | CB16: =AVERAGE(AZ4:AZ16)/AVERAGE(X4:X16) -> 9019.211 | CC16: =AVERAGE(BZ12:BZ16)/AVERAGE(X12:X16) -> 9078.2188 | CD16: =AVERAGE(CA12:CA16)/AVERAGE(X12:X16) -> 9138.5008 | CE16: 0 | CF16: =AVERAGE(BZ4:BZ16)/AVERAGE(X4:X16) -> 8978.655 | CG16: =AVERAGE(CA4:CA16)/AVERAGE(X4:X16) -> 9045.5187 | CH16: =((BF16-CH15)*(2/(1+12)))+CH15 -> 1.3161837e+09 | CI16: =((R16-CI15)*(2/(1+12)))+CI15 -> 62908.635 | CJ16: =CH16/CI16 -> 20922.147 | CK16: 0 | CL16: 0 | CM16: 0 | CN16: 0 | CO16: 0 | CP16: 0 | CQ16: =((BN16-CQ15)*(2/(1+12)))+CQ15 -> 9.8229096e+08 | CR16: =((X16-CR15)*(2/(1+12)))+CR15 -> 108827.4 | CS16: =CQ16/CR16 -> 9026.1361 | CV16: 0 | CW16: 0 | CX16: 0 | CY16: 0 | CZ16: =(BE16-BE15) -> 65.333333 | DA16: =IF(CZ16>=0,BF16,0) -> 1.1860299e+09 | DB16: =IF(CZ16<0,BF16,0) -> 0 | DC16: 0 | DD16: 0 | DE16: 0 | DF16: 0 | DG16: 0 | DH16: 0 | DI16: =(BM16-BM15) -> 13.466667 | DJ16: =IF(DI16>=0,BN16,0) -> 1.0207422e+09 | DK16: =IF(DI16<0,BN16,0) -> 0 | DL16: 0 | DM16: 0 | DN16: 0 | DO16: 0 | DP16: 0 | DQ16: 0 | DR16: =MAX(O16-P16,ABS(O16-Q15),ABS(Q15-P16)) -> 487.55 | DS16: =(DR16*R16) -> 27061463 | DT16: 0 | DU16: 0 | DV16: 0 | DW16: 0 | DX16: 0 | DY16: 0 | DZ16: 0 | EA16: =MAX(U16-V16,ABS(U16-W15),ABS(W15-V16)) -> 47.55 | EB16: =(EA16*X16) -> 5285277.6 | EC16: 0 | ED16: 0 | EE16: 0 | EF16: 0 | EG16: 0 | EH16: 0 | EI16: 0 | EJ16: =MAX(O16-P16,ABS(O16-Q15),ABS(Q15-P16)) -> 487.55 | EK16: =(EJ16*R16) -> 27061463 | EL16: =((EK16-EL15)*(2/(1+8)))+EL15 -> 18508447 | EM16: =((R16-EM15)*(2/(1+8)))+EM15 -> 62228.73 | EN16: =EL16/EM16 -> 297.42608 | EO16: =EN16*$F$4 -> 5948.5216 | EP16: =EO16*'Base Data'!$D$13 -> 4461.3912 | EQ16: =IF(INT(('Base Data'!$D$7)/EP16)=0,0,INT(('Base Data'!$D$7)/EP16)) -> 2 | ER16: =(EN16/Q16) -> 0.014006738 | ES16: =MAX(U16-V16,ABS(U16-W15),ABS(W15-V16)) -> 47.55 | ET16: =(ES16*X16) -> 5285277.6 | EU16: =((ET16-EU15)*(2/(1+8)))+EU15 -> 9673812.8 | EV16: =((X16-EV15)*(2/(1+8)))+EV15 -> 110492.97 | EW16: =EU16/EV16 -> 87.551387 | EX16: =EW16*$G$4 -> 6566.354 | EY16: =EX16*'Base Data'!$D$13 -> 4924.7655 | EZ16: =IF(INT(('Base Data'!$D$7)/EY16)=0,0,INT(('Base Data'!$D$7)/EY16)) -> 2 | FA16: =(EW16/W16) -> 0.0095457668 | FB16: 0 | FC16: =(Q16-AVERAGE(BE8:BE15))/EN16 -> 1.0305362 | FD16: 0 | FE16: =(W16-AVERAGE(BM8:BM15))/EW16 -> 1.6917446 | FF16: =(O16-P16) -> 487.55 | FG16: =FF16/N16 -> 0.022490025 | FH16: =AVERAGE(FG9:FG16) -> 0.01023839 | FI16: =AVERAGE(FG4:FG16) -> 0.0099392955 | FJ16: - | FK16: =(U16-V16) -> 47.55 | FL16: =FK16/T16 -> 0.0051612693 | FM16: =AVERAGE(FL9:FL16) -> 0.0060593266 | FN16: =AVERAGE(FL4:FL16) -> 0.0068551319 | FO16: - | FP16: =IF(Q15<((O14+P14+Q14)/3),1,IF(Q15>((O14+P14+Q14)/3),2,0)) -> 2 | FQ16: =IF(W15<((U14+V14+W14)/3),1,IF(W15>((U14+V14+W14)/3),2,0)) -> 2 | FR16: 0 | FS16: - | FT16: 0 | FU16: - | FV16: =ABS(Q16-Q9)/(MAX(O9:O16)-MIN(P9:P16))*100 -> 47.363353 | FW16: =IF(AND(FV16<30,FV16>FV15),"C-R",IF(AND(FV16<30,FV16=FV15),"C-F",IF(AND(FV16<30,FV16<FV15),"C-D",IF(AND(FV16>=30,FV16>FV15),"T-R",IF(AND(FV16>=30,FV16=FV15),"T-F",IF(AND(FV16>=30,FV16<FV15),"T-D","Check")))))) -> T-D | FX16: =ABS(W16-W9)/(MAX(U9:U16)-MIN(V9:V16))*100 -> 64.760813 | FY16: =IF(AND(FX16<30,FX16>FX15),"C-R",IF(AND(FX16<30,FX16=FX15),"C-F",IF(AND(FX16<30,FX16<FX15),"C-D",IF(AND(FX16>=30,FX16>FX15),"T-R",IF(AND(FX16>=30,FX16=FX15),"T-F",IF(AND(FX16>=30,FX16<FX15),"T-D","Check")))))) -> T-D
A17: 75 | B17: =A17/180 -> 0.41666667 | C17: =POWER(SQRT($F$11)+B17,2) -> 297.09817 | D17: 4X1 | E17: =$D$11+(C17*B17) -> 25878.841 | F17: =$D$11-(H17*I17) -> 25642.94 | G17: 1X4 | H17: =POWER(SQRT($F$11)-I17,2) -> 269.06505 | I17: =J17/180 -> 0.41666667 | J17: 75 | L17: =L16+1 -> 14 | M17: ='[4]BANKNIFTY-I'!C33 -> 42814 | N17: ='[4]BANKNIFTY-I'!D33 -> 21206 | O17: ='[4]BANKNIFTY-I'!E33 -> 21235.95 | P17: ='[4]BANKNIFTY-I'!F33 -> 21140 | Q17: ='[4]BANKNIFTY-I'!G33 -> 21182.55 | R17: ='[4]BANKNIFTY-I'!H33 -> 32204 | S17: ='[5]NIFTY-I'!C33 -> 42814 | T17: ='[5]NIFTY-I'!D33 -> 9164.95 | U17: ='[5]NIFTY-I'!E33 -> 9164.95 | V17: ='[5]NIFTY-I'!F33 -> 9142 | W17: ='[5]NIFTY-I'!G33 -> 9153.55 | X17: ='[5]NIFTY-I'!H33 -> 73494 | Z17: =IF(OR(Q16=0,Q17=0),0,LN(Q17/Q16)) -> -0.0024494879 | AA17: =IF(OR(W16=0,W17=0),0,LN(W17/W16)) -> -0.0019863256 | AB17: 0 | AC17: 0 | AD17: =Z18 -> -0.0043431738 | AE17: - | AF17: =AA18 -> -0.001153223 | AG17: - | AH17: =IF(OR(Q16=0,Q17=0),0,LN(Q17/Q16)) -> -0.0024494879 | AI17: =AJ16 -> 0.0049193713 | AJ17: =SQRT((0.94*(AI17^2))+(0.06*(AH17^2))) -> 0.004807099 | AK17: =AJ17*SQRT(365) -> 0.091839497 | AL17: =IF(OR(W16=0,W17=0),0,LN(W17/W16)) -> -0.0019863256 | AM17: =AN16 -> 0.0045392901 | AN17: =SQRT((0.94*(AM17^2))+(0.06*(AL17^2))) -> 0.0044278183 | AO17: =AN17*SQRT(365) -> 0.08459335 | AP17: =IF(P17=0,0,LN(O17/P17)) -> 0.0045285198 | AQ17: =AR16 -> 0.0085920315 | AR17: =SQRT((0.94*(AQ17^2))+(0.06*(AP17^2))) -> 0.0084038131 | AS17: =AR17*SQRT(365) -> 0.16055462 | AT17: =IF(V17=0,0,LN(U17/V17)) -> 0.0025072458 | AU17: =AV16 -> 0.0052154627 | AV17: =SQRT((0.94*(AU17^2))+(0.06*(AT17^2))) -> 0.0050937379 | AW17: =AV17*SQRT(365) -> 0.097315725 | AX17: =(N17*R17) -> 682918024 | AY17: 0 | AZ17: =(T17*X17) -> 6.7356884e+08 | BA17: 0 | BB17: =((AX17-BB16)*(2/(1+13)))+BB16 -> 1.2375181e+09 | BC17: =((R17-BC16)*(2/(1+13)))+BC16 -> 59099.165 | BD17: =BB17/BC17 -> 20939.688 | BE17: =(O17+P17+Q17)/3 -> 21186.167 | BF17: =(BE17*R17) -> 6.8227931e+08 | BG17: =((BF17-BG16)*(2/(1+5)))+BG16 -> 1.0752443e+09 | BH17: =((R17-BH16)*(2/(1+5)))+BH16 -> 50769.969 | BI17: =BG17/BH17 -> 21178.747 | BJ17: =((AZ17-BJ16)*(2/(1+13)))+BJ16 -> 9.359081e+08 | BK17: =((X17-BK16)*(2/(1+13)))+BK16 -> 103598.64 | BL17: =BJ17/BK17 -> 9033.9808 | BM17: =(U17+V17+W17)/3 -> 9153.5 | BN17: =(BM17*X17) -> 672727329 | BO17: =((BN17-BO16)*(2/(1+5)))+BO16 -> 8.8925395e+08 | BP17: =((X17-BP16)*(2/(1+5)))+BP16 -> 97432.374 | BQ17: =BO17/BP17 -> 9126.8837 | BR17: =(P17*R17) -> 680792560 | BS17: =(O17*R17) -> 6.8388253e+08 | BT17: =AVERAGE(AX5:AX17)/AVERAGE(R5:R17) -> 20941.912 | BU17: =AVERAGE(BR13:BR17)/AVERAGE(R13:R17) -> 21156.266 | BV17: =AVERAGE(BS13:BS17)/AVERAGE(R13:R17) -> 21381.926 | BW17: 0 | BX17: =AVERAGE(BR5:BR17)/AVERAGE(R5:R17) -> 20804.926 | BY17: =AVERAGE(BS5:BS17)/AVERAGE(R5:R17) -> 21028.709 | BZ17: =(V17*X17) -> 671882148 | CA17: =(U17*X17) -> 6.7356884e+08 | CB17: =AVERAGE(AZ5:AZ17)/AVERAGE(X5:X17) -> 9033.0732 | CC17: =AVERAGE(BZ13:BZ17)/AVERAGE(X13:X17) -> 9120.7468 | CD17: =AVERAGE(CA13:CA17)/AVERAGE(X13:X17) -> 9170.5165 | CE17: 0 | CF17: =AVERAGE(BZ5:BZ17)/AVERAGE(X5:X17) -> 8993.2403 | CG17: =AVERAGE(CA5:CA17)/AVERAGE(X5:X17) -> 9058.5902 | CH17: =((BF17-CH16)*(2/(1+12)))+CH16 -> 1.21866e+09 | CI17: =((R17-CI16)*(2/(1+12)))+CI16 -> 58184.845 | CJ17: =CH17/CI17 -> 20944.629 | CK17: 0 | CL17: 0 | CM17: 0 | CN17: 0 | CO17: 0 | CP17: 0 | CQ17: =((BN17-CQ16)*(2/(1+12)))+CQ16 -> 9.3466579e+08 | CR17: =((X17-CR16)*(2/(1+12)))+CR16 -> 103391.5 | CS17: =CQ17/CR17 -> 9040.0645 | CV17: 0 | CW17: 0 | CX17: 0 | CY17: 0 | CZ17: =(BE17-BE16) -> -181.81667 | DA17: =IF(CZ17>=0,BF17,0) -> 0 | DB17: =IF(CZ17<0,BF17,0) -> 6.8227931e+08 | DC17: 0 | DD17: 0 | DE17: 0 | DF17: 0 | DG17: 0 | DH17: 0 | DI17: =(BM17-BM16) -> -29.8 | DJ17: =IF(DI17>=0,BN17,0) -> 0 | DK17: =IF(DI17<0,BN17,0) -> 672727329 | DL17: 0 | DM17: 0 | DN17: 0 | DO17: 0 | DP17: 0 | DQ17: 0 | DR17: =MAX(O17-P17,ABS(O17-Q16),ABS(Q16-P17)) -> 95.95 | DS17: =(DR17*R17) -> 3089973.8 | DT17: 0 | DU17: 0 | DV17: 0 | DW17: 0 | DX17: 0 | DY17: 0 | DZ17: 0 | EA17: =MAX(U17-V17,ABS(U17-W16),ABS(W16-V17)) -> 29.75 | EB17: =(EA17*X17) -> 2186446.5 | EC17: 0 | ED17: 0 | EE17: 0 | EF17: 0 | EG17: 0 | EH17: 0 | EI17: 0 | EJ17: =MAX(O17-P17,ABS(O17-Q16),ABS(Q16-P17)) -> 95.95 | EK17: =(EJ17*R17) -> 3089973.8 | EL17: =((EK17-EL16)*(2/(1+8)))+EL16 -> 15082120 | EM17: =((R17-EM16)*(2/(1+8)))+EM16 -> 55556.568 | EN17: =EL17/EM17 -> 271.47321 | EO17: =EN17*$F$4 -> 5429.4642 | EP17: =EO17*'Base Data'!$D$13 -> 4072.0982 | EQ17: =IF(INT(('Base Data'!$D$7)/EP17)=0,0,INT(('Base Data'!$D$7)/EP17)) -> 2 | ER17: =(EN17/Q17) -> 0.012815889 | ES17: =MAX(U17-V17,ABS(U17-W16),ABS(W16-V17)) -> 29.75 | ET17: =(ES17*X17) -> 2186446.5 | EU17: =((ET17-EU16)*(2/(1+8)))+EU16 -> 8009953.6 | EV17: =((X17-EV16)*(2/(1+8)))+EV16 -> 102270.98 | EW17: =EU17/EV17 -> 78.320887 | EX17: =EW17*$G$4 -> 5874.0665 | EY17: =EX17*'Base Data'!$D$13 -> 4405.5499 | EZ17: =IF(INT(('Base Data'!$D$7)/EY17)=0,0,INT(('Base Data'!$D$7)/EY17)) -> 2 | FA17: =(EW17/W17) -> 0.0085563401 | FB17: 0 | FC17: =(Q17-AVERAGE(BE9:BE16))/EN17 -> 0.6374478 | FD17: 0 | FE17: =(W17-AVERAGE(BM9:BM16))/EW17 -> 1.3090644 | FF17: =(O17-P17) -> 95.95 | FG17: =FF17/N17 -> 0.0045246628 | FH17: =AVERAGE(FG10:FG17) -> 0.010156821 | FI17: =AVERAGE(FG5:FG17) -> 0.0098726037 | FJ17: - | FK17: =(U17-V17) -> 22.95 | FL17: =FK17/T17 -> 0.0025041053 | FM17: =AVERAGE(FL10:FL17) -> 0.0059710613 | FN17: =AVERAGE(FL5:FL17) -> 0.0065795692 | FO17: - | FP17: =IF(Q16<((O15+P15+Q15)/3),1,IF(Q16>((O15+P15+Q15)/3),2,0)) -> 1 | FQ17: =IF(W16<((U15+V15+W15)/3),1,IF(W16>((U15+V15+W15)/3),2,0)) -> 2 | FR17: 0 | FS17: - | FT17: 0 | FU17: - | FV17: =ABS(Q17-Q10)/(MAX(O10:O17)-MIN(P10:P17))*100 -> 39.063646 | FW17: =IF(AND(FV17<30,FV17>FV16),"C-R",IF(AND(FV17<30,FV17=FV16),"C-F",IF(AND(FV17<30,FV17<FV16),"C-D",IF(AND(FV17>=30,FV17>FV16),"T-R",IF(AND(FV17>=30,FV17=FV16),"T-F",IF(AND(FV17>=30,FV17<FV16),"T-D","Check")))))) -> T-D | FX17: =ABS(W17-W10)/(MAX(U10:U17)-MIN(V10:V17))*100 -> 66.005898 | FY17: =IF(AND(FX17<30,FX17>FX16),"C-R",IF(AND(FX17<30,FX17=FX16),"C-F",IF(AND(FX17<30,FX17<FX16),"C-D",IF(AND(FX17>=30,FX17>FX16),"T-R",IF(AND(FX17>=30,FX17=FX16),"T-F",IF(AND(FX17>=30,FX17<FX16),"T-D","Check")))))) -> T-R
A18: 71.25 | B18: =A18/180 -> 0.39583333 | C18: =POWER(SQRT($F$11)+B18,2) -> 296.38041 | D18: 3X1 | E18: =$D$11+(C18*B18) -> 25872.367 | F18: =$D$11-(H18*I18) -> 25648.274 | G18: 1X3 | H18: =POWER(SQRT($F$11)-I18,2) -> 269.74895 | I18: =J18/180 -> 0.39583333 | J18: 71.25 | L18: =L17+1 -> 15 | M18: ='[4]BANKNIFTY-I'!C34 -> 42815 | N18: ='[4]BANKNIFTY-I'!D34 -> 21153.7 | O18: ='[4]BANKNIFTY-I'!E34 -> 21213 | P18: ='[4]BANKNIFTY-I'!F34 -> 21037.55 | Q18: ='[4]BANKNIFTY-I'!G34 -> 21090.75 | R18: ='[4]BANKNIFTY-I'!H34 -> 54610 | S18: ='[5]NIFTY-I'!C34 -> 42815 | T18: ='[5]NIFTY-I'!D34 -> 9165.15 | U18: ='[5]NIFTY-I'!E34 -> 9171.85 | V18: ='[5]NIFTY-I'!F34 -> 9113.65 | W18: ='[5]NIFTY-I'!G34 -> 9143 | X18: ='[5]NIFTY-I'!H34 -> 100487 | Z18: =IF(OR(Q17=0,Q18=0),0,LN(Q18/Q17)) -> -0.0043431738 | AA18: =IF(OR(W17=0,W18=0),0,LN(W18/W17)) -> -0.001153223 | AB18: 0 | AC18: 0 | AD18: =Z19 -> -0.011523774 | AE18: - | AF18: =AA19 -> -0.010179604 | AG18: - | AH18: =IF(OR(Q17=0,Q18=0),0,LN(Q18/Q17)) -> -0.0043431738 | AI18: =AJ17 -> 0.004807099 | AJ18: =SQRT((0.94*(AI18^2))+(0.06*(AH18^2))) -> 0.0047805332 | AK18: =AJ18*SQRT(365) -> 0.091331959 | AL18: =IF(OR(W17=0,W18=0),0,LN(W18/W17)) -> -0.001153223 | AM18: =AN17 -> 0.0044278183 | AN18: =SQRT((0.94*(AM18^2))+(0.06*(AL18^2))) -> 0.0043022129 | AO18: =AN18*SQRT(365) -> 0.082193662 | AP18: =IF(P18=0,0,LN(O18/P18)) -> 0.0083052651 | AQ18: =AR17 -> 0.0084038131 | AR18: =SQRT((0.94*(AQ18^2))+(0.06*(AP18^2))) -> 0.0083979328 | AS18: =AR18*SQRT(365) -> 0.16044228 | AT18: =IF(V18=0,0,LN(U18/V18)) -> 0.0063657211 | AU18: =AV17 -> 0.0050937379 | AV18: =SQRT((0.94*(AU18^2))+(0.06*(AT18^2))) -> 0.0051788744 | AW18: =AV18*SQRT(365) -> 0.098942256 | AX18: =(N18*R18) -> 1155203557 | AY18: 0 | AZ18: =(T18*X18) -> 9.2097843e+08 | BA18: 0 | BB18: =((AX18-BB17)*(2/(1+13)))+BB17 -> 1.2257589e+09 | BC18: =((R18-BC17)*(2/(1+13)))+BC17 -> 58457.856 | BD18: =BB18/BC18 -> 20968.249 | BE18: =(O18+P18+Q18)/3 -> 21113.767 | BF18: =(BE18*R18) -> 1.1530228e+09 | BG18: =((BF18-BG17)*(2/(1+5)))+BG17 -> 1.1011705e+09 | BH18: =((R18-BH17)*(2/(1+5)))+BH17 -> 52049.979 | BI18: =BG18/BH18 -> 21156.021 | BJ18: =((AZ18-BJ17)*(2/(1+13)))+BJ17 -> 9.3377529e+08 | BK18: =((X18-BK17)*(2/(1+13)))+BK17 -> 103154.12 | BL18: =BJ18/BK18 -> 9052.2348 | BM18: =(U18+V18+W18)/3 -> 9142.8333 | BN18: =(BM18*X18) -> 9.1873589e+08 | BO18: =((BN18-BO17)*(2/(1+5)))+BO17 -> 8.9908127e+08 | BP18: =((X18-BP17)*(2/(1+5)))+BP17 -> 98450.583 | BQ18: =BO18/BP18 -> 9132.3102 | BR18: =(P18*R18) -> 1.1488606e+09 | BS18: =(O18*R18) -> 1158441930 | BT18: =AVERAGE(AX6:AX18)/AVERAGE(R6:R18) -> 20970.079 | BU18: =AVERAGE(BR14:BR18)/AVERAGE(R14:R18) -> 21148.145 | BV18: =AVERAGE(BS14:BS18)/AVERAGE(R14:R18) -> 21362.83 | BW18: 0 | BX18: =AVERAGE(BR6:BR18)/AVERAGE(R6:R18) -> 20826.57 | BY18: =AVERAGE(BS6:BS18)/AVERAGE(R6:R18) -> 21050.677 | BZ18: =(V18*X18) -> 9.1580335e+08 | CA18: =(U18*X18) -> 9.2165169e+08 | CB18: =AVERAGE(AZ6:AZ18)/AVERAGE(X6:X18) -> 9051.5696 | CC18: =AVERAGE(BZ14:BZ18)/AVERAGE(X14:X18) -> 9137.1204 | CD18: =AVERAGE(CA14:CA18)/AVERAGE(X14:X18) -> 9176.0106 | CE18: 0 | CF18: =AVERAGE(BZ6:BZ18)/AVERAGE(X6:X18) -> 9007.8241 | CG18: =AVERAGE(CA6:CA18)/AVERAGE(X6:X18) -> 9072.0873 | CH18: =((BF18-CH17)*(2/(1+12)))+CH17 -> 1.2085619e+09 | CI18: =((R18-CI17)*(2/(1+12)))+CI17 -> 57634.869 | CJ18: =CH18/CI18 -> 20969.284 | CK18: 0 | CL18: 0 | CM18: 0 | CN18: 0 | CO18: 0 | CP18: 0 | CQ18: =((BN18-CQ17)*(2/(1+12)))+CQ17 -> 9.3221504e+08 | CR18: =((X18-CR17)*(2/(1+12)))+CR17 -> 102944.65 | CS18: =CQ18/CR18 -> 9055.4976 | CV18: 0 | CW18: 0 | CX18: 0 | CY18: 0 | CZ18: =(BE18-BE17) -> -72.4 | DA18: =IF(CZ18>=0,BF18,0) -> 0 | DB18: =IF(CZ18<0,BF18,0) -> 1.1530228e+09 | DC18: =AVERAGE(DA5:DA18) -> 7.450049e+08 | DD18: =AVERAGE(DB5:DB18) -> 5.5199585e+08 | DE18: =IF(DD18=0,100000,(DC18/DD18)) -> 1.3496567 | DF18: =100-(100/(1+DE18)) -> 57.440591 | DG18: 0 | DH18: 0 | DI18: =(BM18-BM17) -> -10.666667 | DJ18: =IF(DI18>=0,BN18,0) -> 0 | DK18: =IF(DI18<0,BN18,0) -> 9.1873589e+08 | DL18: =AVERAGE(DJ5:DJ18) -> 6.1225678e+08 | DM18: =AVERAGE(DK5:DK18) -> 3.539312e+08 | DN18: =IF(DM18=0,100000,(DL18/DM18)) -> 1.7298751 | DO18: =100-(100/(1+DN18)) -> 63.368288 | DP18: 0 | DQ18: 0 | DR18: =MAX(O18-P18,ABS(O18-Q17),ABS(Q17-P18)) -> 175.45 | DS18: =(DR18*R18) -> 9581324.5 | DT18: 0 | DU18: 0 | DV18: 0 | DW18: 0 | DX18: 0 | DY18: 0 | DZ18: 0 | EA18: =MAX(U18-V18,ABS(U18-W17),ABS(W17-V18)) -> 58.2 | EB18: =(EA18*X18) -> 5848343.4 | EC18: 0 | ED18: 0 | EE18: 0 | EF18: 0 | EG18: 0 | EH18: 0 | EI18: 0 | EJ18: =MAX(O18-P18,ABS(O18-Q17),ABS(Q17-P18)) -> 175.45 | EK18: =(EJ18*R18) -> 9581324.5 | EL18: =((EK18-EL17)*(2/(1+8)))+EL17 -> 13859721 | EM18: =((R18-EM17)*(2/(1+8)))+EM17 -> 55346.219 | EN18: =EL18/EM18 -> 250.41857 | EO18: =EN18*$F$4 -> 5008.3713 | EP18: =EO18*'Base Data'!$D$13 -> 3756.2785 | EQ18: =IF(INT(('Base Data'!$D$7)/EP18)=0,0,INT(('Base Data'!$D$7)/EP18)) -> 2 | ER18: =(EN18/Q18) -> 0.011873384 | ES18: =MAX(U18-V18,ABS(U18-W17),ABS(W17-V18)) -> 58.2 | ET18: =(ES18*X18) -> 5848343.4 | EU18: =((ET18-EU17)*(2/(1+8)))+EU17 -> 7529595.8 | EV18: =((X18-EV17)*(2/(1+8)))+EV17 -> 101874.54 | EW18: =EU18/EV18 -> 73.910478 | EX18: =EW18*$G$4 -> 5543.2859 | EY18: =EX18*'Base Data'!$D$13 -> 4157.4644 | EZ18: =IF(INT(('Base Data'!$D$7)/EY18)=0,0,INT(('Base Data'!$D$7)/EY18)) -> 2 | FA18: =(EW18/W18) -> 0.0080838323 | FB18: 0 | FC18: =(Q18-AVERAGE(BE10:BE17))/EN18 -> 0.089333765 | FD18: 0 | FE18: =(W18-AVERAGE(BM10:BM17))/EW18 -> 0.94145424 | FF18: =(O18-P18) -> 175.45 | FG18: =FF18/N18 -> 0.0082940573 | FH18: =AVERAGE(FG11:FG18) -> 0.0099882583 | FI18: =AVERAGE(FG6:FG18) -> 0.0098607199 | FJ18: - | FK18: =(U18-V18) -> 58.2 | FL18: =FK18/T18 -> 0.0063501416 | FM18: =AVERAGE(FL11:FL18) -> 0.0057570565 | FN18: =AVERAGE(FL6:FL18) -> 0.0064448302 | FO18: - | FP18: =IF(Q17<((O16+P16+Q16)/3),1,IF(Q17>((O16+P16+Q16)/3),2,0)) -> 1 | FQ18: =IF(W17<((U16+V16+W16)/3),1,IF(W17>((U16+V16+W16)/3),2,0)) -> 1 | FR18: 0 | FS18: - | FT18: 0 | FU18: - | FV18: =ABS(Q18-Q11)/(MAX(O11:O18)-MIN(P11:P18))*100 -> 28.897523 | FW18: =IF(AND(FV18<30,FV18>FV17),"C-R",IF(AND(FV18<30,FV18=FV17),"C-F",IF(AND(FV18<30,FV18<FV17),"C-D",IF(AND(FV18>=30,FV18>FV17),"T-R",IF(AND(FV18>=30,FV18=FV17),"T-F",IF(AND(FV18>=30,FV18<FV17),"T-D","Check")))))) -> C-D | FX18: =ABS(W18-W11)/(MAX(U11:U18)-MIN(V11:V18))*100 -> 62.791472 | FY18: =IF(AND(FX18<30,FX18>FX17),"C-R",IF(AND(FX18<30,FX18=FX17),"C-F",IF(AND(FX18<30,FX18<FX17),"C-D",IF(AND(FX18>=30,FX18>FX17),"T-R",IF(AND(FX18>=30,FX18=FX17),"T-F",IF(AND(FX18>=30,FX18<FX17),"T-D","Check")))))) -> T-D
A19: 63.75 | B19: =A19/180 -> 0.35416667 | C19: =POWER(SQRT($F$11)+B19,2) -> 294.94751 | D19: 2X1 | E19: =$D$11+(C19*B19) -> 25859.511 | F19: =$D$11-(H19*I19) -> 25659.029 | G19: 1X2 | H19: =POWER(SQRT($F$11)-I19,2) -> 271.11936 | I19: =J19/180 -> 0.35416667 | J19: 63.75 | L19: =L18+1 -> 16 | M19: ='[4]BANKNIFTY-I'!C35 -> 42816 | N19: ='[4]BANKNIFTY-I'!D35 -> 21017.35 | O19: ='[4]BANKNIFTY-I'!E35 -> 21017.35 | P19: ='[4]BANKNIFTY-I'!F35 -> 20827.3 | Q19: ='[4]BANKNIFTY-I'!G35 -> 20849.1 | R19: ='[4]BANKNIFTY-I'!H35 -> 62985 | S19: ='[5]NIFTY-I'!C35 -> 42816 | T19: ='[5]NIFTY-I'!D35 -> 9081 | U19: ='[5]NIFTY-I'!E35 -> 9130 | V19: ='[5]NIFTY-I'!F35 -> 9045 | W19: ='[5]NIFTY-I'!G35 -> 9050.4 | X19: ='[5]NIFTY-I'!H35 -> 142176 | Z19: =IF(OR(Q18=0,Q19=0),0,LN(Q19/Q18)) -> -0.011523774 | AA19: =IF(OR(W18=0,W19=0),0,LN(W19/W18)) -> -0.010179604 | AB19: 0 | AC19: 0 | AD19: =Z20 -> 0.0049591208 | AE19: - | AF19: =AA20 -> 0.0063057641 | AG19: - | AH19: =IF(OR(Q18=0,Q19=0),0,LN(Q19/Q18)) -> -0.011523774 | AI19: =AJ18 -> 0.0047805332 | AJ19: =SQRT((0.94*(AI19^2))+(0.06*(AH19^2))) -> 0.0054267974 | AK19: =AJ19*SQRT(365) -> 0.10367882 | AL19: =IF(OR(W18=0,W19=0),0,LN(W19/W18)) -> -0.010179604 | AM19: =AN18 -> 0.0043022129 | AN19: =SQRT((0.94*(AM19^2))+(0.06*(AL19^2))) -> 0.0048596248 | AO19: =AN19*SQRT(365) -> 0.092843002 | AP19: =IF(P19=0,0,LN(O19/P19)) -> 0.009083661 | AQ19: =AR18 -> 0.0083979328 | AR19: =SQRT((0.94*(AQ19^2))+(0.06*(AP19^2))) -> 0.0084406477 | AS19: =AR19*SQRT(365) -> 0.16125835 | AT19: =IF(V19=0,0,LN(U19/V19)) -> 0.0093535758 | AU19: =AV18 -> 0.0051788744 | AV19: =SQRT((0.94*(AU19^2))+(0.06*(AT19^2))) -> 0.0055191356 | AW19: =AV19*SQRT(365) -> 0.10544294 | AX19: =(N19*R19) -> 1.3237778e+09 | AY19: 0 | AZ19: =(T19*X19) -> 1291100256 | BA19: 0 | BB19: =((AX19-BB18)*(2/(1+13)))+BB18 -> 1.2397616e+09 | BC19: =((R19-BC18)*(2/(1+13)))+BC18 -> 59104.59 | BD19: =BB19/BC19 -> 20975.724 | BE19: =(O19+P19+Q19)/3 -> 20897.917 | BF19: =(BE19*R19) -> 1.3162553e+09 | BG19: =((BF19-BG18)*(2/(1+5)))+BG18 -> 1.1728654e+09 | BH19: =((R19-BH18)*(2/(1+5)))+BH18 -> 55694.986 | BI19: =BG19/BH19 -> 21058.725 | BJ19: =((AZ19-BJ18)*(2/(1+13)))+BJ18 -> 9.8482171e+08 | BK19: =((X19-BK18)*(2/(1+13)))+BK18 -> 108728.67 | BL19: =BJ19/BK19 -> 9057.6082 | BM19: =(U19+V19+W19)/3 -> 9075.1333 | BN19: =(BM19*X19) -> 1.2902662e+09 | BO19: =((BN19-BO18)*(2/(1+5)))+BO18 -> 1.0294762e+09 | BP19: =((X19-BP18)*(2/(1+5)))+BP18 -> 113025.72 | BQ19: =BO19/BP19 -> 9108.3358 | BR19: =(P19*R19) -> 1.3118075e+09 | BS19: =(O19*R19) -> 1.3237778e+09 | BT19: =AVERAGE(AX7:AX19)/AVERAGE(R7:R19) -> 20980.144 | BU19: =AVERAGE(BR15:BR19)/AVERAGE(R15:R19) -> 21077.553 | BV19: =AVERAGE(BS15:BS19)/AVERAGE(R15:R19) -> 21296.267 | BW19: 0 | BX19: =AVERAGE(BR7:BR19)/AVERAGE(R7:R19) -> 20860.468 | BY19: =AVERAGE(BS7:BS19)/AVERAGE(R7:R19) -> 21060.741 | BZ19: =(V19*X19) -> 1285981920 | CA19: =(U19*X19) -> 1298066880 | CB19: =AVERAGE(AZ7:AZ19)/AVERAGE(X7:X19) -> 9059.9851 | CC19: =AVERAGE(BZ15:BZ19)/AVERAGE(X15:X19) -> 9117.2245 | CD19: =AVERAGE(CA15:CA19)/AVERAGE(X15:X19) -> 9170.0147 | CE19: 0 | CF19: =AVERAGE(BZ7:BZ19)/AVERAGE(X7:X19) -> 9023.3182 | CG19: =AVERAGE(CA7:CA19)/AVERAGE(X7:X19) -> 9083.7804 | CH19: =((BF19-CH18)*(2/(1+12)))+CH18 -> 1.2251301e+09 | CI19: =((R19-CI18)*(2/(1+12)))+CI18 -> 58457.966 | CJ19: =CH19/CI19 -> 20957.454 | CK19: 0 | CL19: 0 | CM19: 0 | CN19: 0 | CO19: 0 | CP19: 0 | CQ19: =((BN19-CQ18)*(2/(1+12)))+CQ18 -> 9.8729982e+08 | CR19: =((X19-CR18)*(2/(1+12)))+CR18 -> 108980.24 | CS19: =CQ19/CR19 -> 9059.4387 | CV19: 0 | CW19: 0 | CX19: 0 | CY19: 0 | CZ19: =(BE19-BE18) -> -215.85 | DA19: =IF(CZ19>=0,BF19,0) -> 0 | DB19: =IF(CZ19<0,BF19,0) -> 1.3162553e+09 | DC19: =((DA19-DC18)*(2/(1+14)))+DC18 -> 6.4567092e+08 | DD19: =((DB19-DD18)*(2/(1+14)))+DD18 -> 6.5389711e+08 | DE19: =IF(DD19=0,100000,(DC19/DD19)) -> 0.98741975 | DF19: =100-(100/(1+DE19)) -> 49.683503 | DG19: 0 | DH19: 0 | DI19: =(BM19-BM18) -> -67.7 | DJ19: =IF(DI19>=0,BN19,0) -> 0 | DK19: =IF(DI19<0,BN19,0) -> 1.2902662e+09 | DL19: =((DJ19-DL18)*(2/(1+14)))+DL18 -> 5.3062254e+08 | DM19: =((DK19-DM18)*(2/(1+14)))+DM18 -> 4.7877586e+08 | DN19: =IF(DM19=0,100000,(DL19/DM19)) -> 1.1082901 | DO19: =100-(100/(1+DN19)) -> 52.568197 | DP19: 0 | DQ19: 0 | DR19: =MAX(O19-P19,ABS(O19-Q18),ABS(Q18-P19)) -> 263.45 | DS19: =(DR19*R19) -> 16593398 | DT19: 0 | DU19: 0 | DV19: 0 | DW19: 0 | DX19: 0 | DY19: 0 | DZ19: 0 | EA19: =MAX(U19-V19,ABS(U19-W18),ABS(W18-V19)) -> 98 | EB19: =(EA19*X19) -> 13933248 | EC19: 0 | ED19: 0 | EE19: 0 | EF19: 0 | EG19: 0 | EH19: 0 | EI19: 0 | EJ19: =MAX(O19-P19,ABS(O19-Q18),ABS(Q18-P19)) -> 263.45 | EK19: =(EJ19*R19) -> 16593398 | EL19: =((EK19-EL18)*(2/(1+8)))+EL18 -> 14467205 | EM19: =((R19-EM18)*(2/(1+8)))+EM18 -> 57043.726 | EN19: =EL19/EM19 -> 253.61605 | EO19: =EN19*$F$4 -> 5072.3211 | EP19: =EO19*'Base Data'!$D$13 -> 3804.2408 | EQ19: =IF(INT(('Base Data'!$D$7)/EP19)=0,0,INT(('Base Data'!$D$7)/EP19)) -> 2 | ER19: =(EN19/Q19) -> 0.012164365 | ES19: =MAX(U19-V19,ABS(U19-W18),ABS(W18-V19)) -> 98 | ET19: =(ES19*X19) -> 13933248 | EU19: =((ET19-EU18)*(2/(1+8)))+EU18 -> 8952629.6 | EV19: =((X19-EV18)*(2/(1+8)))+EV18 -> 110830.42 | EW19: =EU19/EV19 -> 80.77773 | EX19: =EW19*$G$4 -> 6058.3298 | EY19: =EX19*'Base Data'!$D$13 -> 4543.7473 | EZ19: =IF(INT(('Base Data'!$D$7)/EY19)=0,0,INT(('Base Data'!$D$7)/EY19)) -> 2 | FA19: =(EW19/W19) -> 0.0089253216 | FB19: 0 | FC19: =(Q19-AVERAGE(BE11:BE18))/EN19 -> -1.0632213 | FD19: 0 | FE19: =(W19-AVERAGE(BM11:BM18))/EW19 -> -0.58862655 | FF19: =(O19-P19) -> 190.05 | FG19: =FF19/N19 -> 0.0090425291 | FH19: =AVERAGE(FG12:FG19) -> 0.0098171963 | FI19: =AVERAGE(FG7:FG19) -> 0.0091724421 | FJ19: - | FK19: =(U19-V19) -> 85 | FL19: =FK19/T19 -> 0.0093602026 | FM19: =AVERAGE(FL12:FL19) -> 0.0060144123 | FN19: =AVERAGE(FL7:FL19) -> 0.0061388914 | FO19: - | FP19: =IF(Q18<((O17+P17+Q17)/3),1,IF(Q18>((O17+P17+Q17)/3),2,0)) -> 1 | FQ19: =IF(W18<((U17+V17+W17)/3),1,IF(W18>((U17+V17+W17)/3),2,0)) -> 1 | FR19: 0 | FS19: - | FT19: 0 | FU19: - | FV19: =ABS(Q19-Q12)/(MAX(O12:O19)-MIN(P12:P19))*100 -> 5.2604594 | FW19: =IF(AND(FV19<30,FV19>FV18),"C-R",IF(AND(FV19<30,FV19=FV18),"C-F",IF(AND(FV19<30,FV19<FV18),"C-D",IF(AND(FV19>=30,FV19>FV18),"T-R",IF(AND(FV19>=30,FV19=FV18),"T-F",IF(AND(FV19>=30,FV19<FV18),"T-D","Check")))))) -> C-D | FX19: =ABS(W19-W12)/(MAX(U12:U19)-MIN(V12:V19))*100 -> 30.932704 | FY19: =IF(AND(FX19<30,FX19>FX18),"C-R",IF(AND(FX19<30,FX19=FX18),"C-F",IF(AND(FX19<30,FX19<FX18),"C-D",IF(AND(FX19>=30,FX19>FX18),"T-R",IF(AND(FX19>=30,FX19=FX18),"T-F",IF(AND(FX19>=30,FX19<FX18),"T-D","Check")))))) -> T-D
A20: 45 | B20: =A20/180 -> 0.25 | C20: =POWER(SQRT($F$11)+B20,2) -> 291.38043 | D20: 1X1 | E20: =$D$11+(C20*B20) -> 25827.895 | F20: =$D$11-(H20*I20) -> 25686.41 | G20: 1X1 | H20: =POWER(SQRT($F$11)-I20,2) -> 274.56056 | I20: =J20/180 -> 0.25 | J20: 45 | L20: =L19+1 -> 17 | M20: ='[4]BANKNIFTY-I'!C36 -> 42817 | N20: ='[4]BANKNIFTY-I'!D36 -> 20870.15 | O20: ='[4]BANKNIFTY-I'!E36 -> 20990 | P20: ='[4]BANKNIFTY-I'!F36 -> 20822.5 | Q20: ='[4]BANKNIFTY-I'!G36 -> 20952.75 | R20: ='[4]BANKNIFTY-I'!H36 -> 58110 | S20: ='[5]NIFTY-I'!C36 -> 42817 | T20: ='[5]NIFTY-I'!D36 -> 9068.25 | U20: ='[5]NIFTY-I'!E36 -> 9121.4 | V20: ='[5]NIFTY-I'!F36 -> 9061.05 | W20: ='[5]NIFTY-I'!G36 -> 9107.65 | X20: ='[5]NIFTY-I'!H36 -> 97203 | Z20: =IF(OR(Q19=0,Q20=0),0,LN(Q20/Q19)) -> 0.0049591208 | AA20: =IF(OR(W19=0,W20=0),0,LN(W20/W19)) -> 0.0063057641 | AB20: 0 | AC20: 0 | AD20: =Z21 -> 0.0089278247 | AE20: - | AF20: =AA21 -> 0.0011686635 | AG20: - | AH20: =IF(OR(Q19=0,Q20=0),0,LN(Q20/Q19)) -> 0.0049591208 | AI20: =AJ19 -> 0.0054267974 | AJ20: =SQRT((0.94*(AI20^2))+(0.06*(AH20^2))) -> 0.0053998792 | AK20: =AJ20*SQRT(365) -> 0.10316455 | AL20: =IF(OR(W19=0,W20=0),0,LN(W20/W19)) -> 0.0063057641 | AM20: =AN19 -> 0.0048596248 | AN20: =SQRT((0.94*(AM20^2))+(0.06*(AL20^2))) -> 0.0049583017 | AO20: =AN20*SQRT(365) -> 0.094728221 | AP20: =IF(P20=0,0,LN(O20/P20)) -> 0.008012001 | AQ20: =AR19 -> 0.0084406477 | AR20: =SQRT((0.94*(AQ20^2))+(0.06*(AP20^2))) -> 0.0084155446 | AS20: =AR20*SQRT(365) -> 0.16077875 | AT20: =IF(V20=0,0,LN(U20/V20)) -> 0.0066382937 | AU20: =AV19 -> 0.0055191356 | AV20: =SQRT((0.94*(AU20^2))+(0.06*(AT20^2))) -> 0.0055926043 | AW20: =AV20*SQRT(365) -> 0.10684656 | AX20: =(N20*R20) -> 1.2127644e+09 | AY20: 0 | AZ20: =(T20*X20) -> 8.814611e+08 | BA20: 0 | BB20: =((AX20-BB19)*(2/(1+13)))+BB19 -> 1.2359048e+09 | BC20: =((R20-BC19)*(2/(1+13)))+BC19 -> 58962.506 | BD20: =BB20/BC20 -> 20960.86 | BE20: =(O20+P20+Q20)/3 -> 20921.75 | BF20: =(BE20*R20) -> 1.2157629e+09 | BG20: =((BF20-BG19)*(2/(1+5)))+BG19 -> 1.1871646e+09 | BH20: =((R20-BH19)*(2/(1+5)))+BH19 -> 56499.991 | BI20: =BG20/BH20 -> 21011.766 | BJ20: =((AZ20-BJ19)*(2/(1+13)))+BJ19 -> 9.7005591e+08 | BK20: =((X20-BK19)*(2/(1+13)))+BK19 -> 107082.15 | BL20: =BJ20/BK20 -> 9058.9882 | BM20: =(U20+V20+W20)/3 -> 9096.7 | BN20: =(BM20*X20) -> 8.8422653e+08 | BO20: =((BN20-BO19)*(2/(1+5)))+BO19 -> 9.8105966e+08 | BP20: =((X20-BP19)*(2/(1+5)))+BP19 -> 107751.48 | BQ20: =BO20/BP20 -> 9104.8369 | BR20: =(P20*R20) -> 1209995475 | BS20: =(O20*R20) -> 1219728900 | BT20: =AVERAGE(AX8:AX20)/AVERAGE(R8:R20) -> 21004.219 | BU20: =AVERAGE(BR16:BR20)/AVERAGE(R16:R20) -> 20984.685 | BV20: =AVERAGE(BS16:BS20)/AVERAGE(R16:R20) -> 21217.917 | BW20: 0 | BX20: =AVERAGE(BR8:BR20)/AVERAGE(R8:R20) -> 20882.855 | BY20: =AVERAGE(BS8:BS20)/AVERAGE(R8:R20) -> 21085.835 | BZ20: =(V20*X20) -> 8.8076124e+08 | CA20: =(U20*X20) -> 8.8662744e+08 | CB20: =AVERAGE(AZ8:AZ20)/AVERAGE(X8:X20) -> 9074.8508 | CC20: =AVERAGE(BZ16:BZ20)/AVERAGE(X16:X20) -> 9100.2114 | CD20: =AVERAGE(CA16:CA20)/AVERAGE(X16:X20) -> 9158.8783 | CE20: 0 | CF20: =AVERAGE(BZ8:BZ20)/AVERAGE(X8:X20) -> 9038.2226 | CG20: =AVERAGE(CA8:CA20)/AVERAGE(X8:X20) -> 9098.69 | CH20: =((BF20-CH19)*(2/(1+12)))+CH19 -> 1.223689e+09 | CI20: =((R20-CI19)*(2/(1+12)))+CI19 -> 58404.433 | CJ20: =CH20/CI20 -> 20951.989 | CK20: 0 | CL20: 0 | CM20: 0 | CN20: 0 | CO20: 0 | CP20: 0 | CQ20: =((BN20-CQ19)*(2/(1+12)))+CQ19 -> 9.7144239e+08 | CR20: =((X20-CR19)*(2/(1+12)))+CR19 -> 107168.36 | CS20: =CQ20/CR20 -> 9064.6381 | CV20: 0 | CW20: 0 | CX20: 0 | CY20: 0 | CZ20: =(BE20-BE19) -> 23.833333 | DA20: =IF(CZ20>=0,BF20,0) -> 1.2157629e+09 | DB20: =IF(CZ20<0,BF20,0) -> 0 | DC20: =((DA20-DC19)*(2/(1+14)))+DC19 -> 7.2168318e+08 | DD20: =((DB20-DD19)*(2/(1+14)))+DD19 -> 5.6671083e+08 | DE20: =IF(DD20=0,100000,(DC20/DD20)) -> 1.2734593 | DF20: =100-(100/(1+DE20)) -> 56.014168 | DG20: 0 | DH20: 0 | DI20: =(BM20-BM19) -> 21.566667 | DJ20: =IF(DI20>=0,BN20,0) -> 8.8422653e+08 | DK20: =IF(DI20<0,BN20,0) -> 0 | DL20: =((DJ20-DL19)*(2/(1+14)))+DL19 -> 5.7776974e+08 | DM20: =((DK20-DM19)*(2/(1+14)))+DM19 -> 4.1493908e+08 | DN20: =IF(DM20=0,100000,(DL20/DM20)) -> 1.3924207 | DO20: =100-(100/(1+DN20)) -> 58.201331 | DP20: 0 | DQ20: 0 | DR20: =MAX(O20-P20,ABS(O20-Q19),ABS(Q19-P20)) -> 167.5 | DS20: =(DR20*R20) -> 9733425 | DT20: 0 | DU20: 0 | DV20: 0 | DW20: 0 | DX20: 0 | DY20: 0 | DZ20: 0 | EA20: =MAX(U20-V20,ABS(U20-W19),ABS(W19-V20)) -> 71 | EB20: =(EA20*X20) -> 6901413 | EC20: 0 | ED20: 0 | EE20: 0 | EF20: 0 | EG20: 0 | EH20: 0 | EI20: 0 | EJ20: =MAX(O20-P20,ABS(O20-Q19),ABS(Q19-P20)) -> 167.5 | EK20: =(EJ20*R20) -> 9733425 | EL20: =((EK20-EL19)*(2/(1+8)))+EL19 -> 13415254 | EM20: =((R20-EM19)*(2/(1+8)))+EM19 -> 57280.676 | EN20: =EL20/EM20 -> 234.20208 | EO20: =EN20*$F$4 -> 4684.0417 | EP20: =EO20*'Base Data'!$D$13 -> 3513.0313 | EQ20: =IF(INT(('Base Data'!$D$7)/EP20)=0,0,INT(('Base Data'!$D$7)/EP20)) -> 2 | ER20: =(EN20/Q20) -> 0.01117763 | ES20: =MAX(U20-V20,ABS(U20-W19),ABS(W19-V20)) -> 71 | ET20: =(ES20*X20) -> 6901413 | EU20: =((ET20-EU19)*(2/(1+8)))+EU19 -> 8496803.7 | EV20: =((X20-EV19)*(2/(1+8)))+EV19 -> 107802.1 | EW20: =EU20/EV20 -> 78.818534 | EX20: =EW20*$G$4 -> 5911.39 | EY20: =EX20*'Base Data'!$D$13 -> 4433.5425 | EZ20: =IF(INT(('Base Data'!$D$7)/EY20)=0,0,INT(('Base Data'!$D$7)/EY20)) -> 2 | FA20: =(EW20/W20) -> 0.0086541022 | FB20: 0 | FC20: =(Q20-AVERAGE(BE12:BE19))/EN20 -> -0.77767597 | FD20: 0 | FE20: =(W20-AVERAGE(BM12:BM19))/EW20 -> -0.078027333 | FF20: =(O20-P20) -> 167.5 | FG20: =FF20/N20 -> 0.0080258168 | FH20: =AVERAGE(FG13:FG20) -> 0.0094435288 | FI20: =AVERAGE(FG8:FG20) -> 0.0093200857 | FJ20: - | FK20: =(U20-V20) -> 60.35 | FL20: =FK20/T20 -> 0.0066550878 | FM20: =AVERAGE(FL13:FL20) -> 0.0056415629 | FN20: =AVERAGE(FL8:FL20) -> 0.0061287072 | FO20: - | FP20: =IF(Q19<((O18+P18+Q18)/3),1,IF(Q19>((O18+P18+Q18)/3),2,0)) -> 1 | FQ20: =IF(W19<((U18+V18+W18)/3),1,IF(W19>((U18+V18+W18)/3),2,0)) -> 1 | FR20: 0 | FS20: - | FT20: 0 | FU20: - | FV20: =ABS(Q20-Q13)/(MAX(O13:O20)-MIN(P13:P20))*100 -> 22.65771 | FW20: =IF(AND(FV20<30,FV20>FV19),"C-R",IF(AND(FV20<30,FV20=FV19),"C-F",IF(AND(FV20<30,FV20<FV19),"C-D",IF(AND(FV20>=30,FV20>FV19),"T-R",IF(AND(FV20>=30,FV20=FV19),"T-F",IF(AND(FV20>=30,FV20<FV19),"T-D","Check")))))) -> C-R | FX20: =ABS(W20-W13)/(MAX(U13:U20)-MIN(V13:V20))*100 -> 2.7703307 | FY20: =IF(AND(FX20<30,FX20>FX19),"C-R",IF(AND(FX20<30,FX20=FX19),"C-F",IF(AND(FX20<30,FX20<FX19),"C-D",IF(AND(FX20>=30,FX20>FX19),"T-R",IF(AND(FX20>=30,FX20=FX19),"T-F",IF(AND(FX20>=30,FX20<FX19),"T-D","Check")))))) -> C-D
A21: =90-A19 -> 26.25 | B21: =A21/180 -> 0.14583333 | C21: =POWER(SQRT($F$11)+B21,2) -> 287.83506 | D21: 1X2 | E21: =$D$11+(C21*B21) -> 25797.026 | F21: =$D$11-(H21*I21) -> 25714.505 | G21: 2X1 | H21: =POWER(SQRT($F$11)-I21,2) -> 278.02347 | I21: =J21/180 -> 0.14583333 | J21: =90-J19 -> 26.25 | L21: =L20+1 -> 18 | M21: ='[4]BANKNIFTY-I'!C37 -> 42818 | N21: ='[4]BANKNIFTY-I'!D37 -> 20989.75 | O21: ='[4]BANKNIFTY-I'!E37 -> 21206.6 | P21: ='[4]BANKNIFTY-I'!F37 -> 20962.95 | Q21: ='[4]BANKNIFTY-I'!G37 -> 21140.65 | R21: ='[4]BANKNIFTY-I'!H37 -> 68906 | S21: ='[5]NIFTY-I'!C37 -> 42818 | T21: ='[5]NIFTY-I'!D37 -> 9117.85 | U21: ='[5]NIFTY-I'!E37 -> 9146.6 | V21: ='[5]NIFTY-I'!F37 -> 9099.5 | W21: ='[5]NIFTY-I'!G37 -> 9118.3 | X21: ='[5]NIFTY-I'!H37 -> 93896 | Z21: =IF(OR(Q20=0,Q21=0),0,LN(Q21/Q20)) -> 0.0089278247 | AA21: =IF(OR(W20=0,W21=0),0,LN(W21/W20)) -> 0.0011686635 | AB21: 0 | AC21: 0 | AD21: =Z22 -> -0.0018322741 | AE21: - | AF21: =AA22 -> -0.0055371645 | AG21: - | AH21: =IF(OR(Q20=0,Q21=0),0,LN(Q21/Q20)) -> 0.0089278247 | AI21: =AJ20 -> 0.0053998792 | AJ21: =SQRT((0.94*(AI21^2))+(0.06*(AH21^2))) -> 0.0056737586 | AK21: =AJ21*SQRT(365) -> 0.10839701 | AL21: =IF(OR(W20=0,W21=0),0,LN(W21/W20)) -> 0.0011686635 | AM21: =AN20 -> 0.0049583017 | AN21: =SQRT((0.94*(AM21^2))+(0.06*(AL21^2))) -> 0.0048157675 | AO21: =AN21*SQRT(365) -> 0.092005109 | AP21: =IF(P21=0,0,LN(O21/P21)) -> 0.01155586 | AQ21: =AR20 -> 0.0084155446 | AR21: =SQRT((0.94*(AQ21^2))+(0.06*(AP21^2))) -> 0.0086362249 | AS21: =AR21*SQRT(365) -> 0.16499485 | AT21: =IF(V21=0,0,LN(U21/V21)) -> 0.0051627586 | AU21: =AV20 -> 0.0055926043 | AV21: =SQRT((0.94*(AU21^2))+(0.06*(AT21^2))) -> 0.0055677495 | AW21: =AV21*SQRT(365) -> 0.1063717 | AX21: =(N21*R21) -> 1.4463197e+09 | AY21: 0 | AZ21: =(T21*X21) -> 8.5612964e+08 | BA21: 0 | BB21: =((AX21-BB20)*(2/(1+13)))+BB20 -> 1.2659641e+09 | BC21: =((R21-BC20)*(2/(1+13)))+BC20 -> 60383.005 | BD21: =BB21/BC21 -> 20965.57 | BE21: =(O21+P21+Q21)/3 -> 21103.4 | BF21: =(BE21*R21) -> 1.4541509e+09 | BG21: =((BF21-BG20)*(2/(1+5)))+BG20 -> 1.27616e+09 | BH21: =((R21-BH20)*(2/(1+5)))+BH20 -> 60635.327 | BI21: =BG21/BH21 -> 21046.477 | BJ21: =((AZ21-BJ20)*(2/(1+13)))+BJ20 -> 9.5378073e+08 | BK21: =((X21-BK20)*(2/(1+13)))+BK20 -> 105198.41 | BL21: =BJ21/BK21 -> 9066.4936 | BM21: =(U21+V21+W21)/3 -> 9121.4667 | BN21: =(BM21*X21) -> 8.5646923e+08 | BO21: =((BN21-BO20)*(2/(1+5)))+BO20 -> 9.3952952e+08 | BP21: =((X21-BP20)*(2/(1+5)))+BP20 -> 103132.99 | BQ21: =BO21/BP21 -> 9109.8837 | BR21: =(P21*R21) -> 1.444473e+09 | BS21: =(O21*R21) -> 1.461262e+09 | BT21: =AVERAGE(AX9:AX21)/AVERAGE(R9:R21) -> 21031.963 | BU21: =AVERAGE(BR17:BR21)/AVERAGE(R17:R21) -> 20937.916 | BV21: =AVERAGE(BS17:BS21)/AVERAGE(R17:R21) -> 21122.747 | BW21: 0 | BX21: =AVERAGE(BR9:BR21)/AVERAGE(R9:R21) -> 20910.845 | BY21: =AVERAGE(BS9:BS21)/AVERAGE(R9:R21) -> 21118.17 | BZ21: =(V21*X21) -> 854406652 | CA21: =(U21*X21) -> 8.5882915e+08 | CB21: =AVERAGE(AZ9:AZ21)/AVERAGE(X9:X21) -> 9087.2656 | CC21: =AVERAGE(BZ17:BZ21)/AVERAGE(X17:X21) -> 9085.8172 | CD21: =AVERAGE(CA17:CA21)/AVERAGE(X17:X21) -> 9144.779 | CE21: 0 | CF21: =AVERAGE(BZ9:BZ21)/AVERAGE(X9:X21) -> 9049.8575 | CG21: =AVERAGE(CA9:CA21)/AVERAGE(X9:X21) -> 9109.672 | CH21: =((BF21-CH20)*(2/(1+12)))+CH20 -> 1.2591447e+09 | CI21: =((R21-CI20)*(2/(1+12)))+CI20 -> 60020.058 | CJ21: =CH21/CI21 -> 20978.732 | CK21: 0 | CL21: 0 | CM21: 0 | CN21: 0 | CO21: 0 | CP21: 0 | CQ21: =((BN21-CQ20)*(2/(1+12)))+CQ20 -> 9.5375421e+08 | CR21: =((X21-CR20)*(2/(1+12)))+CR20 -> 105126.46 | CS21: =CQ21/CR21 -> 9072.447 | CV21: 0 | CW21: 0 | CX21: 0 | CY21: 0 | CZ21: =(BE21-BE20) -> 181.65 | DA21: =IF(CZ21>=0,BF21,0) -> 1.4541509e+09 | DB21: =IF(CZ21<0,BF21,0) -> 0 | DC21: =((DA21-DC20)*(2/(1+14)))+DC20 -> 8.1934554e+08 | DD21: =((DB21-DD20)*(2/(1+14)))+DD20 -> 4.9114938e+08 | DE21: =IF(DD21=0,100000,(DC21/DD21)) -> 1.6682206 | DF21: =100-(100/(1+DE21)) -> 62.52184 | DG21: 0 | DH21: 0 | DI21: =(BM21-BM20) -> 24.766667 | DJ21: =IF(DI21>=0,BN21,0) -> 8.5646923e+08 | DK21: =IF(DI21<0,BN21,0) -> 0 | DL21: =((DJ21-DL20)*(2/(1+14)))+DL20 -> 6.1492967e+08 | DM21: =((DK21-DM20)*(2/(1+14)))+DM20 -> 3.5961387e+08 | DN21: =IF(DM21=0,100000,(DL21/DM21)) -> 1.7099721 | DO21: =100-(100/(1+DN21)) -> 63.099251 | DP21: 0 | DQ21: 0 | DR21: =MAX(O21-P21,ABS(O21-Q20),ABS(Q20-P21)) -> 253.85 | DS21: =(DR21*R21) -> 17491788 | DT21: 0 | DU21: 0 | DV21: 0 | DW21: 0 | DX21: 0 | DY21: 0 | DZ21: 0 | EA21: =MAX(U21-V21,ABS(U21-W20),ABS(W20-V21)) -> 47.1 | EB21: =(EA21*X21) -> 4422501.6 | EC21: 0 | ED21: 0 | EE21: 0 | EF21: 0 | EG21: 0 | EH21: 0 | EI21: 0 | EJ21: =MAX(O21-P21,ABS(O21-Q20),ABS(Q20-P21)) -> 253.85 | EK21: =(EJ21*R21) -> 17491788 | EL21: =((EK21-EL20)*(2/(1+8)))+EL20 -> 14321150 | EM21: =((R21-EM20)*(2/(1+8)))+EM20 -> 59864.081 | EN21: =EL21/EM21 -> 239.22776 | EO21: =EN21*$F$4 -> 4784.5553 | EP21: =EO21*'Base Data'!$D$13 -> 3588.4164 | EQ21: =IF(INT(('Base Data'!$D$7)/EP21)=0,0,INT(('Base Data'!$D$7)/EP21)) -> 2 | ER21: =(EN21/Q21) -> 0.011316008 | ES21: =MAX(U21-V21,ABS(U21-W20),ABS(W20-V21)) -> 47.1 | ET21: =(ES21*X21) -> 4422501.6 | EU21: =((ET21-EU20)*(2/(1+8)))+EU20 -> 7591403.2 | EV21: =((X21-EV20)*(2/(1+8)))+EV20 -> 104711.86 | EW21: =EU21/EV21 -> 72.498028 | EX21: =EW21*$G$4 -> 5437.3521 | EY21: =EX21*'Base Data'!$D$13 -> 4078.0141 | EZ21: =IF(INT(('Base Data'!$D$7)/EY21)=0,0,INT(('Base Data'!$D$7)/EY21)) -> 2 | FA21: =(EW21/W21) -> 0.0079508273 | FB21: 0 | FC21: =(Q21-AVERAGE(BE13:BE20))/EN21 -> -0.033501895 | FD21: 0 | FE21: =(W21-AVERAGE(BM13:BM20))/EW21 -> -0.17477487 | FF21: =(O21-P21) -> 243.65 | FG21: =FF21/N21 -> 0.011608047 | FH21: =AVERAGE(FG14:FG21) -> 0.0095631076 | FI21: =AVERAGE(FG9:FG21) -> 0.0094924792 | FJ21: - | FK21: =(U21-V21) -> 47.1 | FL21: =FK21/T21 -> 0.0051656915 | FM21: =AVERAGE(FL14:FL21) -> 0.0051883132 | FN21: =AVERAGE(FL9:FL21) -> 0.0060392186 | FO21: - | FP21: =IF(Q20<((O19+P19+Q19)/3),1,IF(Q20>((O19+P19+Q19)/3),2,0)) -> 2 | FQ21: =IF(W20<((U19+V19+W19)/3),1,IF(W20>((U19+V19+W19)/3),2,0)) -> 2 | FR21: 0 | FS21: - | FT21: 0 | FU21: - | FV21: =ABS(Q21-Q14)/(MAX(O14:O21)-MIN(P14:P21))*100 -> 9.5735981 | FW21: =IF(AND(FV21<30,FV21>FV20),"C-R",IF(AND(FV21<30,FV21=FV20),"C-F",IF(AND(FV21<30,FV21<FV20),"C-D",IF(AND(FV21>=30,FV21>FV20),"T-R",IF(AND(FV21>=30,FV21=FV20),"T-F",IF(AND(FV21>=30,FV21<FV20),"T-D","Check")))))) -> C-D | FX21: =ABS(W21-W14)/(MAX(U14:U21)-MIN(V14:V21))*100 -> 5.3619303 | FY21: =IF(AND(FX21<30,FX21>FX20),"C-R",IF(AND(FX21<30,FX21=FX20),"C-F",IF(AND(FX21<30,FX21<FX20),"C-D",IF(AND(FX21>=30,FX21>FX20),"T-R",IF(AND(FX21>=30,FX21=FX20),"T-F",IF(AND(FX21>=30,FX21<FX20),"T-D","Check")))))) -> C-R
A22: =90-A18 -> 18.75 | B22: =A22/180 -> 0.10416667 | C22: =POWER(SQRT($F$11)+B22,2) -> 286.42299 | D22: 1X3 | E22: =$D$11+(C22*B22) -> 25784.886 | F22: =$D$11-(H22*I22) -> 25725.944 | G22: 3X1 | H22: =POWER(SQRT($F$11)-I22,2) -> 279.41471 | I22: =J22/180 -> 0.10416667 | J22: =90-J18 -> 18.75 | L22: =L21+1 -> 19 | M22: ='[4]BANKNIFTY-I'!C38 -> 42821 | N22: ='[4]BANKNIFTY-I'!D38 -> 21001.5 | O22: ='[4]BANKNIFTY-I'!E38 -> 21175 | P22: ='[4]BANKNIFTY-I'!F38 -> 20992.25 | Q22: ='[4]BANKNIFTY-I'!G38 -> 21101.95 | R22: ='[4]BANKNIFTY-I'!H38 -> 61884 | S22: ='[5]NIFTY-I'!C38 -> 42821 | T22: ='[5]NIFTY-I'!D38 -> 9109 | U22: ='[5]NIFTY-I'!E38 -> 9111.05 | V22: ='[5]NIFTY-I'!F38 -> 9035.25 | W22: ='[5]NIFTY-I'!G38 -> 9067.95 | X22: ='[5]NIFTY-I'!H38 -> 171644 | Z22: =IF(OR(Q21=0,Q22=0),0,LN(Q22/Q21)) -> -0.0018322741 | AA22: =IF(OR(W21=0,W22=0),0,LN(W22/W21)) -> -0.0055371645 | AB22: 0 | AC22: 0 | AD22: =Z23 -> 0.0062900197 | AE22: - | AF22: =AA23 -> 0.0045825838 | AG22: - | AH22: =IF(OR(Q21=0,Q22=0),0,LN(Q22/Q21)) -> -0.0018322741 | AI22: =AJ21 -> 0.0056737586 | AJ22: =SQRT((0.94*(AI22^2))+(0.06*(AH22^2))) -> 0.0055191918 | AK22: =AJ22*SQRT(365) -> 0.10544401 | AL22: =IF(OR(W21=0,W22=0),0,LN(W22/W21)) -> -0.0055371645 | AM22: =AN21 -> 0.0048157675 | AN22: =SQRT((0.94*(AM22^2))+(0.06*(AL22^2))) -> 0.0048620707 | AO22: =AN22*SQRT(365) -> 0.09288973 | AP22: =IF(P22=0,0,LN(O22/P22)) -> 0.0086679185 | AQ22: =AR21 -> 0.0086362249 | AR22: =SQRT((0.94*(AQ22^2))+(0.06*(AP22^2))) -> 0.0086381298 | AS22: =AR22*SQRT(365) -> 0.16503124 | AT22: =IF(V22=0,0,LN(U22/V22)) -> 0.0083543688 | AU22: =AV21 -> 0.0055677495 | AV22: =SQRT((0.94*(AU22^2))+(0.06*(AT22^2))) -> 0.0057730038 | AW22: =AV22*SQRT(365) -> 0.11029308 | AX22: =(N22*R22) -> 1299656826 | AY22: 0 | AZ22: =(T22*X22) -> 1563505196 | BA22: 0 | BB22: =((AX22-BB21)*(2/(1+13)))+BB21 -> 1.2707773e+09 | BC22: =((R22-BC21)*(2/(1+13)))+BC21 -> 60597.433 | BD22: =BB22/BC22 -> 20970.812 | BE22: =(O22+P22+Q22)/3 -> 21089.733 | BF22: =(BE22*R22) -> 1.3051171e+09 | BG22: =((BF22-BG21)*(2/(1+5)))+BG21 -> 1.2858124e+09 | BH22: =((R22-BH21)*(2/(1+5)))+BH21 -> 61051.551 | BI22: =BG22/BH22 -> 21061.092 | BJ22: =((AZ22-BJ21)*(2/(1+13)))+BJ21 -> 1.0408842e+09 | BK22: =((X22-BK21)*(2/(1+13)))+BK21 -> 114690.64 | BL22: =BJ22/BK22 -> 9075.5814 | BM22: =(U22+V22+W22)/3 -> 9071.4167 | BN22: =(BM22*X22) -> 1.5570542e+09 | BO22: =((BN22-BO21)*(2/(1+5)))+BO21 -> 1.1453711e+09 | BP22: =((X22-BP21)*(2/(1+5)))+BP21 -> 125969.99 | BQ22: =BO22/BP22 -> 9092.4122 | BR22: =(P22*R22) -> 1299084399 | BS22: =(O22*R22) -> 1310393700 | BT22: =AVERAGE(AX10:AX22)/AVERAGE(R10:R22) -> 21043.757 | BU22: =AVERAGE(BR18:BR22)/AVERAGE(R18:R22) -> 20927.653 | BV22: =AVERAGE(BS18:BS22)/AVERAGE(R18:R22) -> 21121.403 | BW22: 0 | BX22: =AVERAGE(BR10:BR22)/AVERAGE(R10:R22) -> 20929.068 | BY22: =AVERAGE(BS10:BS22)/AVERAGE(R10:R22) -> 21139.261 | BZ22: =(V22*X22) -> 1550846451 | CA22: =(U22*X22) -> 1.5638571e+09 | CB22: =AVERAGE(AZ10:AZ22)/AVERAGE(X10:X22) -> 9093.7899 | CC22: =AVERAGE(BZ18:BZ22)/AVERAGE(X18:X22) -> 9064.6601 | CD22: =AVERAGE(CA18:CA22)/AVERAGE(X18:X22) -> 9132.7675 | CE22: 0 | CF22: =AVERAGE(BZ10:BZ22)/AVERAGE(X10:X22) -> 9051.7459 | CG22: =AVERAGE(CA10:CA22)/AVERAGE(X10:X22) -> 9114.6495 | CH22: =((BF22-CH21)*(2/(1+12)))+CH21 -> 1.2662174e+09 | CI22: =((R22-CI21)*(2/(1+12)))+CI21 -> 60306.819 | CJ22: =CH22/CI22 -> 20996.255 | CK22: 0 | CL22: 0 | CM22: 0 | CN22: 0 | CO22: 0 | CP22: 0 | CQ22: =((BN22-CQ21)*(2/(1+12)))+CQ21 -> 1.0465696e+09 | CR22: =((X22-CR21)*(2/(1+12)))+CR21 -> 115359.93 | CS22: =CQ22/CR22 -> 9072.2112 | CV22: 0 | CW22: 0 | CX22: 0 | CY22: 0 | CZ22: =(BE22-BE21) -> -13.666667 | DA22: =IF(CZ22>=0,BF22,0) -> 0 | DB22: =IF(CZ22<0,BF22,0) -> 1.3051171e+09 | DC22: =((DA22-DC21)*(2/(1+14)))+DC21 -> 7.1009947e+08 | DD22: =((DB22-DD21)*(2/(1+14)))+DD21 -> 5.9967841e+08 | DE22: =IF(DD22=0,100000,(DC22/DD22)) -> 1.1841338 | DF22: =100-(100/(1+DE22)) -> 54.215259 | DG22: 0 | DH22: 0 | DI22: =(BM22-BM21) -> -50.05 | DJ22: =IF(DI22>=0,BN22,0) -> 0 | DK22: =IF(DI22<0,BN22,0) -> 1.5570542e+09 | DL22: =((DJ22-DL21)*(2/(1+14)))+DL21 -> 5.3293905e+08 | DM22: =((DK22-DM21)*(2/(1+14)))+DM21 -> 5.1927258e+08 | DN22: =IF(DM22=0,100000,(DL22/DM22)) -> 1.0263185 | DO22: =100-(100/(1+DN22)) -> 50.649416 | DP22: 0 | DQ22: 0 | DR22: =MAX(O22-P22,ABS(O22-Q21),ABS(Q21-P22)) -> 182.75 | DS22: =(DR22*R22) -> 11309301 | DT22: 0 | DU22: 0 | DV22: 0 | DW22: 0 | DX22: 0 | DY22: 0 | DZ22: 0 | EA22: =MAX(U22-V22,ABS(U22-W21),ABS(W21-V22)) -> 83.05 | EB22: =(EA22*X22) -> 14255034 | EC22: 0 | ED22: 0 | EE22: 0 | EF22: 0 | EG22: 0 | EH22: 0 | EI22: 0 | EJ22: =MAX(O22-P22,ABS(O22-Q21),ABS(Q21-P22)) -> 182.75 | EK22: =(EJ22*R22) -> 11309301 | EL22: =((EK22-EL21)*(2/(1+8)))+EL21 -> 13651850 | EM22: =((R22-EM21)*(2/(1+8)))+EM21 -> 60312.952 | EN22: =EL22/EM22 -> 226.35023 | EO22: =EN22*$F$4 -> 4527.0045 | EP22: =EO22*'Base Data'!$D$13 -> 3395.2534 | EQ22: =IF(INT(('Base Data'!$D$7)/EP22)=0,0,INT(('Base Data'!$D$7)/EP22)) -> 3 | ER22: =(EN22/Q22) -> 0.010726508 | ES22: =MAX(U22-V22,ABS(U22-W21),ABS(W21-V22)) -> 83.05 | ET22: =(ES22*X22) -> 14255034 | EU22: =((ET22-EU21)*(2/(1+8)))+EU21 -> 9072210.1 | EV22: =((X22-EV21)*(2/(1+8)))+EV21 -> 119585.67 | EW22: =EU22/EV22 -> 75.863691 | EX22: =EW22*$G$4 -> 5689.7768 | EY22: =EX22*'Base Data'!$D$13 -> 4267.3326 | EZ22: =IF(INT(('Base Data'!$D$7)/EY22)=0,0,INT(('Base Data'!$D$7)/EY22)) -> 2 | FA22: =(EW22/W22) -> 0.0083661347 | FB22: 0 | FC22: =(Q22-AVERAGE(BE14:BE21))/EN22 -> -0.15800551 | FD22: 0 | FE22: =(W22-AVERAGE(BM14:BM21))/EW22 -> -0.84488156 | FF22: =(O22-P22) -> 182.75 | FG22: =FF22/N22 -> 0.0087017594 | FH22: =AVERAGE(FG15:FG22) -> 0.0096559758 | FI22: =AVERAGE(FG10:FG22) -> 0.0097635982 | FJ22: - | FK22: =(U22-V22) -> 75.8 | FL22: =FK22/T22 -> 0.0083214403 | FM22: =AVERAGE(FL15:FL22) -> 0.0058377054 | FN22: =AVERAGE(FL10:FL22) -> 0.0064323888 | FO22: - | FP22: =IF(Q21<((O20+P20+Q20)/3),1,IF(Q21>((O20+P20+Q20)/3),2,0)) -> 2 | FQ22: =IF(W21<((U20+V20+W20)/3),1,IF(W21>((U20+V20+W20)/3),2,0)) -> 2 | FR22: 0 | FS22: - | FT22: 0 | FU22: - | FV22: =ABS(Q22-Q15)/(MAX(O15:O22)-MIN(P15:P22))*100 -> 24.398364 | FW22: =IF(AND(FV22<30,FV22>FV21),"C-R",IF(AND(FV22<30,FV22=FV21),"C-F",IF(AND(FV22<30,FV22<FV21),"C-D",IF(AND(FV22>=30,FV22>FV21),"T-R",IF(AND(FV22>=30,FV22=FV21),"T-F",IF(AND(FV22>=30,FV22<FV21),"T-D","Check")))))) -> C-R | FX22: =ABS(W22-W15)/(MAX(U15:U22)-MIN(V15:V22))*100 -> 60.923423 | FY22: =IF(AND(FX22<30,FX22>FX21),"C-R",IF(AND(FX22<30,FX22=FX21),"C-F",IF(AND(FX22<30,FX22<FX21),"C-D",IF(AND(FX22>=30,FX22>FX21),"T-R",IF(AND(FX22>=30,FX22=FX21),"T-F",IF(AND(FX22>=30,FX22<FX21),"T-D","Check")))))) -> T-R
A23: =90-A17 -> 15 | B23: =A23/180 -> 0.083333333 | C23: =POWER(SQRT($F$11)+B23,2) -> 285.71825 | D23: 1X4 | E23: =$D$11+(C23*B23) -> 25778.86 | F23: =$D$11-(H23*I23) -> 25731.707 | G23: 4X1 | H23: =POWER(SQRT($F$11)-I23,2) -> 280.11163 | I23: =J23/180 -> 0.083333333 | J23: =90-J17 -> 15 | L23: =L22+1 -> 20 | M23: ='[4]BANKNIFTY-I'!C39 -> 42822 | N23: ='[4]BANKNIFTY-I'!D39 -> 21225.25 | O23: ='[4]BANKNIFTY-I'!E39 -> 21265 | P23: ='[4]BANKNIFTY-I'!F39 -> 21150 | Q23: ='[4]BANKNIFTY-I'!G39 -> 21235.1 | R23: ='[4]BANKNIFTY-I'!H39 -> 62454 | S23: ='[5]NIFTY-I'!C39 -> 42822 | T23: ='[5]NIFTY-I'!D39 -> 9095.15 | U23: ='[5]NIFTY-I'!E39 -> 9123.8 | V23: ='[5]NIFTY-I'!F39 -> 9085.4 | W23: ='[5]NIFTY-I'!G39 -> 9109.6 | X23: ='[5]NIFTY-I'!H39 -> 136796 | Z23: =IF(OR(Q22=0,Q23=0),0,LN(Q23/Q22)) -> 0.0062900197 | AA23: =IF(OR(W22=0,W23=0),0,LN(W23/W22)) -> 0.0045825838 | AB23: 0 | AC23: 0 | AD23: =Z24 -> 0.0078896428 | AE23: - | AF23: =AA24 -> 0.0036433505 | AG23: - | AH23: =IF(OR(Q22=0,Q23=0),0,LN(Q23/Q22)) -> 0.0062900197 | AI23: =AJ22 -> 0.0055191918 | AJ23: =SQRT((0.94*(AI23^2))+(0.06*(AH23^2))) -> 0.0055684513 | AK23: =AJ23*SQRT(365) -> 0.10638511 | AL23: =IF(OR(W22=0,W23=0),0,LN(W23/W22)) -> 0.0045825838 | AM23: =AN22 -> 0.0048620707 | AN23: =SQRT((0.94*(AM23^2))+(0.06*(AL23^2))) -> 0.0048457561 | AO23: =AN23*SQRT(365) -> 0.09257804 | AP23: =IF(P23=0,0,LN(O23/P23)) -> 0.0054226232 | AQ23: =AR22 -> 0.0086381298 | AR23: =SQRT((0.94*(AQ23^2))+(0.06*(AP23^2))) -> 0.0084796545 | AS23: =AR23*SQRT(365) -> 0.16200357 | AT23: =IF(V23=0,0,LN(U23/V23)) -> 0.0042176545 | AU23: =AV22 -> 0.0057730038 | AV23: =SQRT((0.94*(AU23^2))+(0.06*(AT23^2))) -> 0.0056916812 | AW23: =AV23*SQRT(365) -> 0.10873942 | AX23: =(N23*R23) -> 1.3256018e+09 | AY23: 0 | AZ23: =(T23*X23) -> 1.2441801e+09 | BA23: 0 | BB23: =((AX23-BB22)*(2/(1+13)))+BB22 -> 1.2786094e+09 | BC23: =((R23-BC22)*(2/(1+13)))+BC22 -> 60862.657 | BD23: =BB23/BC23 -> 21008.11 | BE23: =(O23+P23+Q23)/3 -> 21216.7 | BF23: =(BE23*R23) -> 1.3250678e+09 | BG23: =((BF23-BG22)*(2/(1+5)))+BG22 -> 1.2988975e+09 | BH23: =((R23-BH22)*(2/(1+5)))+BH22 -> 61519.034 | BI23: =BG23/BH23 -> 21113.75 | BJ23: =((AZ23-BJ22)*(2/(1+13)))+BJ22 -> 1.0699265e+09 | BK23: =((X23-BK22)*(2/(1+13)))+BK22 -> 117848.55 | BL23: =BJ23/BK23 -> 9078.8263 | BM23: =(U23+V23+W23)/3 -> 9106.2667 | BN23: =(BM23*X23) -> 1.2457009e+09 | BO23: =((BN23-BO22)*(2/(1+5)))+BO22 -> 1.1788143e+09 | BP23: =((X23-BP22)*(2/(1+5)))+BP22 -> 129578.66 | BQ23: =BO23/BP23 -> 9097.2876 | BR23: =(P23*R23) -> 1320902100 | BS23: =(O23*R23) -> 1328084310 | BT23: =AVERAGE(AX11:AX23)/AVERAGE(R11:R23) -> 21097.134 | BU23: =AVERAGE(BR19:BR23)/AVERAGE(R19:R23) -> 20952.737 | BV23: =AVERAGE(BS19:BS23)/AVERAGE(R19:R23) -> 21134.02 | BW23: 0 | BX23: =AVERAGE(BR11:BR23)/AVERAGE(R11:R23) -> 20985.286 | BY23: =AVERAGE(BS11:BS23)/AVERAGE(R11:R23) -> 21189.03 | BZ23: =(V23*X23) -> 1.2428464e+09 | CA23: =(U23*X23) -> 1.2480993e+09 | CB23: =AVERAGE(AZ11:AZ23)/AVERAGE(X11:X23) -> 9103.4117 | CC23: =AVERAGE(BZ19:BZ23)/AVERAGE(X19:X23) -> 9061.4099 | CD23: =AVERAGE(CA19:CA23)/AVERAGE(X19:X23) -> 9124.7359 | CE23: 0 | CF23: =AVERAGE(BZ11:BZ23)/AVERAGE(X11:X23) -> 9066.2438 | CG23: =AVERAGE(CA11:CA23)/AVERAGE(X11:X23) -> 9126.1609 | CH23: =((BF23-CH22)*(2/(1+12)))+CH22 -> 1.2752713e+09 | CI23: =((R23-CI22)*(2/(1+12)))+CI22 -> 60637.154 | CJ23: =CH23/CI23 -> 21031.186 | CK23: 0 | CL23: 0 | CM23: 0 | CN23: 0 | CO23: 0 | CP23: 0 | CQ23: =((BN23-CQ22)*(2/(1+12)))+CQ22 -> 1.0772052e+09 | CR23: =((X23-CR22)*(2/(1+12)))+CR22 -> 118657.78 | CS23: =CQ23/CR23 -> 9078.2514 | CV23: 0 | CW23: 0 | CX23: 0 | CY23: 0 | CZ23: =(BE23-BE22) -> 126.96667 | DA23: =IF(CZ23>=0,BF23,0) -> 1.3250678e+09 | DB23: =IF(CZ23<0,BF23,0) -> 0 | DC23: =((DA23-DC22)*(2/(1+14)))+DC22 -> 7.9209524e+08 | DD23: =((DB23-DD22)*(2/(1+14)))+DD22 -> 5.1972128e+08 | DE23: =IF(DD23=0,100000,(DC23/DD23)) -> 1.524077 | DF23: =100-(100/(1+DE23)) -> 60.381557 | DG23: 0 | DH23: 0 | DI23: =(BM23-BM22) -> 34.85 | DJ23: =IF(DI23>=0,BN23,0) -> 1.2457009e+09 | DK23: =IF(DI23<0,BN23,0) -> 0 | DL23: =((DJ23-DL22)*(2/(1+14)))+DL22 -> 6.2797396e+08 | DM23: =((DK23-DM22)*(2/(1+14)))+DM22 -> 4.5003624e+08 | DN23: =IF(DM23=0,100000,(DL23/DM23)) -> 1.3953853 | DO23: =100-(100/(1+DN23)) -> 58.253063 | DP23: 0 | DQ23: 0 | DR23: =MAX(O23-P23,ABS(O23-Q22),ABS(Q22-P23)) -> 163.05 | DS23: =(DR23*R23) -> 10183125 | DT23: 0 | DU23: 0 | DV23: 0 | DW23: 0 | DX23: 0 | DY23: 0 | DZ23: 0 | EA23: =MAX(U23-V23,ABS(U23-W22),ABS(W22-V23)) -> 55.85 | EB23: =(EA23*X23) -> 7640056.6 | EC23: 0 | ED23: 0 | EE23: 0 | EF23: 0 | EG23: 0 | EH23: 0 | EI23: 0 | EJ23: =MAX(O23-P23,ABS(O23-Q22),ABS(Q22-P23)) -> 163.05 | EK23: =(EJ23*R23) -> 10183125 | EL23: =((EK23-EL22)*(2/(1+8)))+EL22 -> 12881022 | EM23: =((R23-EM22)*(2/(1+8)))+EM22 -> 60788.741 | EN23: =EL23/EM23 -> 211.89816 | EO23: =EN23*$F$4 -> 4237.9633 | EP23: =EO23*'Base Data'!$D$13 -> 3178.4724 | EQ23: =IF(INT(('Base Data'!$D$7)/EP23)=0,0,INT(('Base Data'!$D$7)/EP23)) -> 3 | ER23: =(EN23/Q23) -> 0.0099786751 | ES23: =MAX(U23-V23,ABS(U23-W22),ABS(W22-V23)) -> 55.85 | ET23: =(ES23*X23) -> 7640056.6 | EU23: =((ET23-EU22)*(2/(1+8)))+EU22 -> 8753953.8 | EV23: =((X23-EV22)*(2/(1+8)))+EV22 -> 123410.19 | EW23: =EU23/EV23 -> 70.933803 | EX23: =EW23*$G$4 -> 5320.0352 | EY23: =EX23*'Base Data'!$D$13 -> 3990.0264 | EZ23: =IF(INT(('Base Data'!$D$7)/EY23)=0,0,INT(('Base Data'!$D$7)/EY23)) -> 2 | FA23: =(EW23/W23) -> 0.0077867088 | FB23: 0 | FC23: =(Q23-AVERAGE(BE15:BE22))/EN23 -> 0.52940132 | FD23: 0 | FE23: =(W23-AVERAGE(BM15:BM22))/EW23 -> -0.24209779 | FF23: =(O23-P23) -> 115 | FG23: =FF23/N23 -> 0.0054180752 | FH23: =AVERAGE(FG16:FG23) -> 0.0097631215 | FI23: =AVERAGE(FG11:FG23) -> 0.0094386379 | FJ23: - | FK23: =(U23-V23) -> 38.4 | FL23: =FK23/T23 -> 0.0042220304 | FM23: =AVERAGE(FL16:FL23) -> 0.0059674961 | FN23: =AVERAGE(FL11:FL23) -> 0.0061369927 | FO23: - | FP23: =IF(Q22<((O21+P21+Q21)/3),1,IF(Q22>((O21+P21+Q21)/3),2,0)) -> 1 | FQ23: =IF(W22<((U21+V21+W21)/3),1,IF(W22>((U21+V21+W21)/3),2,0)) -> 1 | FR23: 0 | FS23: - | FT23: 0 | FU23: - | FV23: =ABS(Q23-Q16)/(MAX(O16:O23)-MIN(P16:P23))*100 -> 0.070093458 | FW23: =IF(AND(FV23<30,FV23>FV22),"C-R",IF(AND(FV23<30,FV23=FV22),"C-F",IF(AND(FV23<30,FV23<FV22),"C-D",IF(AND(FV23>=30,FV23>FV22),"T-R",IF(AND(FV23>=30,FV23=FV22),"T-F",IF(AND(FV23>=30,FV23<FV22),"T-D","Check")))))) -> C-D | FX23: =ABS(W23-W16)/(MAX(U16:U23)-MIN(V16:V23))*100 -> 34.994369 | FY23: =IF(AND(FX23<30,FX23>FX22),"C-R",IF(AND(FX23<30,FX23=FX22),"C-F",IF(AND(FX23<30,FX23<FX22),"C-D",IF(AND(FX23>=30,FX23>FX22),"T-R",IF(AND(FX23>=30,FX23=FX22),"T-F",IF(AND(FX23>=30,FX23<FX22),"T-D","Check")))))) -> T-D
A24: =90-A16 -> 7.5 | B24: =A24/180 -> 0.041666667 | C24: =POWER(SQRT($F$11)+B24,2) -> 284.31139 | D24: 1X8 | E24: =$D$11+(C24*B24) -> 25766.896 | F24: =$D$11-(H24*I24) -> 25743.32 | G24: 8X1 | H24: =POWER(SQRT($F$11)-I24,2) -> 281.50808 | I24: =J24/180 -> 0.041666667 | J24: =90-J16 -> 7.5 | L24: =L23+1 -> 21 | M24: ='[4]BANKNIFTY-I'!C40 -> 42823 | N24: ='[4]BANKNIFTY-I'!D40 -> 21277.85 | O24: ='[4]BANKNIFTY-I'!E40 -> 21422.6 | P24: ='[4]BANKNIFTY-I'!F40 -> 21256.65 | Q24: ='[4]BANKNIFTY-I'!G40 -> 21403.3 | R24: ='[4]BANKNIFTY-I'!H40 -> 63945 | S24: ='[5]NIFTY-I'!C40 -> 42823 | T24: ='[5]NIFTY-I'!D40 -> 9140.55 | U24: ='[5]NIFTY-I'!E40 -> 9151.4 | V24: ='[5]NIFTY-I'!F40 -> 9118.8 | W24: ='[5]NIFTY-I'!G40 -> 9142.85 | X24: ='[5]NIFTY-I'!H40 -> 141173 | Z24: =IF(OR(Q23=0,Q24=0),0,LN(Q24/Q23)) -> 0.0078896428 | AA24: =IF(OR(W23=0,W24=0),0,LN(W24/W23)) -> 0.0036433505 | AB24: 0 | AC24: 0 | AD24: =Z25 -> 0.0095809757 | AE24: - | AF24: =AA25 -> 0.0031777606 | AG24: - | AH24: =IF(OR(Q23=0,Q24=0),0,LN(Q24/Q23)) -> 0.0078896428 | AI24: =AJ23 -> 0.0055684513 | AJ24: =SQRT((0.94*(AI24^2))+(0.06*(AH24^2))) -> 0.005734281 | AK24: =AJ24*SQRT(365) -> 0.10955329 | AL24: =IF(OR(W23=0,W24=0),0,LN(W24/W23)) -> 0.0036433505 | AM24: =AN23 -> 0.0048457561 | AN24: =SQRT((0.94*(AM24^2))+(0.06*(AL24^2))) -> 0.004782145 | AO24: =AN24*SQRT(365) -> 0.091362752 | AP24: =IF(P24=0,0,LN(O24/P24)) -> 0.0077766519 | AQ24: =AR23 -> 0.0084796545 | AR24: =SQRT((0.94*(AQ24^2))+(0.06*(AP24^2))) -> 0.008439126 | AS24: =AR24*SQRT(365) -> 0.16122928 | AT24: =IF(V24=0,0,LN(U24/V24)) -> 0.0035686566 | AU24: =AV23 -> 0.0056916812 | AV24: =SQRT((0.94*(AU24^2))+(0.06*(AT24^2))) -> 0.0055870958 | AW24: =AV24*SQRT(365) -> 0.10674132 | AX24: =(N24*R24) -> 1.3606121e+09 | AY24: 0 | AZ24: =(T24*X24) -> 1.2903989e+09 | BA24: 0 | BB24: =((AX24-BB23)*(2/(1+13)))+BB23 -> 1.2903241e+09 | BC24: =((R24-BC23)*(2/(1+13)))+BC23 -> 61302.992 | BD24: =BB24/BC24 -> 21048.305 | BE24: =(O24+P24+Q24)/3 -> 21360.85 | BF24: =(BE24*R24) -> 1.3659196e+09 | BG24: =((BF24-BG23)*(2/(1+5)))+BG23 -> 1.3212382e+09 | BH24: =((R24-BH23)*(2/(1+5)))+BH23 -> 62327.69 | BI24: =BG24/BH24 -> 21198.254 | BJ24: =((AZ24-BJ23)*(2/(1+13)))+BJ23 -> 1.1014226e+09 | BK24: =((X24-BK23)*(2/(1+13)))+BK23 -> 121180.61 | BL24: =BJ24/BK24 -> 9089.0987 | BM24: =(U24+V24+W24)/3 -> 9137.6833 | BN24: =(BM24*X24) -> 1.2899942e+09 | BO24: =((BN24-BO23)*(2/(1+5)))+BO23 -> 1.2158743e+09 | BP24: =((X24-BP23)*(2/(1+5)))+BP23 -> 133443.44 | BQ24: =BO24/BP24 -> 9111.5328 | BR24: =(P24*R24) -> 1.3592565e+09 | BS24: =(O24*R24) -> 1369868157 | BT24: =AVERAGE(AX12:AX24)/AVERAGE(R12:R24) -> 21145.697 | BU24: =AVERAGE(BR20:BR24)/AVERAGE(R20:R24) -> 21039.431 | BV24: =AVERAGE(BS20:BS24)/AVERAGE(R20:R24) -> 21215.852 | BW24: 0 | BX24: =AVERAGE(BR12:BR24)/AVERAGE(R12:R24) -> 21034.757 | BY24: =AVERAGE(BS12:BS24)/AVERAGE(R12:R24) -> 21234.463 | BZ24: =(V24*X24) -> 1.2873284e+09 | CA24: =(U24*X24) -> 1.2919306e+09 | CB24: =AVERAGE(AZ12:AZ24)/AVERAGE(X12:X24) -> 9117.6556 | CC24: =AVERAGE(BZ20:BZ24)/AVERAGE(X20:X24) -> 9077.6965 | CD24: =AVERAGE(CA20:CA24)/AVERAGE(X20:X24) -> 9129.4429 | CE24: 0 | CF24: =AVERAGE(BZ12:BZ24)/AVERAGE(X12:X24) -> 9080.2821 | CG24: =AVERAGE(CA12:CA24)/AVERAGE(X12:X24) -> 9137.3903 | CH24: =((BF24-CH23)*(2/(1+12)))+CH23 -> 1.2892172e+09 | CI24: =((R24-CI23)*(2/(1+12)))+CI23 -> 61146.054 | CJ24: =CH24/CI24 -> 21084.225 | CK24: 0 | CL24: 0 | CM24: 0 | CN24: 0 | CO24: 0 | CP24: 0 | CQ24: =((BN24-CQ23)*(2/(1+12)))+CQ23 -> 1.1099419e+09 | CR24: =((X24-CR23)*(2/(1+12)))+CR23 -> 122121.66 | CS24: =CQ24/CR24 -> 9088.8211 | CV24: 0 | CW24: 0 | CX24: 0 | CY24: 0 | CZ24: =(BE24-BE23) -> 144.15 | DA24: =IF(CZ24>=0,BF24,0) -> 1.3659196e+09 | DB24: =IF(CZ24<0,BF24,0) -> 0 | DC24: =((DA24-DC23)*(2/(1+14)))+DC23 -> 8.6860515e+08 | DD24: =((DB24-DD23)*(2/(1+14)))+DD23 -> 4.5042511e+08 | DE24: =IF(DD24=0,100000,(DC24/DD24)) -> 1.9284119 | DF24: =100-(100/(1+DE24)) -> 65.851798 | DG24: 0 | DH24: 0 | DI24: =(BM24-BM23) -> 31.416667 | DJ24: =IF(DI24>=0,BN24,0) -> 1.2899942e+09 | DK24: =IF(DI24<0,BN24,0) -> 0 | DL24: =((DJ24-DL23)*(2/(1+14)))+DL23 -> 7.1624332e+08 | DM24: =((DK24-DM23)*(2/(1+14)))+DM23 -> 3.9003141e+08 | DN24: =IF(DM24=0,100000,(DL24/DM24)) -> 1.8363734 | DO24: =100-(100/(1+DN24)) -> 64.743712 | DP24: 0 | DQ24: 0 | DR24: =MAX(O24-P24,ABS(O24-Q23),ABS(Q23-P24)) -> 187.5 | DS24: =(DR24*R24) -> 11989688 | DT24: 0 | DU24: 0 | DV24: 0 | DW24: 0 | DX24: 0 | DY24: 0 | DZ24: 0 | EA24: =MAX(U24-V24,ABS(U24-W23),ABS(W23-V24)) -> 41.8 | EB24: =(EA24*X24) -> 5901031.4 | EC24: 0 | ED24: 0 | EE24: 0 | EF24: 0 | EG24: 0 | EH24: 0 | EI24: 0 | EJ24: =MAX(O24-P24,ABS(O24-Q23),ABS(Q23-P24)) -> 187.5 | EK24: =(EJ24*R24) -> 11989688 | EL24: =((EK24-EL23)*(2/(1+8)))+EL23 -> 12682948 | EM24: =((R24-EM23)*(2/(1+8)))+EM23 -> 61490.132 | EN24: =EL24/EM24 -> 206.25989 | EO24: =EN24*$F$4 -> 4125.1979 | EP24: =EO24*'Base Data'!$D$13 -> 3093.8984 | EQ24: =IF(INT(('Base Data'!$D$7)/EP24)=0,0,INT(('Base Data'!$D$7)/EP24)) -> 3 | ER24: =(EN24/Q24) -> 0.0096368268 | ES24: =MAX(U24-V24,ABS(U24-W23),ABS(W23-V24)) -> 41.8 | ET24: =(ES24*X24) -> 5901031.4 | EU24: =((ET24-EU23)*(2/(1+8)))+EU23 -> 8119971 | EV24: =((X24-EV23)*(2/(1+8)))+EV23 -> 127357.48 | EW24: =EU24/EV24 -> 63.757317 | EX24: =EW24*$G$4 -> 4781.7987 | EY24: =EX24*'Base Data'!$D$13 -> 3586.3491 | EZ24: =IF(INT(('Base Data'!$D$7)/EY24)=0,0,INT(('Base Data'!$D$7)/EY24)) -> 2 | FA24: =(EW24/W24) -> 0.006973462 | FB24: 0 | FC24: =(Q24-AVERAGE(BE16:BE23))/EN24 -> 1.4114373 | FD24: 0 | FE24: =(W24-AVERAGE(BM16:BM23))/EW24 -> 0.37678682 | FF24: =(O24-P24) -> 165.95 | FG24: =FF24/N24 -> 0.0077991902 | FH24: =AVERAGE(FG17:FG24) -> 0.0079267672 | FI24: =AVERAGE(FG12:FG24) -> 0.0092377276 | FJ24: =AVERAGE(FG4:FG24) -> 0.0091726181 | FK24: =(U24-V24) -> 32.6 | FL24: =FK24/T24 -> 0.003566525 | FM24: =AVERAGE(FL17:FL24) -> 0.0057681531 | FN24: =AVERAGE(FL12:FL24) -> 0.005849698 | FO24: =AVERAGE(FL4:FL24) -> 0.0064410447 | FP24: =IF(Q23<((O22+P22+Q22)/3),1,IF(Q23>((O22+P22+Q22)/3),2,0)) -> 2 | FQ24: =IF(W23<((U22+V22+W22)/3),1,IF(W23>((U22+V22+W22)/3),2,0)) -> 2 | FR24: =ABS(Q24-Q4)/(MAX(O4:O24)-MIN(P4:P24))*100 -> 60.97221 | FS24: =IF(AND(FR24<30,FR24>FR23),"C-R",IF(AND(FR24<30,FR24=FR23),"C-F",IF(AND(FR24<30,FR24<FR23),"C-D",IF(AND(FR24>=30,FR24>FR23),"T-R",IF(AND(FR24>=30,FR24=FR23),"T-F",IF(AND(FR24>=30,FR24<FR23),"T-D","Check")))))) -> T-R | FT24: =ABS(W24-W4)/(MAX(U4:U24)-MIN(V4:V24))*100 -> 68.646186 | FU24: =IF(AND(FT24<30,FT24>FT23),"C-R",IF(AND(FT24<30,FT24=FT23),"C-F",IF(AND(FT24<30,FT24<FT23),"C-D",IF(AND(FT24>=30,FT24>FT23),"T-R",IF(AND(FT24>=30,FT24=FT23),"T-F",IF(AND(FT24>=30,FT24<FT23),"T-D","Check")))))) -> T-R | FV24: =ABS(Q24-Q17)/(MAX(O17:O24)-MIN(P17:P24))*100 -> 36.785536 | FW24: =IF(AND(FV24<30,FV24>FV23),"C-R",IF(AND(FV24<30,FV24=FV23),"C-F",IF(AND(FV24<30,FV24<FV23),"C-D",IF(AND(FV24>=30,FV24>FV23),"T-R",IF(AND(FV24>=30,FV24=FV23),"T-F",IF(AND(FV24>=30,FV24<FV23),"T-D","Check")))))) -> T-R | FX24: =ABS(W24-W17)/(MAX(U17:U24)-MIN(V17:V24))*100 -> 7.8330893 | FY24: =IF(AND(FX24<30,FX24>FX23),"C-R",IF(AND(FX24<30,FX24=FX23),"C-F",IF(AND(FX24<30,FX24<FX23),"C-D",IF(AND(FX24>=30,FX24>FX23),"T-R",IF(AND(FX24>=30,FX24=FX23),"T-F",IF(AND(FX24>=30,FX24<FX23),"T-D","Check")))))) -> C-D
